Workbook

Sheet PILETAS
A1: ID_PILETA | B1: Capacidad | C1: Lote Pta | D1: Estado | E1: Tipo | F1: Lts_x_cm
A2: 1 | B2: 107500 | E2: EST | F2: 574
A3: 2 | B3: 8400 | C3: da997936 | E3: EST | F3: 43
A4: 3 | B4: 15000 | E4: EST | F4: 78
A5: 4 | B5: 26000 | E5: EST | F5: 127
A6: 5 | B6: 30000 | C6: ebf08055 | E6: EST | F6: 170
A7: 6 | B7: 32000 | C7: a324303d | E7: EST | F7: 170
A8: 7 | B8: 30000 | E8: EST | F8: 170
A9: 8 | B9: 22000 | C9: 376dbee6 | E9: EST | F9: 130
A10: 9 | B10: 30000 | E10: EST | F10: 170
A11: 10 | B11: 21000 | C11: f9bf68a3 | E11: EST | F11: 132
A12: 11 | B12: 36000 | E12: EST | F12: 190
A13: 12 | B13: 35300 | E13: EST | F13: 190
A14: 13 | B14: 20000 | E14: EST | F14: 145
A15: 14 | B15: 37000 | C15: 10b87434 | E15: EST | F15: 201
A16: 15 | B16: 36500 | E16: EST | F16: 197
A17: 16 | B17: 19500 | C17: 869e8a1b | E17: EST | F17: 137
A18: 17 | B18: 39500 | E18: EST | F18: 200
A19: 18 | B19: 39500 | E19: EST | F19: 200
A20: 19 | B20: 27500 | E20: EST | F20: 139
A21: 20 | B21: 38100 | E21: EST | F21: 175
A22: 21 | B22: 28000 | E22: EST | F22: 137
A23: 22 | B23: 41100 | E23: EST | F23: 205
A24: 23 | B24: 197100 | E24: EST | F24: 564
A25: 24 | B25: 186600 | C25: b3a40361 | E25: EST | F25: 550
A26: 25 | B26: 194300 | C26: a2728d01 | E26: EST | F26: 560
A27: 26 | B27: 207600 | C27: a37dae6b | E27: EST | F27: 600
A28: 27 | B28: 207100 | E28: EST | F28: 600
A29: 28 | B29: 216000 | E29: EST | F29: 600
A30: 29 | B30: 20400 | E30: EST | F30: 113
A31: 30 | B31: 38800 | E31: EST | F31: 170
A32: 31 | B32: 25700 | E32: EST | F32: 133
A33: 32 | B33: 36300 | E33: EST | F33: 180
A34: 33 | B34: 25300 | C34: 7def2139 | E34: EST | F34: 138
A35: 34 | B35: 39500 | C35: 08cd1438 | E35: EST | F35: 200
A36: 35 | B36: 39300 | E36: EST | F36: 200
A37: 36 | B37: 19700 | C37: 0997a77d | E37: EST | F37: 120
A38: 37 | B38: 39000 | E38: EST | F38: 200
A39: 38 | B39: 23500 | E39: EST | F39: 130
A40: 39 | B40: 40000 | E40: EST | F40: 200
A41: 40 | B41: 24000 | E41: EST | F41: 130
A42: 41 | B42: 35100 | E42: EST | F42: 181
A43: 42 | B43: 35900 | C43: dccd4f5e | E43: EST | F43: 180
A44: 43 | B44: 17000 | E44: EST | F44: 110
A45: 44 | B45: 19100 | C45: 7ae457f1 | E45: EST | F45: 136
A46: 45 | B46: 30000 | E46: EST | F46: 192
A47: 46 | B47: 29000 | C47: 9b47717c | E47: EST | F47: 160
A48: 47 | B48: 20000 | E48: EST | F48: 133
A49: 48 | B49: 26000 | C49: ef198a97 | E49: EST | F49: 162
A50: 49 | B50: 26000 | E50: EST | F50: 162
A51: 50 | B51: 5100 | C51: 5db7be38 | E51: EST | F51: 29
A52: 51 | B52: 3900 | C52: b7784dc8 | E52: EST | F52: 22
A53: 52 | B53: 27000 | E53: EST | F53: 170
A54: 53 | B54: 22000 | C54: da5fcb21 | E54: EST | F54: 1
A55: 54 | B55: 22900 | C55: 5c87f162 | E55: EST | F55: 143
A56: 55 | B56: 3000 | C56: 2d412906 | E56: EST
A57: 56 | B57: 3000 | E57: EST
A58: 57 | B58: 96800 | E58: EST
A59: 58 | B59: 58400 | E59: EST | F59: 275
A60: 59 | B60: 58200 | E60: EST | F60: 275
A61: 60 | B61: 55000 | E61: EST | F61: 270
A62: 61 | B62: 57100 | E62: EST | F62: 270
A63: 62 | B63: 55000 | E63: EST | F63: 270
A64: 63 | B64: 70300 | E64: EST
A65: 64 | B65: 259600 | E65: EST | F65: 917
A66: 65 | B66: 35500 | C66: 4d3f24b6 | E66: FER | F66: 147
A67: 66 | B67: 23000 | C67: d52c4944 | E67: FER | F67: 90
A68: 67 | B68: 23000 | C68: eb6cce4f | E68: FER | F68: 89
A69: 68 | B69: 13000 | C69: 22a75cd4 | E69: FER | F69: 52
A70: 69 | B70: 13000 | C70: fdb74546 | E70: FER | F70: 52
A71: 70 | B71: 13000 | E71: FER | F71: 52
A72: 71 | B72: 13000 | C72: 7a61df09 | E72: FER | F72: 52
A73: 72 | B73: 13000 | E73: FER | F73: 52
A74: 73 | B74: 13000 | E74: FER | F74: 52
A75: 74 | B75: 13000 | E75: FER | F75: 52
A76: 75 | B76: 7000 | C76: 7a9e7f06 | E76: EST | F76: 46
A77: 76 | B77: 25500 | E77: FER | F77: 90
A78: 77 | B78: 26000 | E78: FER | F78: 90
A79: 78 | B79: 25800 | E79: FER | F79: 90
A80: 79 | B80: 26000 | E80: FER | F80: 90
A81: 80 | B81: 26100 | E81: FER | F81: 91
A82: 81 | B82: 26500 | E82: FER | F82: 93
A83: 82 | B83: 42600 | E83: FER | F83: 175
A84: 83 | B84: 81500 | C84: 32396d27 | E84: FER | F84: 362
A85: 84 | B85: 83000 | C85: 52e2d0ea | E85: FER | F85: 368
A86: 85 | B86: 84000 | C86: dc08aecd | E86: FER | F86: 370
A87: 86 | B87: 88000 | C87: 734aedeb | E87: FER | F87: 395
A88: 87 | B88: 93700 | C88: 502df566 | E88: FER | F88: 418
A89: 88 | B89: 78900 | E89: FER | F89: 408
A90: 89 | B90: 83500 | C90: 6d97827a | E90: FER | F90: 417
A91: 90 | B91: 97500 | C91: 686fc77a | E91: FER | F91: 449
A92: 91 | B92: 86000 | E92: FER | F92: 380
A93: 92 | B93: 76000 | E93: FER | F93: 375
A94: 931 | B94: 11200 | C94: 90fc33de | E94: EST | F94: 54
A95: 935 | B95: 11200 | C95: a774778b | E95: EST | F95: 54
A96: 94 | B96: 11600 | E96: EST | F96: 54
A97: 95 | B97: 77100 | E97: FER | F97: 382
A98: 96 | B98: 85600 | E98: FER | F98: 382
A99: 97 | B99: 299200 | E99: EST | F99: 509
A100: 98 | B100: 254800 | E100: EST | F100: 487
...

Sheet SQL_GENERADO_V2
A1: -- 1. TABLA: Estado_pileta
A3: INSERT INTO Estado_pileta (nombre) VALUES ('ACTIVO');
A5: -- 2. TABLA: Tipo_movimiento
A7: INSERT INTO Tipo_movimiento (nombre) VALUES ('Trasiego');
A8: INSERT INTO Tipo_movimiento (nombre) VALUES ('Ajuste Volumen');
A9: INSERT INTO Tipo_movimiento (nombre) VALUES ('Llenado');
A11: -- 3. TABLA: Variedad
A13: INSERT INTO Variedad (nombre, descripcion) VALUES ('Syrah', NULL);
A14: INSERT INTO Variedad (nombre, descripcion) VALUES ('Malbec', NULL);
A15: INSERT INTO Variedad (nombre, descripcion) VALUES ('Merlot', NULL);
A16: INSERT INTO Variedad (nombre, descripcion) VALUES ('Malbec Syrah', NULL);
A17: INSERT INTO Variedad (nombre, descripcion) VALUES ('Ajuste Volumen', NULL);
... A3201: -- FIN DEL SCRIPT

Sheet CALIFICACION VINO
A1: Calificacion
A2: 1+
A3: 1
A4: 1-
A5: 2+
A6: 2
A7: 2-
A8: 3+
A9: 3
A10: 3-

Sheet Trazado
A1: Pileta a trazar | B1: 83
A2: PILETA
A3: =IFERROR(__xludf.DUMMYFUNCTION("query(PILETAS!A1:D132,""SELECT * WHERE A=""&B1,1)"),"ID_PILETA") -> ID_PILETA | B3: =IFERROR(__xludf.DUMMYFUNCTION("""COMPUTED_VALUE"""),"Capacidad") -> Capacidad | C3: =IFERROR(__xludf.DUMMYFUNCTION("""COMPUTED_VALUE"""),"Lote Pta") -> Lote Pta | D3: =IFERROR(__xludf.DUMMYFUNCTION("""COMPUTED_VALUE"""),"Estado") -> Estado
A4: =IFERROR(__xludf.DUMMYFUNCTION("""COMPUTED_VALUE"""),83.0) -> 83 | B4: =IFERROR(__xludf.DUMMYFUNCTION("""COMPUTED_VALUE"""),81500.0) -> 81500 | C4: =IFERROR(__xludf.DUMMYFUNCTION("""COMPUTED_VALUE"""),"32396d27") -> 32396d27
A6: LOTE
A7: =IFERROR(__xludf.DUMMYFUNCTION("QUERY('PILETAS LOTES'!A1:L1001,""SELECT * WHERE A='""&C4&""'"",1)"),"ID Lote Pileta") -> ID Lote Pileta | B7: =IFERROR(__xludf.DUMMYFUNCTION("""COMPUTED_VALUE"""),"Lotes Origen") -> Lotes Origen | C7: =IFERROR(__xludf.DUMMYFUNCTION("""COMPUTED_VALUE"""),"DateTime") -> DateTime | D7: =IFERROR(__xludf.DUMMYFUNCTION("""COMPUTED_VALUE"""),"Pileta Nro") -> Pileta Nro | E7: =IFERROR(__xludf.DUMMYFUNCTION("""COMPUTED_VALUE"""),"Capacidad") -> Capacidad | F7: =IFERROR(__xludf.DUMMYFUNCTION("""COMPUTED_VALUE"""),"Variedad") -> Variedad | G7: =IFERROR(__xludf.DUMMYFUNCTION("""COMPUTED_VALUE"""),"Cantidad Inicial") -> Cantidad Inicial | H7: =IFERROR(__xludf.DUMMYFUNCTION("""COMPUTED_VALUE"""),"Cantidad Actual") -> Cantidad Actual | I7: =IFERROR(__xludf.DUMMYFUNCTION("""COMPUTED_VALUE"""),"Observaciones Lote") -> Observaciones Lote | J7: =IFERROR(__xludf.DUMMYFUNCTION("""COMPUTED_VALUE"""),"CIU") -> CIU | K7: =IFERROR(__xludf.DUMMYFUNCTION("""COMPUTED_VALUE"""),"Estado") -> Estado | L7: =IFERROR(__xludf.DUMMYFUNCTION("""COMPUTED_VALUE"""),"Califiacion Vino") -> Califiacion Vino
A10: MOVIMIENTOS QUE DIERON ORIGEN A ESTE LOTE
A11: =IFERROR(__xludf.DUMMYFUNCTION("QUERY(MOVIMIENTO!A1:R1001,""SELECT * WHERE L='""&A8&""'"",1)"),"#REF!") -> #REF!
A14: LOTES DE PILETAS QUE FORMAN PARTE DE ESTE MOVIMIENTO
A15: =IFERROR(__xludf.DUMMYFUNCTION("QUERY('PILETAS LOTES'!A1:L1001,""SELECT * WHERE A='""&C12&""' OR A='""&H12&""'"" ,1)"),"ID Lote Pileta") -> ID Lote Pileta | B15: =IFERROR(__xludf.DUMMYFUNCTION("""COMPUTED_VALUE"""),"Lotes Origen") -> Lotes Origen | C15: =IFERROR(__xludf.DUMMYFUNCTION("""COMPUTED_VALUE"""),"DateTime") -> DateTime | D15: =IFERROR(__xludf.DUMMYFUNCTION("""COMPUTED_VALUE"""),"Pileta Nro") -> Pileta Nro | E15: =IFERROR(__xludf.DUMMYFUNCTION("""COMPUTED_VALUE"""),"Capacidad") -> Capacidad | F15: =IFERROR(__xludf.DUMMYFUNCTION("""COMPUTED_VALUE"""),"Variedad") -> Variedad | G15: =IFERROR(__xludf.DUMMYFUNCTION("""COMPUTED_VALUE"""),"Cantidad Inicial") -> Cantidad Inicial | H15: =IFERROR(__xludf.DUMMYFUNCTION("""COMPUTED_VALUE"""),"Cantidad Actual") -> Cantidad Actual | I15: =IFERROR(__xludf.DUMMYFUNCTION("""COMPUTED_VALUE"""),"Observaciones Lote") -> Observaciones Lote | J15: =IFERROR(__xludf.DUMMYFUNCTION("""COMPUTED_VALUE"""),"CIU") -> CIU | K15: =IFERROR(__xludf.DUMMYFUNCTION("""COMPUTED_VALUE"""),"Estado") -> Estado | L15: =IFERROR(__xludf.DUMMYFUNCTION("""COMPUTED_VALUE"""),"Califiacion Vino") -> Califiacion Vino

Sheet PILETAS LOTES
A1: ID Lote Pileta | B1: Lotes Origen | C1: DateTime | D1: Pileta Nro | E1: Capacidad | F1: Variedad | G1: Cantidad Inicial | H1: Cantidad Actual | I1: Observaciones Lote | J1: CIU | K1: Estado | L1: Califiacion Vino | M1: Color
A2: 04b35bd0 | C2: 45703 | D2: 2 | E2: 12500 | F2: Syrah | G2: 12500 | H2: 12500 | M2: Tinto
A3: 51d6bbdd | C3: 45703 | D3: 3 | E3: 14000 | F3: Malbec | H3: 14000
A4: 6cde19b3 | C4: 45703 | D4: 6 | E4: 69750 | F4: Merlot | H4: 69750
A5: 348ea8a7 | B5: 04b35bd0 | C5: 45703 | D5: 7 | E5: 85000 | F5: Syrah | H5: 12500
A6: 8c336568 | B6: 51d6bbdd, 348ea8a7 | C6: 45703 | D6: 7 | E6: 85000 | F6: Malbec Syrah | G6: 12500 | H6: 26500
A7: a1c20159 | B7: 8c336568 | C7: 45704 | D7: 5 | E7: 52000 | F7: Malbec Syrah | G7: 0 | H7: 26500
A8: c63f7bed | B8: a1c20159 | C8: 45704.938 | D8: 79 | E8: 26000 | F8: Malbec Syrah | G8: 0 | H8: 26000
A9: d13652cf | B9: 6cde19b3 | C9: 45704.947 | D9: 30 | E9: 38800 | F9: Merlot | G9: 0 | H9: 37750
A10: b27a5ea7 | C10: 45704.951 | D10: 1 | E10: 107500 | F10: Ajuste Volumen | H10: 107500
A11: 58b123c6 | B11: 6cde19b3 | C11: 45704.967 | D11: 11 | E11: 36000 | F11: Merlot | G11: 0 | H11: 32000
A12: 53f98d96 | B12: a1c20159, 58b123c6 | C12: 45704.969 | D12: 11 | E12: 36000 | F12: Merlot | G12: 32000 | H12: 32500
A13: ce475c91 | B13: b27a5ea7, d13652cf | C13: 45704.97 | D13: 30 | E13: 38800 | F13: Ajuste Volumen | G13: 37750 | H13: 37800
A14: cedc0dc0 | C14: 45705.533 | D14: 77 | E14: 26000 | F14: Chardonnay | H14: 25000 | K14: Fermentando
A15: 868560b2 | C15: 45705.534 | D15: 80 | E15: 26100 | F15: Aspirant Ferm 25 | H15: 12000 | J15: 5765 , 5766
A16: 5eb33d17 | C16: 45705.534 | D16: 81 | E16: 26500 | F16: Syrah Ferm 25 | H16: 8000 | J16: 5790
A17: 7c1795fa | C17: 45705.535 | D17: 82 | E17: 42600 | F17: Merlot Ferm 25 | H17: 20000 | J17: 5780 , 5782 , 5783
A18: 7366c02e | C18: 45705.535 | D18: 65 | E18: 35500 | F18: Merlot Ferm 25 | H18: 15000 | J18: 5784 , 5785 , 5786 , 5788
A19: 0632409f | C19: 45705.535 | D19: 83 | E19: 81500 | F19: Malbec Ferm 25 | H19: 30000 | J19: 5770 , 5772 , 5774 , 5775 , 5777 , 5778
A20: 24b66da0 | C20: 45705.536 | D20: 84 | E20: 83000 | F20: Aspirant Ferm 25 | H20: 30000 | J20: 5761 , 5762 , 5763 , 5764
A21: e323890c | C21: 45705.536 | D21: 85 | E21: 84000 | F21: Aspirant Anccelota Ferm | H21: 40000 | J21: 5767 , 5768 , 5769 , 5771 , 5773 , 5776 , 5779 , 5781
A23: c76dfce1 | C23: 45691.827 | D23: 86 | E23: 88000 | F23: Aspirant | H23: 42000 | J23: 5760 , 5756 , 5757 , 5758 , 5759
A24: f6f9d651 | C24: 45708.712 | D24: 88 | E24: 78900 | F24: Merlot | H24: 28000 | J24: 5792 , 5796 , 5797 , 5800
A25: 0835b42b | B25: c76dfce1 | C25: 45708.716 | D25: 102 | E25: 31000 | F25: Aspirant | G25: 0 | H25: 30000 | I25: Vino al c9rte de la vendimia | K25: Descubada
A26: 903e1ab8 | B26: 24b66da0 | C26: 45708.725 | D26: 103 | E26: 31000 | F26: Aspirant | G26: 0 | H26: 15000
A27: 65eb8fac | B27: 5eb33d17, c76dfce1 | C27: 45708.743 | D27: 86 | E27: 88000 | F27: Syrah s/Asp | G27: 12000 | H27: 20000
A28: 13b5f72f | B28: 7c1795fa, 65eb8fac | C28: 45708.748 | D28: 86 | E28: 88000 | F28: Syrah Merlot s/Asp | G28: 20000 | H28: 40000
A29: 3c569c0a | B29: 7366c02e, 24b66da0 | C29: 45708.751 | D29: 84 | E29: 83000 | F29: Merlot s/Asp | G29: 15000 | H29: 30000
A30: d7af693c | B30: 0632409f | C30: 45708.752 | D30: 104 | E30: 31000 | F30: Malbec Gota | G30: 0 | H30: 29000 | K30: Descubada
A31: 1749cd27 | B31: 0632409f | C31: 45708.754 | D31: 105 | E31: 31000 | F31: Malbec Prensa | G31: 0 | H31: 5000
A32: 5008e5a3 | C32: 45708.794 | D32: 11 | E32: 36000 | F32: Cabernet Sauv Rect | H32: 36000 | K32: Rectificado
A33: 27abb7ee | C33: 45708.794 | D33: 16 | E33: 19500 | F33: Cabernet Sauvignon Rect | H33: 19500 | K33: Rectificado
A34: eec28962 | C34: 45708.795 | D34: 30 | E34: 38800 | F34: Aspirant 24 | H34: 38800 | K34: Terminado | M34: Tinto
A35: 30d0ce51 | C35: 45708.795 | D35: 41 | E35: 35100 | F35: Cabernet Sauvignon Rect 24 | H35: 35100 | K35: Rectificado
A36: 73b50dc4 | C36: 45708.797 | D36: 42 | E36: 35900 | F36: Malbec 24 | H36: 35900 | K36: Terminado
A37: d5c7ee63 | C37: 45708.798 | D37: 44 | E37: 19100 | F37: Cabernet Sauvignon Rect 24 | H37: 19100 | K37: Rectificado
A38: 241b642a | C38: 45708.799 | D38: 45 | E38: 30000 | F38: Bonarda 24 Rect | H38: 30000 | K38: Rectificado
A39: 665bbad3 | C39: 45708.799 | D39: 47 | E39: 20000 | F39: Cabernet Sauvignon 24 Rect | H39: 20000 | K39: Rectificado
A40: d9821c78 | C40: 45708.799 | D40: 48 | E40: 26000 | F40: Bonarda 24 Rect | H40: 26000 | K40: Rectificado
A41: a9ae339e | C41: 45708.799 | D41: 49 | E41: 26000 | F41: Bonarda 24 Rect | H41: 26000 | K41: Rectificado
A42: 6ee897e9 | C42: 45708.8 | D42: 50 | E42: 5100 | F42: Tinto 24 Rect | H42: 5100 | K42: Rectificado
A43: fe114136 | C43: 45708.8 | D43: 67 | E43: 23000 | F43: Malbec 24 | H43: 23000 | K43: Terminado
A44: c4f0d9b2 | C44: 45708.804 | D44: 74 | E44: 13000 | F44: Malbec 24 | H44: 13000 | K44: Terminado
A45: f1388e78 | C45: 45708.804 | D45: 75 | E45: 7000 | F45: Aspirant 24 Rect | H45: 7000 | K45: Rectificado
A46: 904bbb40 | C46: 45708.804 | D46: 90 | E46: 97500 | F46: Syrah 24 | H46: 97500 | K46: Terminado
... A48: b336cfcb | C48: 45708.805 | D48: 94 | E48: 11600 | F48: Syrah 24 | H48: 11600 | K48: Terminado
A49: 6a04e7d6 | C49: 45708.805 | D49: 111 | E49: 4000 | F49: Malbec Magneta | H49: 4000 | I49: 20/3 Degustación. Muy bien | K49: Terminado
A50: b502a55e | C50: 45708.805 | D50: 114 | E50: 125300 | F50: Bonarda 24 | H50: 125300 | K50: Terminado
A51: 4368dec6 | C51: 45708.805 | D51: 118 | E51: 155600 | F51: Malbec 24 | H51: 155600 | K51: Terminado
A52: b9e5067b | C52: 45708.807 | D52: 15 | E52: 36500 | F52: Cabernet Sauvignon 24 Rect | H52: 20000
A53: bd4decc8 | C53: 45708.809 | D53: 46 | E53: 29000 | F53: Cabernet Sauvignon 24 Rect | H53: 29000 | K53: Rectificado
A54: 26b37af9 | C54: 45708.811 | D54: 52 | E54: 27000 | F54: Chardonnay 24 Rect | H54: 27000 | K54: Rectificado
A55: 4a5cb789 | C55: 45708.811 | D55: 54 | E55: 22900 | F55: Chardonnay 24 Rect | H55: 22900 | K55: Rectificado
A56: e3903041 | C56: 45708.8 | D56: 89 | E56: 83500 | F56: Syrah Colombo | H56: 36000 | I56: Polilla | J56: 5852 , 5854 , 5855 , 5859 , 5865 , 5869
A57: 977cb5a1 | C57: 45709.802 | D57: 92 | E57: 76000 | F57: Syrah Tempranillo | H57: 39700 | J57: 5856 , 5857 , 5861 , 5863 , 5866 , 5867
A58: d6272af5 | B58: f6f9d651, 868560b2 | C58: 45709.835 | D58: 80 | E58: 26100 | F58: Merlot s/ Asp | G58: 12000 | H58: 22000 | K58: Fermentando
A59: 0aa8c362 | B59: e323890c | C59: 45709.837 | D59: 107 | E59: 31000 | F59: Aspirant Anccelota Gota | G59: 0 | H59: 30000 | K59: Descubada
A60: f8624f14 | B60: f6f9d651, e323890c | C60: 45709.838 | D60: 85 | E60: 84000 | F60: Merlot s/Asp | G60: 10000 | H60: 28000 | K60: Fermentando
A61: c3f4cae7 | C61: 45710.488 | D61: 82 | E61: 42600 | F61: Chardonnay | H61: 28000 | J61: 5868 , 5873 , 5864 , 5872 , 5780 , 5782 , 5783 | K61: Fermentando
A62: a1e13111 | C62: 45712.469 | D62: 32 | E62: 36300 | F62: Chardonnay (Filtra) | H62: 36300 | I62: 14/5 Fresco, rico | K62: Descubada | L62: 1 | M62: Blanco
A63: 7def2139 | C63: 45712.469 | D63: 33 | E63: 25300 | F63: Chardonnay | H63: 25300 | I63: 14/5 .bien comercial | K63: Descubada | L63: 1- | M63: Blanco
A64: 8a7074cf | C64: 45712.469 | D64: 31 | E64: 25700 | F64: Chardonnay | H64: 25700 | I64: 14/5 simple, para una base | K64: Descubada
A65: 7c5390c8 | C65: 45712.47 | D65: 40 | E65: 24000 | F65: Chardonnay | H65: 24000 | I65: 14/5 muy rico | K65: Descubada | L65: 1 | M65: Blanco
A66: 861200f5 | C66: 45712.471 | D66: 81 | E66: 26500 | F66: Chardonnay | H66: 24000 | K66: Fermentando
A67: 7e515c96 | C67: 45712.472 | D67: 78 | E67: 25800 | F67: Chardonnay | H67: 24000 | K67: Fermentando
A68: dae2c109 | C68: 45712.472 | D68: 79 | E68: 26000 | F68: Chardonnay | H68: 24000 | K68: Fermentando
A69: a43178d5 | B69: 13b5f72f, 1749cd27 | C69: 45713.528 | D69: 105 | E69: 31000 | F69: Syrah Merlot s/Asp gota | G69: 5000 | H69: 30000
A70: a1ad6cb4 | B70: 13b5f72f, | C70: 45713.54 | D70: 108 | E70: 31000 | F70: Syrah Merlot s/Asp Gota | G70: 0 | H70: 7500 | K70: Descubada
A71: 3b2a1e70 | B71: 977cb5a1, 13b5f72f | C71: 45713.542 | D71: 86 | E71: 88000 | F71: Syrah Tempranillo s/Asp 2da | G71: 7500 | H71: 47200 | I71: Prueba offline | K71: Fermentando
A72: d177809a | C72: 45713.542 | D72: 83 | E72: 81500 | F72: Syrah | H72: 35800 | J72: 5871 , 5870 , 5874 , 5875 | K72: Fermentando
A73: 8b03a986 | C73: 45713.544 | D73: 88 | E73: 78900 | F73: Syrah | H73: 37400 | J73: 5878 , 5877 , 5876 , 5879 , 5880 | K73: Fermentando
A74: 00e2c403 | C74: 45713.709 | D74: 59 | E74: 58200 | F74: prueba 1 | H74: 10000
A75: cff5f914 | C75: 45713.709 | D75: 60 | E75: 55000 | F75: Prueva 2 Variedad | G75: 12000 | H75: 55000
A76: fa54e834 | B76: cff5f914, 00e2c403 | C76: 45713.712 | D76: 59 | E76: 58200 | F76: Prueva 2 Variedad | G76: 10000 | H76: 18000
A77: 24faf549 | B77: cff5f914, fa54e834 | C77: 45713.72 | D77: 59 | E77: 58200 | F77: Prueva 2 Variedad | G77: 18000 | H77: 25000
A78: 57a0fadf | B78: cff5f914, 24faf549 | C78: 45713.723 | D78: 59 | E78: 58200 | F78: Prueva 2 Variedad | G78: 25000 | H78: 35000
A79: e2c70b60 | B79: 57a0fadf, cff5f914 | C79: 45713.739 | D79: 60 | E79: 55000 | F79: Prueva 2 Variedad | G79: 20000 | H79: 25000
A80: 5e86e265 | C80: 45713.741 | D80: 60 | E80: 55000 | F80: Prueva 2 Variedad | G80: 25000 | H80: 28000
A81: c1d665de | C81: 45713.749 | D81: 60 | E81: 55000 | F81: Prueva 2 Variedad | G81: 28000 | H81: 29500
A82: eeeff983 | C82: 45713.774 | D82: 400 | E82: 200000 | F82: Cabernet Sauvignon 24 Rect | G82: 0 | H82: 20000
A83: b9edcc33 | C83: 45713.778 | D83: 51 | E83: 3900 | F83: Cabernet Sauv Despacho Bodega | H83: 2500 | K83: Terminado
A84: ae4bc1ac | C84: 45713.779 | D84: 400 | E84: 200000 | F84: Chardonnay 24 Rect | G84: 20000 | H84: 30000
A85: a22cb4a2 | C85: 45713.794 | D85: 103 | E85: 31000 | F85: Aspirat | G85: 15000 | H85: 30000 | K85: Descubada
A86: 0b7fd98e | C86: 45713.797 | D86: 400 | E86: 200000 | F86: Syrah Merlot s/Asp gota | G86: 30000 | H86: 46000
A87: 7ad5b1b2 | C87: 45713.799 | D87: 105 | E87: 31000 | F87: Malbec con Merlot s/Asp | G87: 14000 | H87: 30000 | K87: Descubada
A88: 00bdd4ad | C88: 45713.799 | D88: 106 | E88: 11000 | F88: Merlot s/Asp | G88: 0 | H88: 11000 | K88: Descubada
A89: 3e5c0749 | C89: 45713.81 | D89: 92 | E89: 76000 | F89: Syrah Ferm | H89: 35900 | J89: 5881 , 5882 , 5883 , 5884 , 5885 | K89: Fermentando
A90: 7082548e | C90: 45714.411 | D90: 84 | E90: 83000 | F90: Syrah Colom s/Asp 2 | G90: 3000 | H90: 39000 | K90: Fermentando
A91: f3ebcf34 | C91: 45714.412 | D91: 87 | E91: 93700 | F91: Merlot Fer | G91: 16500 | H91: 38200 | J91: 5886 , 5887 , 5888 , 5889 , 5890 , 5891 | K91: Fermentando
A92: 9776a719 | C92: 45715.41 | D92: 109 | E92: 15600 | F92: Merlot s/ Asp descube | G92: 0 | H92: 4000
A93: d6ff9a07 | C93: 45715.411 | D93: 109 | E93: 15600 | F93: Merlot s/Asp descube | G93: 4000 | H93: 24000 | I93: Muy bueno | K93: Descubada
A94: 8c09a554 | C94: 45715.411 | D94: 110 | E94: 15600 | F94: Merlot s/Asp descube | G94: 0 | H94: 3000 | K94: Descubada
A95: 7525cd32 | C95: 45715.412 | D95: 80 | E95: 26100 | F95: Syrah s/Asp 2da | G95: 3000 | H95: 13000 | K95: Recarga Fermentando
A96: 245cd9d6 | C96: 45715.413 | D96: 85 | E96: 84000 | F96: Syrah s/Asp 2da | G96: 5000 | H96: 30800 | I96: Tiene Prensa con un amargo | K96: Fermentando
A97: 13d1574d | C97: 45715.766 | D97: 110 | E97: 15600 | F97: Merlot s/Asp descube | G97: 3000 | H97: 13000 | K97: Descubada
A98: 9adbf19e | C98: 45715.792 | D98: 88 | E98: 78900 | F98: Syrah | G98: 37400 | H98: 42100 | I98: 16% de Rectificado agregado | K98: Fermentando
A99: b45049fe | C99: 45715.842 | D99: 83 | E99: 81500 | F99: Syrah | H99: 45000 | J99: 5895 , 5892 , 5896 , 5897 , 5899 , 5900 | K99: Fermentando
A100: e95eaf53 | C100: 45715.843 | D100: 65 | E100: 35500 | F100: Anccelotta | H100: 20500 | J100: 5894 , 5893 , 5898 | K100: Fermentando
A101: 4adbcbaf | C101: 45716.834 | D101: 68 | E101: 13000 | F101: Syrah | H101: 7400 | I101: Tiene medio viaje del ciu 5899 (cornejo) | J101: 5901 | K101: Fermentando
A102: bf5594db | C102: 45717.517 | D102: 15 | E102: 36500 | F102: Syrah Tempranillo s/Asp 2da | G102: 0 | H102: 36500 | K102: Descubada
...

Sheet MOVIMIENTO
A1: ID_Movimiento | B1: Date_Time | C1: Lote Origen | D1: Pileta Origen | E1: Variedad Origen | F1: Volumen Trasegado | G1: Pileta Destino | H1: Lote Destino Original | I1: Variedad Destino Original | J1: Volumen Destino Original | K1: Volumen Destino Final | L1: Lote Destino Final | M1: Variedad Destino Final | N1: Observaciones Movimiento | O1: Pileta Origen Estado | P1: Pileta Destino Estado | Q1: Copiar Estado Destino | R1: Pileta Destino Final Estado | S1: Calificacion Origen | T1: Calificacion Destino | U1: Calificacion Destino Final
A2: de764408 | B2: 45703.876 | C2: 04b35bd0 | D2: 2 | E2: Syrah | F2: 12500 | G2: 7 | K2: 12500 | L2: 348ea8a7 | M2: Syrah
A3: 6596058d | B3: 45703.876 | C3: 51d6bbdd | D3: 3 | E3: Malbec | F3: 14000 | G3: 7 | H3: 348ea8a7 | I3: Syrah | J3: 12500 | K3: 26500 | L3: 8c336568 | M3: Malbec Syrah
A4: ea75ff40 | B4: 45704.903 | C4: 8c336568 | D4: 7 | E4: Malbec Syrah | F4: 26500 | G4: 5 | J4: 0 | K4: 26500 | L4: a1c20159 | M4: Malbec Syrah
A5: 12e4e13b | B5: 45704.937 | C5: a1c20159 | D5: 5 | E5: Malbec Syrah | F5: 26000 | G5: 79 | J5: 0 | K5: 26000 | L5: c63f7bed | M5: Malbec Syrah
A6: 14c84b1e | B6: 45704.946 | C6: 6cde19b3 | D6: 6 | E6: Merlot | F6: 37750 | G6: 30 | J6: 0 | K6: 37750 | L6: d13652cf | M6: Merlot
A8: db9bd61e | B8: 45704.967 | C8: 6cde19b3 | D8: 6 | E8: Merlot | F8: 32000 | G8: 11 | J8: 0 | K8: 32000 | L8: 58b123c6 | M8: Merlot
A9: 405705de | B9: 45704.968 | C9: a1c20159 | D9: 5 | E9: Malbec Syrah | F9: 500 | G9: 11 | H9: 58b123c6 | I9: Merlot | J9: 32000 | K9: 32500 | L9: 53f98d96 | M9: Merlot
A10: 345b4c91 | B10: 45704.97 | C10: b27a5ea7 | D10: 1 | E10: Ajuste Volumen | F10: 50 | G10: 30 | H10: d13652cf | I10: Merlot | J10: 37750 | K10: 37800 | L10: ce475c91 | M10: Ajuste Volumen
A11: cdf62189 | B11: 45708.714 | C11: c76dfce1 | D11: 86 | E11: Aspirant | F11: 30000 | G11: 102 | J11: 0 | K11: 30000 | L11: 0835b42b | M11: Aspirant | N11: Descube
A12: 14a9777e | B12: 45708.725 | C12: 24b66da0 | D12: 84 | E12: Aspirant Ferm 25 | F12: 15000 | G12: 103 | J12: 0 | K12: 15000 | L12: 903e1ab8 | M12: Aspirant | N12: Descube Gota
A13: ee927519 | B13: 45708.741 | C13: 5eb33d17 | D13: 81 | E13: Syrah Ferm 25 | F13: 8000 | G13: 86 | H13: c76dfce1 | I13: Aspirant | J13: 12000 | K13: 20000 | L13: 65eb8fac | M13: Syrah s/Asp | N13: Descube gota y prensa a Aspirant
A14: 6f1c07ae | B14: 45708.747 | C14: 7c1795fa | D14: 82 | E14: Merlot Ferm 25 | F14: 20000 | G14: 86 | H14: 65eb8fac | I14: Syrah s/Asp | J14: 20000 | K14: 40000 | L14: 13b5f72f | M14: Syrah Merlot s/Asp | N14: Descube gota y prensa
A15: 662b2483 | B15: 45708.75 | C15: 7366c02e | D15: 65 | E15: Merlot Ferm 25 | F15: 15000 | G15: 84 | H15: 24b66da0 | I15: Aspirant Ferm 25 | J15: 15000 | K15: 30000 | L15: 3c569c0a | M15: Merlot s/Asp | N15: Descube Gota y prensa sobre Aspirant
A16: 9f189d7d | B16: 45708.752 | C16: 0632409f | D16: 83 | E16: Malbec Ferm 25 | F16: 25000 | G16: 104 | J16: 0 | K16: 29000 | L16: d7af693c | M16: Malbec Gota | N16: Descube Gota
A17: cfa35761 | B17: 45708.753 | C17: 0632409f | D17: 83 | E17: Malbec Ferm 25 | F17: 5000 | G17: 105 | J17: 0 | K17: 5000 | L17: 1749cd27 | M17: Malbec Prensa | N17: Malbec descubado a prensa
A18: 968706bd | B18: 45709.814 | C18: f6f9d651 | D18: 88 | E18: Merlot | F18: 10000 | G18: 80 | H18: 868560b2 | I18: Aspirant Ferm 25 | J18: 12000 | K18: 22000 | L18: d6272af5 | M18: Merlot s/ Asp
A19: 8dbab148 | B19: 45709.836 | C19: e323890c | D19: 85 | E19: Aspirant Anccelota Ferm | F19: 30000 | G19: 107 | J19: 0 | K19: 30000 | L19: 0aa8c362 | M19: Aspirant Anccelota Gota | N19: Sin prensar pileta origen para recargar
A20: 7039bd57 | B20: 45709.837 | C20: f6f9d651 | D20: 88 | E20: Merlot | F20: 18000 | G20: 85 | H20: e323890c | I20: Aspirant Anccelota Ferm | J20: 10000 | K20: 28000 | L20: f8624f14 | M20: Merlot s/Asp | N20: Gota y Prensa sobre Aspirant
A21: 22cfff5c | B21: 45713.523 | C21: 13b5f72f | D21: 86 | E21: Syrah Merlot s/Asp | F21: 25000 | G21: 105 | H21: 1749cd27 | I21: Malbec Prensa | J21: 5000 | K21: 30000 | L21: a43178d5 | M21: Syrah Merlot s/Asp gota | N21: Descube Gota
A22: 1ee5f0af | B22: 45713.537 | C22: 13b5f72f | D22: 86 | E22: Syrah Merlot s/Asp | F22: 7500 | G22: 108 | J22: 0 | K22: 7500 | L22: a1ad6cb4 | M22: Syrah Merlot s/Asp Gota
A23: 9eab323a | B23: 45713.541 | C23: 977cb5a1 | D23: 92 | E23: Syrah Tempranillo | F23: 39700 | G23: 86 | H23: 13b5f72f | I23: Syrah Merlot s/Asp | J23: 7500 | K23: 47200 | L23: 3b2a1e70 | M23: Syrah Tempranillo s/Asp 2da | N23: Gota y Prensa sobre orujos Aspiran 2da pasada
A24: 57f7f4a6 | B24: 45713.71 | C24: cff5f914 | D24: 60 | E24: Prueva 2 Variedad | F24: 8000 | G24: 59 | H24: 00e2c403 | I24: prueba 1 | J24: 10000 | K24: 18000 | L24: fa54e834 | M24: Prueva 2 Variedad
A25: 96b203c8 | B25: 45713.713 | C25: cff5f914 | D25: 60 | E25: Prueva 2 Variedad | F25: 7000 | G25: 59 | H25: fa54e834 | I25: Prueva 2 Variedad | J25: 18000 | K25: 25000 | L25: 24faf549 | M25: Prueva 2 Variedad
A26: a78ab6e7 | B26: 45713.722 | C26: cff5f914 | D26: 60 | E26: Prueva 2 Variedad | F26: 10000 | G26: 59 | H26: 24faf549 | I26: Prueva 2 Variedad | J26: 25000 | K26: 35000 | L26: 57a0fadf | M26: Prueva 2 Variedad
A27: b92404cd | B27: 45713.723 | C27: cff5f914 | D27: 60 | E27: Prueva 2 Variedad | F27: 10000 | G27: 59 | H27: 57a0fadf | I27: Prueva 2 Variedad | J27: 35000 | K27: 45000 | L27: c980cfc2 | M27: Prueva 2 Variedad
A28: ee34047e | B28: 45713.738 | C28: 57a0fadf | D28: 59 | E28: Prueva 2 Variedad | F28: 5000 | G28: 60 | H28: cff5f914 | I28: Prueva 2 Variedad | J28: 20000 | K28: 25000 | L28: e2c70b60 | M28: Prueva 2 Variedad
A29: fe7eff9f | B29: 45713.739 | C29: 57a0fadf | D29: 59 | E29: Prueva 2 Variedad | F29: 3000 | G29: 60 | H29: e2c70b60 | I29: Prueva 2 Variedad | J29: 25000 | K29: 28000 | L29: 5e86e265 | M29: Prueva 2 Variedad
A30: ec72ee89 | B30: 45713.748 | C30: 57a0fadf | D30: 59 | E30: Prueva 2 Variedad | F30: 1500 | G30: 60 | H30: 5e86e265 | I30: Prueva 2 Variedad | J30: 28000 | K30: 29500 | L30: c1d665de | M30: Prueva 2 Variedad
A31: 9e8d0f39 | B31: 45713.773 | C31: b9e5067b | D31: 15 | E31: Cabernet Sauvignon 24 Rect | F31: 20000 | G31: 400 | I31: Vino Re | J31: 0 | K31: 20000 | L31: eeeff983 | M31: Cabernet Sauvignon 24 Rect | N31: Vino rectificado utilizado
A32: 7b4bffff | B32: 45713.779 | C32: 26b37af9 | D32: 52 | E32: Chardonnay 24 Rect | F32: 10000 | G32: 400 | H32: eeeff983 | I32: Cabernet Sauvignon 24 Rect | J32: 20000 | K32: 30000 | L32: ae4bc1ac | M32: Chardonnay 24 Rect | N32: Rectificado utilizado
A33: 490375eb | B33: 45713.794 | C33: d6272af5 | D33: 80 | E33: Merlot s/ Asp | F33: 15000 | G33: 103 | H33: 903e1ab8 | I33: Aspirant | J33: 15000 | K33: 30000 | L33: a22cb4a2 | M33: Merlot s/ Asp
A34: e1980736 | B34: 45713.797 | C34: a43178d5 | D34: 105 | E34: Syrah Merlot s/Asp gota | F34: 16000 | G34: 400 | H34: ae4bc1ac | I34: Chardonnay 24 Rect | J34: 30000 | K34: 46000 | L34: 0b7fd98e | M34: Syrah Merlot s/Asp gota | N34: Ajuste Volumen
A35: 2d753a75 | B35: 45713.798 | C35: 3c569c0a | D35: 84 | E35: Merlot s/Asp | F35: 16000 | G35: 105 | H35: a43178d5 | I35: Syrah Merlot s/Asp gota | J35: 14000 | K35: 30000 | L35: 7ad5b1b2 | M35: Malbec con Merlot s/Asp
A36: da96250f | B36: 45713.799 | C36: 3c569c0a | D36: 84 | E36: Merlot s/Asp | F36: 11000 | G36: 106 | J36: 0 | K36: 11000 | L36: 00bdd4ad | M36: Merlot s/Asp
A37: c98d4615 | B37: 45714.411 | C37: e3903041 | D37: 89 | E37: Syrah Colombo | F37: 36000 | G37: 84 | H37: 3c569c0a | I37: Merlot s/Asp | J37: 3000 | K37: 39000 | L37: 7082548e | M37: Syrah Colom s/Asp 2 | N37: Gota y Prensa sobre Aspiran 2da pasada
A38: 277c1553 | B38: 45715.409 | C38: d6272af5 | D38: 80 | E38: Merlot s/ Asp | F38: 4000 | G38: 109 | J38: 0 | K38: 4000 | L38: 9776a719 | M38: Merlot s/ Asp descube
A39: 150bb873 | B39: 45715.41 | C39: f8624f14 | D39: 85 | E39: Merlot s/Asp | F39: 20000 | G39: 109 | H39: 9776a719 | I39: Merlot s/ Asp descube | J39: 4000 | K39: 24000 | L39: d6ff9a07 | M39: Merlot s/Asp descube
A40: 828ab6d5 | B40: 45715.411 | C40: f8624f14 | D40: 85 | E40: Merlot s/Asp | F40: 3000 | G40: 110 | J40: 0 | K40: 3000 | L40: 8c09a554 | M40: Merlot s/Asp descube | N40: Gota
A41: 7463f544 | B41: 45715.412 | C41: d177809a | D41: 83 | E41: Syrah | F41: 10000 | G41: 80 | H41: d6272af5 | I41: Merlot s/ Asp | J41: 3000 | K41: 13000 | L41: 7525cd32 | M41: Syrah s/Asp 2da | N41: Gota
A42: 01f1dc38 | B42: 45715.413 | C42: d177809a | D42: 83 | E42: Syrah | F42: 25800 | G42: 85 | H42: f8624f14 | I42: Merlot s/Asp | J42: 5000 | K42: 30800 | L42: 245cd9d6 | M42: Syrah s/Asp 2da | N42: Gota y prensa recarga
A43: 43efe779 | B43: 45715.765 | C43: d6ff9a07 | D43: 109 | E43: Merlot s/Asp descube | F43: 10000 | G43: 110 | H43: 8c09a554 | I43: Merlot s/Asp descube | J43: 3000 | K43: 13000 | L43: 13d1574d | M43: Merlot s/Asp descube | N43: Envie volumen de mas a la 109 y lo estoy trasegando a la 110
A44: 41500743 | B44: 45715.792 | C44: 5008e5a3 | D44: 11 | E44: Cabernet Sauv Rect | F44: 4700 | G44: 88 | H44: 8b03a986 | I44: Syrah | J44: 37400 | K44: 42100 | L44: 9adbf19e | M44: Syrah | N44: agregado de Rectificado al Syrah
A45: 516d898a | B45: 45717.516 | C45: 3b2a1e70 | D45: 86 | E45: Syrah Tempranillo s/Asp 2da | F45: 36000 | G45: 15 | J45: 0 | K45: 36000 | L45: bf5594db | M45: Syrah Tempranillo s/Asp 2da
A46: d15b7359 | B46: 45717.523 | C46: 3b2a1e70 | D46: 86 | E46: Syrah Tempranillo s/Asp 2da | F46: 5000 | G46: 34 | J46: 0 | K46: 5000 | L46: fea4a82d | M46: Syrah Tempranillo s/Asp 2da
A47: c02698f9 | B47: 45717.523 | C47: 245cd9d6 | D47: 85 | E47: Syrah s/Asp 2da | F47: 25000 | G47: 34 | H47: fea4a82d | I47: Syrah Tempranillo s/Asp 2da | J47: 5000 | K47: 30000 | L47: 61098b0e | M47: Syrah s/Asp 2da
A48: d7db7220 | B48: 45717.531 | C48: 9adbf19e | D48: 88 | E48: Syrah | F48: 42100 | G48: 86 | H48: 3b2a1e70 | I48: Syrah Tempranillo s/Asp 2da | J48: 6200 | K48: 48300 | L48: ce659e77 | M48: Syrah s/Asp 3ra | N48: Tercer recarga de Syrah sobre Aspirant
A49: 3bd69807 | B49: 45717.535 | C49: 3e5c0749 | D49: 92 | E49: Syrah Ferm | F49: 35900 | G49: 85 | H49: 245cd9d6 | I49: Syrah s/Asp 2da | J49: 5800 | K49: 41700 | L49: 5f87c3d5 | M49: Syrah s/Asp 3ra | N49: Gota y Prensa sobre 3er de Aspirant
A50: 5c36256b | B50: 45717.536 | C50: 5008e5a3 | D50: 11 | E50: Cabernet Sauv Rect | F50: 6000 | G50: 87 | H50: f3ebcf34 | I50: Merlot Fer | J50: 38200 | K50: 44200 | L50: 6c3c93fd | M50: Merlot | N50: agregado de rectificado
A51: 2957daf0 | B51: 45718.647 | C51: 5008e5a3 | D51: 11 | E51: Cabernet Sauv Rect | F51: 4000 | G51: 65 | H51: e95eaf53 | I51: Anccelotta | J51: 20500 | K51: 24500 | L51: 15e7b86f | M51: Anccelotta
A52: c6944202 | B52: 45718.653 | C52: 5008e5a3 | D52: 11 | E52: Cabernet Sauv Rect | F52: 8000 | G52: 83 | H52: b45049fe | I52: Syrah | J52: 45000 | K52: 53000 | L52: 6c349523 | M52: Syrah
A53: c86ba992 | B53: 45719.698 | C53: d53930ff | D53: 150 | E53: Correccion | F53: 2000 | G53: 84 | H53: 7082548e | I53: Syrah Colom s/Asp 2 | J53: 39000 | K53: 41000 | L53: 994b8afe | M53: Syrah Colom s/Asp 2 | N53: Correccion hecha en la pilta 89 antes de trasegar a la 84 sobre los orujos de Aspirant
A54: e0151fea | B54: 45720.784 | C54: 27abb7ee | D54: 16 | E54: Cabernet Sauvignon Rect | F54: 2000 | G54: 68 | H54: 4adbcbaf | I54: Syrah | J54: 8000 | K54: 10000 | L54: 702b9808 | M54: Syrah | N54: Se agrega Rectificado 20%
A55: 85bf8a32 | B55: 45721.499 | C55: ce659e77 | D55: 86 | E55: Syrah s/Asp 3ra | F55: 48300 | G55: 121 | J55: 0 | K55: 48300 | L55: 58c72f6a | M55: Syrah s/Asp 3ra | N55: Gota y Prensa
A56: 76b1f67d | B56: 45721.5 | C56: 13d1574d | D56: 110 | E56: Merlot s/Asp descube | F56: 5000 | G56: 500 | I56: Ajuste de volumen | J56: 0 | K56: 5000 | L56: a18d2b54 | M56: Merlot s/Asp descube
A57: 9ac6d73d | B57: 45721.503 | C57: 5f87c3d5 | D57: 85 | E57: Syrah s/Asp 3ra | F57: 9500 | G57: 34 | H57: 61098b0e | I57: Syrah s/Asp 2da | J57: 30000 | K57: 39500 | L57: f41ecbda | M57: Syrah s/Asp 2da
A58: 1eb58a27 | B58: 45721.509 | C58: 5f87c3d5 | D58: 85 | E58: Syrah s/Asp 3ra | F58: 6000 | G58: 110 | H58: 13d1574d | I58: Merlot s/Asp descube | J58: 8000 | K58: 14000 | L58: 963fbbab | M58: Merlot s/Asp y Syrah
A59: f06d5126 | B59: 45721.51 | C59: 5f87c3d5 | D59: 85 | E59: Syrah s/Asp 3ra | F59: 26200 | G59: 121 | H59: 58c72f6a | I59: Syrah s/Asp 3ra | J59: 48300 | K59: 85800 | L59: f90482a4 | M59: Syrah s/Asp 3ra | N59: Descube gota y prensa
A60: 68cd71e8 | B60: 45721.512 | C60: d53930ff | D60: 150 | E60: Correccion | F60: 3000 | G60: 87 | H60: 6c3c93fd | I60: Merlot | J60: 44200 | K60: 47200 | L60: a62e4289 | M60: Correccion | N60: Correcion 150
A61: cc0f71ad | B61: 45721.515 | C61: c3f4cae7 | D61: 82 | E61: Chardonnay | F61: 1000 | G61: 77 | H61: cedc0dc0 | I61: Chardonnay | J61: 25000 | K61: 26000 | L61: 94493a7b | M61: Chardonnay
A62: 0c3c4109 | B62: 45721.515 | C62: c3f4cae7 | D62: 82 | E62: Chardonnay | F62: 1800 | G62: 78 | H62: 7e515c96 | I62: Chardonnay | J62: 24000 | K62: 25800 | L62: 9f119881 | M62: Chardonnay
A63: e22d3e22 | B63: 45721.518 | C63: c3f4cae7 | D63: 82 | E63: Chardonnay | F63: 2000 | G63: 79 | H63: dae2c109 | I63: Chardonnay | J63: 24000 | K63: 26000 | L63: e5b434bb | M63: Chardonnay
A64: c649af19 | B64: 45721.52 | C64: c3f4cae7 | D64: 82 | E64: Chardonnay | F64: 2500 | G64: 81 | H64: 861200f5 | I64: Chardonnay | J64: 24000 | K64: 26500 | L64: 1f033edd | M64: Chardonnay
A65: f19b3624 | B65: 45721.521 | C65: c3f4cae7 | D65: 82 | E65: Chardonnay | F65: 20700 | G65: 10 | J65: 0 | K65: 20700 | L65: f9bf68a3 | M65: Chardonnay
A66: a9f9a0bf | B66: 45722.4 | C66: 99fabf46 | D66: 69 | E66: Malbec | F66: 1500 | G66: 89 | H66: d2779d8c | I66: Syrah | J66: 39000 | K66: 40500 | L66: 5d46dc83 | M66: Syrah | N66: Sangria porque se lleno de mas la pileta
A67: 856d152a | B67: 45722.405 | C67: 7525cd32 | D67: 80 | E67: Syrah s/Asp 2da | F67: 2000 | G67: 110 | H67: 963fbbab | I67: Merlot s/Asp y Syrah | J67: 14000 | K67: 16000 | L67: d8ebe8ad | M67: Syrah s/Asp 2da | N67: Desvine relleno
A68: ba7c9884 | B68: 45722.406 | C68: 7525cd32 | D68: 80 | E68: Syrah s/Asp 2da | F68: 11000 | G68: 11 | J68: 0 | K68: 11000 | L68: 40c05149 | M68: Syrah s/Asp 2da | N68: Descube
A69: 0b7480e0 | B69: 45722.407 | C69: 994b8afe | D69: 84 | E69: Syrah Colom s/Asp 2 | F69: 25000 | G69: 11 | H69: 40c05149 | I69: Syrah s/Asp 2da | J69: 11000 | K69: 36000 | L69: 9c695ba3 | M69: Syrah Colom s/Asp 2 | N69: Descube Gota y prensa
A70: 5376b536 | B70: 45722.414 | C70: 994b8afe | D70: 84 | E70: Syrah Colom s/Asp 2 | F70: 37000 | G70: 14 | I70: Este volumen de mas vino de la 86 | J70: 0 | K70: 37000 | L70: 21a02bb8 | M70: Syrah Colom s/Asp 2
A71: d699073e | B71: 45722.415 | C71: 994b8afe | D71: 84 | E71: Syrah Colom s/Asp 2 | F71: 10000 | G71: 53 | J71: 0 | K71: 10000 | L71: 577b30d8 | M71: Syrah s/Asp 2 Prensa | N71: Esto es volumen de mas que falto de la 86
A72: 039b3a15 | B72: 45722.419 | C72: 27abb7ee | D72: 16 | E72: Cabernet Sauvignon Rect | F72: 9500 | G72: 88 | H72: 39ea0cc6 | I72: Syrah Ferm | J72: 40000 | K72: 49500 | L72: 4bf00cf0 | M72: Syrah Ferm | N72: Rectificado agregado
A73: 268d8d70 | B73: 45722.422 | C73: 4368dec6 | D73: 118 | E73: Malbec 24 | F73: 59700 | G73: 24 | J73: 0 | K73: 155600 | L73: 5dbffbd0 | M73: Tinto La Vendimia | N73: Corte La Vendimia
A74: 7011477f | B74: 45722.424 | C74: 4368dec6 | D74: 118 | E74: Malbec 24 | F74: 62100 | G74: 25 | J74: 0 | K74: 62100 | L74: 6d7a380a | M74: Tinto La Vendimia
A75: 0779902a | B75: 45722.424 | C75: 4368dec6 | D75: 118 | E75: Malbec 24 | F75: 24600 | G75: 95 | J75: 0 | K75: 24600 | L75: 58ded1ae | M75: Tinto La Vendimia
A76: 6b47fc79 | B76: 45722.425 | C76: 4368dec6 | D76: 118 | E76: Malbec 24 | F76: 9200 | G76: 96 | J76: 0 | K76: 9200 | L76: 0effecea | M76: Tinto La Vendimia
A77: b64c6496 | B77: 45722.76 | C77: 27abb7ee | D77: 16 | E77: Cabernet Sauvignon Rect | F77: 8000 | G77: 89 | H77: 5d46dc83 | I77: Syrah | J77: 40500 | K77: 48500 | L77: 3a5e04a4 | M77: Syrah | N77: Agregado de Rectificado
A78: 42091a69 | B78: 45722.776 | C78: b502a55e | D78: 114 | E78: Bonarda 24 | F78: 11200 | G78: 931 | J78: 0 | K78: 11200 | L78: abbbaccc | M78: Bonarda 24
A79: d8aa6864 | B79: 45722.776 | C79: b502a55e | D79: 114 | E79: Bonarda 24 | F79: 41000 | G79: 24 | H79: 5dbffbd0 | I79: Tinto La Vendimia | J79: 59700 | K79: 100700 | L79: 44d88f23 | M79: Tinto La Vendimia
A80: 8bdbe45e | B80: 45722.778 | C80: b502a55e | D80: 114 | E80: Bonarda 24 | F80: 42700 | G80: 25 | H80: 6d7a380a | I80: Tinto La Vendimia | J80: 62100 | K80: 104800 | L80: c4743b1b | M80: Tinto La Vendimia
A81: 4ea00640 | B81: 45722.778 | C81: b502a55e | D81: 114 | E81: Bonarda 24 | F81: 17000 | G81: 95 | H81: 58ded1ae | I81: Tinto La Vendimia | J81: 24600 | K81: 41600 | L81: 3bd6f9bf | M81: Tinto La Vendimia
A82: 32dd6da9 | B82: 45722.786 | C82: b502a55e | D82: 114 | E82: Bonarda 24 | F82: 13400 | G82: 96 | H82: 0effecea | I82: Tinto La Vendimia | J82: 9200 | K82: 22600 | L82: 0799e5db | M82: Tinto La Vendimia
A83: fc23046e | B83: 45723.448 | C83: d53930ff | D83: 150 | E83: Correccion | F83: 1000 | G83: 68 | H83: 702b9808 | I83: Syrah | J83: 10000 | K83: 11000 | L83: af88e380 | M83: Syrah | O83: Terminado | P83: Fermentando | Q83: TRUE | R83: Fermentando
A84: c2c37144 | B84: 45723.758 | C84: 665bbad3 | D84: 47 | E84: Cabernet Sauvignon 24 Rect | F84: 1000 | G84: 69 | H84: 99fabf46 | I84: Malbec | J84: 7600 | K84: 8600 | L84: 9c317849 | M84: Malbec | O84: Rectificado | P84: Fermentando | Q84: TRUE | R84: Fermentando
A85: 234faefd | B85: 45723.76 | C85: 665bbad3 | D85: 47 | E85: Cabernet Sauvignon 24 Rect | F85: 4000 | G85: 92 | H85: 3c90bae8 | I85: Syrah Tempranillo | J85: 40700 | K85: 44700 | L85: c85d74dc | M85: Syrah Tempranillo | O85: Rectificado | P85: Fermentando | Q85: TRUE | R85: Fermentando
A86: 3d37857c | B86: 45723.76 | C86: 665bbad3 | D86: 47 | E86: Cabernet Sauvignon 24 Rect | F86: 2000 | G86: 66 | H86: 9c95c706 | I86: Anccelotta | J86: 15000 | K86: 17000 | L86: 4d28a747 | M86: Anccelotta | O86: Rectificado | P86: Fermentando | Q86: TRUE | R86: Fermentando
A87: 047c2d7c | B87: 45723.771 | C87: 91f934c1 | D87: 35 | E87: Syrah 24 | F87: 15000 | G87: 24 | H87: 44d88f23 | I87: Tinto La Vendimia | J87: 100700 | K87: 115700 | L87: 915299ff | M87: Tinto La Vendimia | O87: Terminado | P87: Terminado | Q87: TRUE | R87: Terminado
A88: c142ff82 | B88: 45723.773 | C88: 91f934c1 | D88: 35 | E88: Syrah 24 | F88: 15500 | G88: 25 | H88: c4743b1b | I88: Tinto La Vendimia | J88: 104800 | K88: 120300 | L88: 0700b55d | M88: Tinto La Vendimia | O88: Terminado | P88: Terminado | Q88: TRUE | R88: Terminado
A89: a2ec88ae | B89: 45723.773 | C89: 91f934c1 | D89: 35 | E89: Syrah 24 | F89: 6200 | G89: 95 | H89: 3bd6f9bf | I89: Tinto La Vendimia | J89: 41600 | K89: 47800 | L89: df446c40 | M89: Tinto La Vendimia | O89: Terminado | P89: Terminado | Q89: TRUE | R89: Terminado
A90: a390f916 | B90: 45723.774 | C90: 91f934c1 | D90: 35 | E90: Syrah 24 | F90: 2600 | G90: 96 | H90: 0799e5db | I90: Tinto La Vendimia | J90: 22600 | K90: 25200 | L90: 61e7a661 | M90: Tinto La Vendimia | O90: Terminado | P90: Terminado | Q90: TRUE | R90: Terminado
A91: 2d51a36a | B91: 45723.793 | C91: 0835b42b | D91: 102 | E91: Aspirant | F91: 2700 | G91: 95 | H91: df446c40 | I91: Tinto La Vendimia | J91: 47800 | K91: 50500 | L91: 83cb5e85 | M91: Tinto La Vendimia | O91: Descubada | P91: Terminado | Q91: TRUE | R91: Terminado
A92: 723d4d28 | B92: 45723.794 | C92: 0835b42b | D92: 102 | E92: Aspirant | F92: 1100 | G92: 96 | H92: 61e7a661 | I92: Tinto La Vendimia | J92: 25200 | K92: 26300 | L92: 9c2bc1c1 | M92: Tinto La Vendimia | O92: Descubada | P92: Terminado | Q92: TRUE | R92: Terminado
A93: 222dbe9a | B93: 45723.796 | C93: 0835b42b | D93: 102 | E93: Aspirant | F93: 6500 | G93: 24 | H93: 915299ff | I93: Tinto La Vendimia | J93: 115700 | K93: 122200 | L93: 66440ff8 | M93: Tinto La Vendimia | O93: Descubada | P93: Terminado | Q93: TRUE | R93: Terminado
A94: 81e90a51 | B94: 45723.797 | C94: 0835b42b | D94: 102 | E94: Aspirant | F94: 6800 | G94: 25 | H94: 0700b55d | I94: Tinto La Vendimia | J94: 120300 | K94: 127100 | L94: c883c10a | M94: Tinto La Vendimia | O94: Descubada | P94: Terminado | Q94: TRUE | R94: Terminado
... A102: 0b8dfe7e | B102: 45723.821 | C102: fe114136 | D102: 67 | E102: Malbec 24 | F102: 1600 | G102: 96 | H102: cdd54045 | I102: Tinto La Vendimia | J102: 33100 | K102: 34700 | L102: c50c5100 | M102: Tinto La Vendimia | O102: Terminado | P102: Terminado | Q102: TRUE | R102: Terminado
A103: e6d010c5 | B103: 45724.546 | C103: e5b434bb | D103: 79 | E103: Chardonnay | F103: 26000 | G103: 5 | J103: 0 | K103: 26000 | L103: 78ca3339 | M103: Chardonnay | O103: Fermentando | Q103: FALSE | R103: Fermentando
A104: 7f5134a8 | B104: 45724.547 | C104: 94493a7b | D104: 77 | E104: Chardonnay | F104: 4000 | G104: 5 | H104: 78ca3339 | I104: Chardonnay | J104: 26000 | K104: 30000 | L104: 593f826f | M104: Chardonnay | O104: Fermentando | P104: Fermentando | Q104: TRUE | R104: Fermentando
A105: cf666ee7 | B105: 45724.548 | C105: 94493a7b | D105: 77 | E105: Chardonnay | F105: 22000 | G105: 8 | J105: 0 | K105: 22000 | L105: 376dbee6 | M105: Chardonnay | O105: Fermentando | Q105: FALSE | R105: Descubada
A106: 42fe26ec | B106: 45724.55 | C106: 73b50dc4 | D106: 42 | E106: Malbec 24 | F106: 13600 | G106: 24 | H106: 212851d2 | I106: Tinto La Vendimia | J106: 168000 | K106: 181600 | L106: 8782f51d | M106: Tinto La Vendimia | O106: Terminado | P106: Terminado | Q106: TRUE | R106: Terminado
A107: 07b798ca | B107: 45724.551 | C107: 73b50dc4 | D107: 42 | E107: Malbec 24 | F107: 14100 | G107: 25 | H107: 6ccc7bc6 | I107: Tinto La Vendimia | J107: 174800 | K107: 188900 | L107: 481ac202 | M107: Tinto La Vendimia | O107: Terminado | P107: Terminado | Q107: TRUE | R107: Terminado
A108: 84b16607 | B108: 45724.551 | C108: 73b50dc4 | D108: 42 | E108: Malbec 24 | F108: 5600 | G108: 95 | H108: 69fc871f | I108: Tinto La Vendimia | J108: 69100 | K108: 74700 | L108: 1953afee | M108: Tinto La Vendimia | O108: Terminado | P108: Terminado | Q108: TRUE | R108: Terminado
...

Sheet SQL_GENERADO_V3
A1: -- ========================================
A2: -- SCRIPT SQL GENERADO AUTOMÁTICAMENTE
A3: -- Bodega - Sistema de Gestión de Piletas
A4: -- ========================================
A6: -- 1. TABLA: Estado_pileta
A7: INSERT INTO Estado_pileta (nombre) VALUES ('ACTIVO');
A9: -- 2. TABLA: Tipo_movimiento
A10: INSERT INTO Tipo_movimiento (nombre) VALUES ('Trasiego');
A11: INSERT INTO Tipo_movimiento (nombre) VALUES ('Ajuste Volumen');
A12: INSERT INTO Tipo_movimiento (nombre) VALUES ('Llenado');
A14: -- 3. TABLA: Variedad
A15: INSERT INTO Variedad (nombre, descripcion) VALUES ('Syrah', NULL);
... A4365: -- ========================================

Sheet GLOBAL
A1: ID Global | B1: Pileta Llena | C1: Pileta Numero | D1: Lote | E1: Estado
A2: 15343ec1 | C2: 116 | D2: 8347bdfc

Sheet ESTADO_PILETAS
A1: ID Estado Pileta
A2: Fermentando
A3: Descubada
A4: 1er Trasiego
A5: 2do Trasiego
A6: Terminado
A7: Filtrado Tang
A8: Rectificado
A9: Desvinada
A10: Recarga Fermentando
A11: Traslado Venta

Sheet CIU
A1: Fecha | B1: Sem | C1: Rto. | D1: Productor | E1: Finca | F1: I.N.V. | G1: Cambio | H1: Ctel. | I1: Tachos | J1: Chofer | K1: CUIT / CUIL | L1: Camion | M1: Modelo | N1: Patente | O1: Bruto | P1: Tara | Q1: Neto | R1: Uva Real | S1: Variedad CIU | T1: Destino VINO | U1: Brix Real | V1: T. Azuc. | W1: Nº - CIU | X1: Cosecha | Y1: Vasija
A2: =IFERROR(__xludf.DUMMYFUNCTION("IMPORTRANGE(""https://docs.google.com/spreadsheets/d/1K4FbrEqBWgpGHU7endU5yHpLzeM0dREtUGQF3mOWIUk/edit?gid=542800275#gid=542800275"",""CIU_EXPO!A2:Y700"")"),"#REF!") -> #REF!

Sheet PILETASEXPO
A1: ID_PILETA | B1: Capacidad | C1: Lote Pta | D1: Varietal | E1: Volumen
A2: 1 | B2: 107500 | C2: {=PILETAS!C2:C130} | D2: {=XLOOKUP(C2,'PILETAS LOTES'!$A$2:$A1000,'PILETAS LOTES'!$F$2:$F1000,"",0)} | E2: {=XLOOKUP(C2,'PILETAS LOTES'!$A$2:$A1000,'PILETAS LOTES'!$H$2:$H1000,"",0)}
A3: 2 | B3: 8400 | C3: da997936 | D3: {=XLOOKUP(C3,'PILETAS LOTES'!$A$2:$A1000,'PILETAS LOTES'!$F$2:$F1000,"",0)} -> Chardonnay | E3: {=XLOOKUP(C3,'PILETAS LOTES'!$A$2:$A1000,'PILETAS LOTES'!$H$2:$H1000,"",0)} -> 2200
A4: 3 | B4: 15000 | D4: {=XLOOKUP(C4,'PILETAS LOTES'!$A$2:$A1000,'PILETAS LOTES'!$F$2:$F1000,"",0)} | E4: {=XLOOKUP(C4,'PILETAS LOTES'!$A$2:$A1000,'PILETAS LOTES'!$H$2:$H1000,"",0)}
A5: 4 | B5: 26000 | D5: {=XLOOKUP(C5,'PILETAS LOTES'!$A$2:$A1000,'PILETAS LOTES'!$F$2:$F1000,"",0)} | E5: {=XLOOKUP(C5,'PILETAS LOTES'!$A$2:$A1000,'PILETAS LOTES'!$H$2:$H1000,"",0)}
A6: 5 | B6: 30000 | C6: ebf08055 | D6: {=XLOOKUP(C6,'PILETAS LOTES'!$A$2:$A1000,'PILETAS LOTES'!$F$2:$F1000,"",0)} -> Chardonnay | E6: {=XLOOKUP(C6,'PILETAS LOTES'!$A$2:$A1000,'PILETAS LOTES'!$H$2:$H1000,"",0)} -> 30000
A7: 6 | B7: 32000 | C7: a324303d | D7: {=XLOOKUP(C7,'PILETAS LOTES'!$A$2:$A1000,'PILETAS LOTES'!$F$2:$F1000,"",0)} | E7: {=XLOOKUP(C7,'PILETAS LOTES'!$A$2:$A1000,'PILETAS LOTES'!$H$2:$H1000,"",0)}
A8: 7 | B8: 30000 | D8: {=XLOOKUP(C8,'PILETAS LOTES'!$A$2:$A1000,'PILETAS LOTES'!$F$2:$F1000,"",0)} | E8: {=XLOOKUP(C8,'PILETAS LOTES'!$A$2:$A1000,'PILETAS LOTES'!$H$2:$H1000,"",0)}
A9: 8 | B9: 22000 | C9: 376dbee6 | D9: {=XLOOKUP(C9,'PILETAS LOTES'!$A$2:$A1000,'PILETAS LOTES'!$F$2:$F1000,"",0)} -> Chardonnay | E9: {=XLOOKUP(C9,'PILETAS LOTES'!$A$2:$A1000,'PILETAS LOTES'!$H$2:$H1000,"",0)} -> 22000
A10: 9 | B10: 30000 | D10: {=XLOOKUP(C10,'PILETAS LOTES'!$A$2:$A1000,'PILETAS LOTES'!$F$2:$F1000,"",0)} | E10: {=XLOOKUP(C10,'PILETAS LOTES'!$A$2:$A1000,'PILETAS LOTES'!$H$2:$H1000,"",0)}
A11: 10 | B11: 21000 | C11: f9bf68a3 | D11: {=XLOOKUP(C11,'PILETAS LOTES'!$A$2:$A1000,'PILETAS LOTES'!$F$2:$F1000,"",0)} -> Chardonnay | E11: {=XLOOKUP(C11,'PILETAS LOTES'!$A$2:$A1000,'PILETAS LOTES'!$H$2:$H1000,"",0)} -> 21000
A12: 11 | B12: 36000 | D12: {=XLOOKUP(C12,'PILETAS LOTES'!$A$2:$A1000,'PILETAS LOTES'!$F$2:$F1000,"",0)} | E12: {=XLOOKUP(C12,'PILETAS LOTES'!$A$2:$A1000,'PILETAS LOTES'!$H$2:$H1000,"",0)}
A13: 12 | B13: 35300 | D13: {=XLOOKUP(C13,'PILETAS LOTES'!$A$2:$A1000,'PILETAS LOTES'!$F$2:$F1000,"",0)} | E13: {=XLOOKUP(C13,'PILETAS LOTES'!$A$2:$A1000,'PILETAS LOTES'!$H$2:$H1000,"",0)}
A14: 13 | B14: 20000 | D14: {=XLOOKUP(C14,'PILETAS LOTES'!$A$2:$A1000,'PILETAS LOTES'!$F$2:$F1000,"",0)} | E14: {=XLOOKUP(C14,'PILETAS LOTES'!$A$2:$A1000,'PILETAS LOTES'!$H$2:$H1000,"",0)}
A15: 14 | B15: 37000 | C15: 10b87434 | D15: {=XLOOKUP(C15,'PILETAS LOTES'!$A$2:$A1000,'PILETAS LOTES'!$F$2:$F1000,"",0)} -> Aspirant | E15: {=XLOOKUP(C15,'PILETAS LOTES'!$A$2:$A1000,'PILETAS LOTES'!$H$2:$H1000,"",0)} -> 37000
A16: 15 | B16: 36500 | D16: {=XLOOKUP(C16,'PILETAS LOTES'!$A$2:$A1000,'PILETAS LOTES'!$F$2:$F1000,"",0)} | E16: {=XLOOKUP(C16,'PILETAS LOTES'!$A$2:$A1000,'PILETAS LOTES'!$H$2:$H1000,"",0)}
A17: 16 | B17: 19500 | C17: 869e8a1b | D17: {=XLOOKUP(C17,'PILETAS LOTES'!$A$2:$A1000,'PILETAS LOTES'!$F$2:$F1000,"",0)} | E17: {=XLOOKUP(C17,'PILETAS LOTES'!$A$2:$A1000,'PILETAS LOTES'!$H$2:$H1000,"",0)}
A18: 17 | B18: 39500 | D18: {=XLOOKUP(C18,'PILETAS LOTES'!$A$2:$A1000,'PILETAS LOTES'!$F$2:$F1000,"",0)} | E18: {=XLOOKUP(C18,'PILETAS LOTES'!$A$2:$A1000,'PILETAS LOTES'!$H$2:$H1000,"",0)}
A19: 18 | B19: 39500 | D19: {=XLOOKUP(C19,'PILETAS LOTES'!$A$2:$A1000,'PILETAS LOTES'!$F$2:$F1000,"",0)} | E19: {=XLOOKUP(C19,'PILETAS LOTES'!$A$2:$A1000,'PILETAS LOTES'!$H$2:$H1000,"",0)}
A20: 19 | B20: 27500 | D20: {=XLOOKUP(C20,'PILETAS LOTES'!$A$2:$A1000,'PILETAS LOTES'!$F$2:$F1000,"",0)} | E20: {=XLOOKUP(C20,'PILETAS LOTES'!$A$2:$A1000,'PILETAS LOTES'!$H$2:$H1000,"",0)}
A21: 20 | B21: 38100 | D21: {=XLOOKUP(C21,'PILETAS LOTES'!$A$2:$A1000,'PILETAS LOTES'!$F$2:$F1000,"",0)} | E21: {=XLOOKUP(C21,'PILETAS LOTES'!$A$2:$A1000,'PILETAS LOTES'!$H$2:$H1000,"",0)}
A22: 21 | B22: 28000 | D22: {=XLOOKUP(C22,'PILETAS LOTES'!$A$2:$A1000,'PILETAS LOTES'!$F$2:$F1000,"",0)} | E22: {=XLOOKUP(C22,'PILETAS LOTES'!$A$2:$A1000,'PILETAS LOTES'!$H$2:$H1000,"",0)}
A23: 22 | B23: 41100 | D23: {=XLOOKUP(C23,'PILETAS LOTES'!$A$2:$A1000,'PILETAS LOTES'!$F$2:$F1000,"",0)} | E23: {=XLOOKUP(C23,'PILETAS LOTES'!$A$2:$A1000,'PILETAS LOTES'!$H$2:$H1000,"",0)}
A24: 23 | B24: 197100 | D24: {=XLOOKUP(C24,'PILETAS LOTES'!$A$2:$A1000,'PILETAS LOTES'!$F$2:$F1000,"",0)} | E24: {=XLOOKUP(C24,'PILETAS LOTES'!$A$2:$A1000,'PILETAS LOTES'!$H$2:$H1000,"",0)}
A25: 24 | B25: 186600 | C25: b3a40361 | D25: {=XLOOKUP(C25,'PILETAS LOTES'!$A$2:$A1000,'PILETAS LOTES'!$F$2:$F1000,"",0)} -> Malbec | E25: {=XLOOKUP(C25,'PILETAS LOTES'!$A$2:$A1000,'PILETAS LOTES'!$H$2:$H1000,"",0)} -> 186600
A26: 25 | B26: 194300 | C26: a2728d01 | D26: {=XLOOKUP(C26,'PILETAS LOTES'!$A$2:$A1000,'PILETAS LOTES'!$F$2:$F1000,"",0)} | E26: {=XLOOKUP(C26,'PILETAS LOTES'!$A$2:$A1000,'PILETAS LOTES'!$H$2:$H1000,"",0)}
A27: 26 | B27: 207600 | C27: a37dae6b | D27: {=XLOOKUP(C27,'PILETAS LOTES'!$A$2:$A1000,'PILETAS LOTES'!$F$2:$F1000,"",0)} -> Tinto | E27: {=XLOOKUP(C27,'PILETAS LOTES'!$A$2:$A1000,'PILETAS LOTES'!$H$2:$H1000,"",0)} -> 207600
A28: 27 | B28: 207100 | D28: {=XLOOKUP(C28,'PILETAS LOTES'!$A$2:$A1000,'PILETAS LOTES'!$F$2:$F1000,"",0)} | E28: {=XLOOKUP(C28,'PILETAS LOTES'!$A$2:$A1000,'PILETAS LOTES'!$H$2:$H1000,"",0)}
A29: 28 | B29: 216000 | D29: {=XLOOKUP(C29,'PILETAS LOTES'!$A$2:$A1000,'PILETAS LOTES'!$F$2:$F1000,"",0)} | E29: {=XLOOKUP(C29,'PILETAS LOTES'!$A$2:$A1000,'PILETAS LOTES'!$H$2:$H1000,"",0)}
A30: 29 | B30: 20400 | D30: {=XLOOKUP(C30,'PILETAS LOTES'!$A$2:$A1000,'PILETAS LOTES'!$F$2:$F1000,"",0)} | E30: {=XLOOKUP(C30,'PILETAS LOTES'!$A$2:$A1000,'PILETAS LOTES'!$H$2:$H1000,"",0)}
A31: 30 | B31: 38800 | D31: {=XLOOKUP(C31,'PILETAS LOTES'!$A$2:$A1000,'PILETAS LOTES'!$F$2:$F1000,"",0)} | E31: {=XLOOKUP(C31,'PILETAS LOTES'!$A$2:$A1000,'PILETAS LOTES'!$H$2:$H1000,"",0)}
A32: 31 | B32: 25700 | D32: {=XLOOKUP(C32,'PILETAS LOTES'!$A$2:$A1000,'PILETAS LOTES'!$F$2:$F1000,"",0)} | E32: {=XLOOKUP(C32,'PILETAS LOTES'!$A$2:$A1000,'PILETAS LOTES'!$H$2:$H1000,"",0)}
A33: 32 | B33: 36300 | D33: {=XLOOKUP(C33,'PILETAS LOTES'!$A$2:$A1000,'PILETAS LOTES'!$F$2:$F1000,"",0)} | E33: {=XLOOKUP(C33,'PILETAS LOTES'!$A$2:$A1000,'PILETAS LOTES'!$H$2:$H1000,"",0)}
A34: 33 | B34: 25300 | C34: 7def2139 | D34: {=XLOOKUP(C34,'PILETAS LOTES'!$A$2:$A1000,'PILETAS LOTES'!$F$2:$F1000,"",0)} -> Chardonnay | E34: {=XLOOKUP(C34,'PILETAS LOTES'!$A$2:$A1000,'PILETAS LOTES'!$H$2:$H1000,"",0)} -> 25300
A35: 34 | B35: 39500 | C35: 08cd1438 | D35: {=XLOOKUP(C35,'PILETAS LOTES'!$A$2:$A1000,'PILETAS LOTES'!$F$2:$F1000,"",0)} -> Malbec | E35: {=XLOOKUP(C35,'PILETAS LOTES'!$A$2:$A1000,'PILETAS LOTES'!$H$2:$H1000,"",0)} -> 39500
A36: 35 | B36: 39300 | D36: {=XLOOKUP(C36,'PILETAS LOTES'!$A$2:$A1000,'PILETAS LOTES'!$F$2:$F1000,"",0)} | E36: {=XLOOKUP(C36,'PILETAS LOTES'!$A$2:$A1000,'PILETAS LOTES'!$H$2:$H1000,"",0)}
A37: 36 | B37: 19700 | C37: 0997a77d | D37: {=XLOOKUP(C37,'PILETAS LOTES'!$A$2:$A1000,'PILETAS LOTES'!$F$2:$F1000,"",0)} -> Torrontes | E37: {=XLOOKUP(C37,'PILETAS LOTES'!$A$2:$A1000,'PILETAS LOTES'!$H$2:$H1000,"",0)} -> 19700
A38: 37 | B38: 39000 | D38: {=XLOOKUP(C38,'PILETAS LOTES'!$A$2:$A1000,'PILETAS LOTES'!$F$2:$F1000,"",0)} | E38: {=XLOOKUP(C38,'PILETAS LOTES'!$A$2:$A1000,'PILETAS LOTES'!$H$2:$H1000,"",0)}
A39: 38 | B39: 23500 | D39: {=XLOOKUP(C39,'PILETAS LOTES'!$A$2:$A1000,'PILETAS LOTES'!$F$2:$F1000,"",0)} | E39: {=XLOOKUP(C39,'PILETAS LOTES'!$A$2:$A1000,'PILETAS LOTES'!$H$2:$H1000,"",0)}
A40: 39 | B40: 40000 | D40: {=XLOOKUP(C40,'PILETAS LOTES'!$A$2:$A1000,'PILETAS LOTES'!$F$2:$F1000,"",0)} | E40: {=XLOOKUP(C40,'PILETAS LOTES'!$A$2:$A1000,'PILETAS LOTES'!$H$2:$H1000,"",0)}
A41: 40 | B41: 24000 | D41: {=XLOOKUP(C41,'PILETAS LOTES'!$A$2:$A1000,'PILETAS LOTES'!$F$2:$F1000,"",0)} | E41: {=XLOOKUP(C41,'PILETAS LOTES'!$A$2:$A1000,'PILETAS LOTES'!$H$2:$H1000,"",0)}
A42: 41 | B42: 35100 | D42: {=XLOOKUP(C42,'PILETAS LOTES'!$A$2:$A1000,'PILETAS LOTES'!$F$2:$F1000,"",0)} | E42: {=XLOOKUP(C42,'PILETAS LOTES'!$A$2:$A1000,'PILETAS LOTES'!$H$2:$H1000,"",0)}
A43: 42 | B43: 35900 | C43: dccd4f5e | D43: {=XLOOKUP(C43,'PILETAS LOTES'!$A$2:$A1000,'PILETAS LOTES'!$F$2:$F1000,"",0)} -> Bonarda | E43: {=XLOOKUP(C43,'PILETAS LOTES'!$A$2:$A1000,'PILETAS LOTES'!$H$2:$H1000,"",0)} -> 35900
A44: 43 | B44: 17000 | D44: {=XLOOKUP(C44,'PILETAS LOTES'!$A$2:$A1000,'PILETAS LOTES'!$F$2:$F1000,"",0)} | E44: {=XLOOKUP(C44,'PILETAS LOTES'!$A$2:$A1000,'PILETAS LOTES'!$H$2:$H1000,"",0)}
A45: 44 | B45: 19100 | C45: 7ae457f1 | D45: {=XLOOKUP(C45,'PILETAS LOTES'!$A$2:$A1000,'PILETAS LOTES'!$F$2:$F1000,"",0)} -> Torrontes | E45: {=XLOOKUP(C45,'PILETAS LOTES'!$A$2:$A1000,'PILETAS LOTES'!$H$2:$H1000,"",0)} -> 19100
A46: 45 | B46: 30000 | D46: {=XLOOKUP(C46,'PILETAS LOTES'!$A$2:$A1000,'PILETAS LOTES'!$F$2:$F1000,"",0)} | E46: {=XLOOKUP(C46,'PILETAS LOTES'!$A$2:$A1000,'PILETAS LOTES'!$H$2:$H1000,"",0)}
A47: 46 | B47: 29000 | C47: 9b47717c | D47: {=XLOOKUP(C47,'PILETAS LOTES'!$A$2:$A1000,'PILETAS LOTES'!$F$2:$F1000,"",0)} -> Bonarda | E47: {=XLOOKUP(C47,'PILETAS LOTES'!$A$2:$A1000,'PILETAS LOTES'!$H$2:$H1000,"",0)} -> 29000
A48: 47 | B48: 20000 | D48: {=XLOOKUP(C48,'PILETAS LOTES'!$A$2:$A1000,'PILETAS LOTES'!$F$2:$F1000,"",0)} | E48: {=XLOOKUP(C48,'PILETAS LOTES'!$A$2:$A1000,'PILETAS LOTES'!$H$2:$H1000,"",0)}
A49: 48 | B49: 26000 | C49: ef198a97 | D49: {=XLOOKUP(C49,'PILETAS LOTES'!$A$2:$A1000,'PILETAS LOTES'!$F$2:$F1000,"",0)} -> Pedro Gimenez | E49: {=XLOOKUP(C49,'PILETAS LOTES'!$A$2:$A1000,'PILETAS LOTES'!$H$2:$H1000,"",0)} -> 26000
A50: 49 | B50: 26000 | D50: {=XLOOKUP(C50,'PILETAS LOTES'!$A$2:$A1000,'PILETAS LOTES'!$F$2:$F1000,"",0)} | E50: {=XLOOKUP(C50,'PILETAS LOTES'!$A$2:$A1000,'PILETAS LOTES'!$H$2:$H1000,"",0)}
A51: 50 | B51: 5100 | C51: 5db7be38 | D51: {=XLOOKUP(C51,'PILETAS LOTES'!$A$2:$A1000,'PILETAS LOTES'!$F$2:$F1000,"",0)} | E51: {=XLOOKUP(C51,'PILETAS LOTES'!$A$2:$A1000,'PILETAS LOTES'!$H$2:$H1000,"",0)}
A52: 51 | B52: 3900 | C52: b7784dc8 | D52: {=XLOOKUP(C52,'PILETAS LOTES'!$A$2:$A1000,'PILETAS LOTES'!$F$2:$F1000,"",0)} | E52: {=XLOOKUP(C52,'PILETAS LOTES'!$A$2:$A1000,'PILETAS LOTES'!$H$2:$H1000,"",0)}
A53: 52 | B53: 27000 | D53: {=XLOOKUP(C53,'PILETAS LOTES'!$A$2:$A1000,'PILETAS LOTES'!$F$2:$F1000,"",0)} | E53: {=XLOOKUP(C53,'PILETAS LOTES'!$A$2:$A1000,'PILETAS LOTES'!$H$2:$H1000,"",0)}
A54: 53 | B54: 22000 | C54: da5fcb21 | D54: {=XLOOKUP(C54,'PILETAS LOTES'!$A$2:$A1000,'PILETAS LOTES'!$F$2:$F1000,"",0)} -> Tanat | E54: {=XLOOKUP(C54,'PILETAS LOTES'!$A$2:$A1000,'PILETAS LOTES'!$H$2:$H1000,"",0)} -> 22000
A55: 54 | B55: 22900 | C55: 5c87f162 | D55: {=XLOOKUP(C55,'PILETAS LOTES'!$A$2:$A1000,'PILETAS LOTES'!$F$2:$F1000,"",0)} | E55: {=XLOOKUP(C55,'PILETAS LOTES'!$A$2:$A1000,'PILETAS LOTES'!$H$2:$H1000,"",0)}
A56: 55 | B56: 3000 | C56: 2d412906 | D56: {=XLOOKUP(C56,'PILETAS LOTES'!$A$2:$A1000,'PILETAS LOTES'!$F$2:$F1000,"",0)} -> Chardonnay | E56: {=XLOOKUP(C56,'PILETAS LOTES'!$A$2:$A1000,'PILETAS LOTES'!$H$2:$H1000,"",0)} -> 3000
A57: 56 | B57: 3000 | D57: {=XLOOKUP(C57,'PILETAS LOTES'!$A$2:$A1000,'PILETAS LOTES'!$F$2:$F1000,"",0)} | E57: {=XLOOKUP(C57,'PILETAS LOTES'!$A$2:$A1000,'PILETAS LOTES'!$H$2:$H1000,"",0)}
A58: 57 | B58: 96800 | D58: {=XLOOKUP(C58,'PILETAS LOTES'!$A$2:$A1000,'PILETAS LOTES'!$F$2:$F1000,"",0)} | E58: {=XLOOKUP(C58,'PILETAS LOTES'!$A$2:$A1000,'PILETAS LOTES'!$H$2:$H1000,"",0)}
A59: 58 | B59: 58400 | D59: {=XLOOKUP(C59,'PILETAS LOTES'!$A$2:$A1000,'PILETAS LOTES'!$F$2:$F1000,"",0)} | E59: {=XLOOKUP(C59,'PILETAS LOTES'!$A$2:$A1000,'PILETAS LOTES'!$H$2:$H1000,"",0)}
A60: 59 | B60: 58200 | D60: {=XLOOKUP(C60,'PILETAS LOTES'!$A$2:$A1000,'PILETAS LOTES'!$F$2:$F1000,"",0)} | E60: {=XLOOKUP(C60,'PILETAS LOTES'!$A$2:$A1000,'PILETAS LOTES'!$H$2:$H1000,"",0)}
A61: 60 | B61: 55000 | D61: {=XLOOKUP(C61,'PILETAS LOTES'!$A$2:$A1000,'PILETAS LOTES'!$F$2:$F1000,"",0)} | E61: {=XLOOKUP(C61,'PILETAS LOTES'!$A$2:$A1000,'PILETAS LOTES'!$H$2:$H1000,"",0)}
A62: 61 | B62: 57100 | D62: {=XLOOKUP(C62,'PILETAS LOTES'!$A$2:$A1000,'PILETAS LOTES'!$F$2:$F1000,"",0)} | E62: {=XLOOKUP(C62,'PILETAS LOTES'!$A$2:$A1000,'PILETAS LOTES'!$H$2:$H1000,"",0)}
A63: 62 | B63: 55000 | D63: {=XLOOKUP(C63,'PILETAS LOTES'!$A$2:$A1000,'PILETAS LOTES'!$F$2:$F1000,"",0)} | E63: {=XLOOKUP(C63,'PILETAS LOTES'!$A$2:$A1000,'PILETAS LOTES'!$H$2:$H1000,"",0)}
A64: 63 | B64: 70300 | D64: {=XLOOKUP(C64,'PILETAS LOTES'!$A$2:$A1000,'PILETAS LOTES'!$F$2:$F1000,"",0)} | E64: {=XLOOKUP(C64,'PILETAS LOTES'!$A$2:$A1000,'PILETAS LOTES'!$H$2:$H1000,"",0)}
A65: 64 | B65: 259600 | D65: {=XLOOKUP(C65,'PILETAS LOTES'!$A$2:$A1000,'PILETAS LOTES'!$F$2:$F1000,"",0)} | E65: {=XLOOKUP(C65,'PILETAS LOTES'!$A$2:$A1000,'PILETAS LOTES'!$H$2:$H1000,"",0)}
A66: 65 | B66: 35500 | C66: 4d3f24b6 | D66: {=XLOOKUP(C66,'PILETAS LOTES'!$A$2:$A1000,'PILETAS LOTES'!$F$2:$F1000,"",0)} | E66: {=XLOOKUP(C66,'PILETAS LOTES'!$A$2:$A1000,'PILETAS LOTES'!$H$2:$H1000,"",0)}
A67: 66 | B67: 23000 | C67: d52c4944 | D67: {=XLOOKUP(C67,'PILETAS LOTES'!$A$2:$A1000,'PILETAS LOTES'!$F$2:$F1000,"",0)} | E67: {=XLOOKUP(C67,'PILETAS LOTES'!$A$2:$A1000,'PILETAS LOTES'!$H$2:$H1000,"",0)}
A68: 67 | B68: 23000 | C68: eb6cce4f | D68: {=XLOOKUP(C68,'PILETAS LOTES'!$A$2:$A1000,'PILETAS LOTES'!$F$2:$F1000,"",0)} -> Anccelotta | E68: {=XLOOKUP(C68,'PILETAS LOTES'!$A$2:$A1000,'PILETAS LOTES'!$H$2:$H1000,"",0)} -> 23000
A69: 68 | B69: 13000 | C69: 22a75cd4 | D69: {=XLOOKUP(C69,'PILETAS LOTES'!$A$2:$A1000,'PILETAS LOTES'!$F$2:$F1000,"",0)} | E69: {=XLOOKUP(C69,'PILETAS LOTES'!$A$2:$A1000,'PILETAS LOTES'!$H$2:$H1000,"",0)}
A70: 69 | B70: 13000 | C70: fdb74546 | D70: {=XLOOKUP(C70,'PILETAS LOTES'!$A$2:$A1000,'PILETAS LOTES'!$F$2:$F1000,"",0)} | E70: {=XLOOKUP(C70,'PILETAS LOTES'!$A$2:$A1000,'PILETAS LOTES'!$H$2:$H1000,"",0)}
A71: 70 | B71: 13000 | D71: {=XLOOKUP(C71,'PILETAS LOTES'!$A$2:$A1000,'PILETAS LOTES'!$F$2:$F1000,"",0)} | E71: {=XLOOKUP(C71,'PILETAS LOTES'!$A$2:$A1000,'PILETAS LOTES'!$H$2:$H1000,"",0)}
A72: 71 | B72: 13000 | C72: 7a61df09 | D72: {=XLOOKUP(C72,'PILETAS LOTES'!$A$2:$A1000,'PILETAS LOTES'!$F$2:$F1000,"",0)} | E72: {=XLOOKUP(C72,'PILETAS LOTES'!$A$2:$A1000,'PILETAS LOTES'!$H$2:$H1000,"",0)}
A73: 72 | B73: 13000 | D73: {=XLOOKUP(C73,'PILETAS LOTES'!$A$2:$A1000,'PILETAS LOTES'!$F$2:$F1000,"",0)} | E73: {=XLOOKUP(C73,'PILETAS LOTES'!$A$2:$A1000,'PILETAS LOTES'!$H$2:$H1000,"",0)}
A74: 73 | B74: 13000 | D74: {=XLOOKUP(C74,'PILETAS LOTES'!$A$2:$A1000,'PILETAS LOTES'!$F$2:$F1000,"",0)} | E74: {=XLOOKUP(C74,'PILETAS LOTES'!$A$2:$A1000,'PILETAS LOTES'!$H$2:$H1000,"",0)}
A75: 74 | B75: 13000 | D75: {=XLOOKUP(C75,'PILETAS LOTES'!$A$2:$A1000,'PILETAS LOTES'!$F$2:$F1000,"",0)} | E75: {=XLOOKUP(C75,'PILETAS LOTES'!$A$2:$A1000,'PILETAS LOTES'!$H$2:$H1000,"",0)}
A76: 75 | B76: 7000 | C76: 7a9e7f06 | D76: {=XLOOKUP(C76,'PILETAS LOTES'!$A$2:$A1000,'PILETAS LOTES'!$F$2:$F1000,"",0)} -> Tanat | E76: {=XLOOKUP(C76,'PILETAS LOTES'!$A$2:$A1000,'PILETAS LOTES'!$H$2:$H1000,"",0)} -> 7000
A77: 76 | B77: 25500 | D77: {=XLOOKUP(C77,'PILETAS LOTES'!$A$2:$A1000,'PILETAS LOTES'!$F$2:$F1000,"",0)} | E77: {=XLOOKUP(C77,'PILETAS LOTES'!$A$2:$A1000,'PILETAS LOTES'!$H$2:$H1000,"",0)}
A78: 77 | B78: 26000 | D78: {=XLOOKUP(C78,'PILETAS LOTES'!$A$2:$A1000,'PILETAS LOTES'!$F$2:$F1000,"",0)} | E78: {=XLOOKUP(C78,'PILETAS LOTES'!$A$2:$A1000,'PILETAS LOTES'!$H$2:$H1000,"",0)}
A79: 78 | B79: 25800 | D79: {=XLOOKUP(C79,'PILETAS LOTES'!$A$2:$A1000,'PILETAS LOTES'!$F$2:$F1000,"",0)} | E79: {=XLOOKUP(C79,'PILETAS LOTES'!$A$2:$A1000,'PILETAS LOTES'!$H$2:$H1000,"",0)}
A80: 79 | B80: 26000 | D80: {=XLOOKUP(C80,'PILETAS LOTES'!$A$2:$A1000,'PILETAS LOTES'!$F$2:$F1000,"",0)} | E80: {=XLOOKUP(C80,'PILETAS LOTES'!$A$2:$A1000,'PILETAS LOTES'!$H$2:$H1000,"",0)}
A81: 80 | B81: 26100 | D81: {=XLOOKUP(C81,'PILETAS LOTES'!$A$2:$A1000,'PILETAS LOTES'!$F$2:$F1000,"",0)} | E81: {=XLOOKUP(C81,'PILETAS LOTES'!$A$2:$A1000,'PILETAS LOTES'!$H$2:$H1000,"",0)}
A82: 81 | B82: 26500 | D82: {=XLOOKUP(C82,'PILETAS LOTES'!$A$2:$A1000,'PILETAS LOTES'!$F$2:$F1000,"",0)} | E82: {=XLOOKUP(C82,'PILETAS LOTES'!$A$2:$A1000,'PILETAS LOTES'!$H$2:$H1000,"",0)}
A83: 82 | B83: 42600 | D83: {=XLOOKUP(C83,'PILETAS LOTES'!$A$2:$A1000,'PILETAS LOTES'!$F$2:$F1000,"",0)} | E83: {=XLOOKUP(C83,'PILETAS LOTES'!$A$2:$A1000,'PILETAS LOTES'!$H$2:$H1000,"",0)}
A84: 83 | B84: 81500 | C84: 32396d27 | D84: {=XLOOKUP(C84,'PILETAS LOTES'!$A$2:$A1000,'PILETAS LOTES'!$F$2:$F1000,"",0)} | E84: {=XLOOKUP(C84,'PILETAS LOTES'!$A$2:$A1000,'PILETAS LOTES'!$H$2:$H1000,"",0)}
A85: 84 | B85: 83000 | C85: 52e2d0ea | D85: {=XLOOKUP(C85,'PILETAS LOTES'!$A$2:$A1000,'PILETAS LOTES'!$F$2:$F1000,"",0)} | E85: {=XLOOKUP(C85,'PILETAS LOTES'!$A$2:$A1000,'PILETAS LOTES'!$H$2:$H1000,"",0)}
A86: 85 | B86: 84000 | C86: dc08aecd | D86: {=XLOOKUP(C86,'PILETAS LOTES'!$A$2:$A1000,'PILETAS LOTES'!$F$2:$F1000,"",0)} | E86: {=XLOOKUP(C86,'PILETAS LOTES'!$A$2:$A1000,'PILETAS LOTES'!$H$2:$H1000,"",0)}
A87: 86 | B87: 88000 | C87: 734aedeb | D87: {=XLOOKUP(C87,'PILETAS LOTES'!$A$2:$A1000,'PILETAS LOTES'!$F$2:$F1000,"",0)} | E87: {=XLOOKUP(C87,'PILETAS LOTES'!$A$2:$A1000,'PILETAS LOTES'!$H$2:$H1000,"",0)}
A88: 87 | B88: 93700 | C88: 502df566 | D88: {=XLOOKUP(C88,'PILETAS LOTES'!$A$2:$A1000,'PILETAS LOTES'!$F$2:$F1000,"",0)} | E88: {=XLOOKUP(C88,'PILETAS LOTES'!$A$2:$A1000,'PILETAS LOTES'!$H$2:$H1000,"",0)}
A89: 88 | B89: 78900 | D89: {=XLOOKUP(C89,'PILETAS LOTES'!$A$2:$A1000,'PILETAS LOTES'!$F$2:$F1000,"",0)} | E89: {=XLOOKUP(C89,'PILETAS LOTES'!$A$2:$A1000,'PILETAS LOTES'!$H$2:$H1000,"",0)}
A90: 89 | B90: 83500 | C90: 6d97827a | D90: {=XLOOKUP(C90,'PILETAS LOTES'!$A$2:$A1000,'PILETAS LOTES'!$F$2:$F1000,"",0)} | E90: {=XLOOKUP(C90,'PILETAS LOTES'!$A$2:$A1000,'PILETAS LOTES'!$H$2:$H1000,"",0)}
A91: 90 | B91: 97500 | C91: 686fc77a | D91: {=XLOOKUP(C91,'PILETAS LOTES'!$A$2:$A1000,'PILETAS LOTES'!$F$2:$F1000,"",0)} | E91: {=XLOOKUP(C91,'PILETAS LOTES'!$A$2:$A1000,'PILETAS LOTES'!$H$2:$H1000,"",0)}
A92: 91 | B92: 86000 | D92: {=XLOOKUP(C92,'PILETAS LOTES'!$A$2:$A1000,'PILETAS LOTES'!$F$2:$F1000,"",0)} | E92: {=XLOOKUP(C92,'PILETAS LOTES'!$A$2:$A1000,'PILETAS LOTES'!$H$2:$H1000,"",0)}
A93: 92 | B93: 76000 | D93: {=XLOOKUP(C93,'PILETAS LOTES'!$A$2:$A1000,'PILETAS LOTES'!$F$2:$F1000,"",0)} | E93: {=XLOOKUP(C93,'PILETAS LOTES'!$A$2:$A1000,'PILETAS LOTES'!$H$2:$H1000,"",0)}
A94: 931 | B94: 11200 | C94: 90fc33de | D94: {=XLOOKUP(C94,'PILETAS LOTES'!$A$2:$A1000,'PILETAS LOTES'!$F$2:$F1000,"",0)} | E94: {=XLOOKUP(C94,'PILETAS LOTES'!$A$2:$A1000,'PILETAS LOTES'!$H$2:$H1000,"",0)}
A95: 935 | B95: 11200 | C95: a774778b | D95: {=XLOOKUP(C95,'PILETAS LOTES'!$A$2:$A1000,'PILETAS LOTES'!$F$2:$F1000,"",0)} | E95: {=XLOOKUP(C95,'PILETAS LOTES'!$A$2:$A1000,'PILETAS LOTES'!$H$2:$H1000,"",0)}
A96: 94 | B96: 11600 | D96: {=XLOOKUP(C96,'PILETAS LOTES'!$A$2:$A1000,'PILETAS LOTES'!$F$2:$F1000,"",0)} | E96: {=XLOOKUP(C96,'PILETAS LOTES'!$A$2:$A1000,'PILETAS LOTES'!$H$2:$H1000,"",0)}
A97: 95 | B97: 77100 | D97: {=XLOOKUP(C97,'PILETAS LOTES'!$A$2:$A1000,'PILETAS LOTES'!$F$2:$F1000,"",0)} | E97: {=XLOOKUP(C97,'PILETAS LOTES'!$A$2:$A1000,'PILETAS LOTES'!$H$2:$H1000,"",0)}
A98: 96 | B98: 85600 | D98: {=XLOOKUP(C98,'PILETAS LOTES'!$A$2:$A1000,'PILETAS LOTES'!$F$2:$F1000,"",0)} | E98: {=XLOOKUP(C98,'PILETAS LOTES'!$A$2:$A1000,'PILETAS LOTES'!$H$2:$H1000,"",0)}
A99: 97 | B99: 299200 | D99: {=XLOOKUP(C99,'PILETAS LOTES'!$A$2:$A1000,'PILETAS LOTES'!$F$2:$F1000,"",0)} | E99: {=XLOOKUP(C99,'PILETAS LOTES'!$A$2:$A1000,'PILETAS LOTES'!$H$2:$H1000,"",0)}
A100: 98 | B100: 254800 | D100: {=XLOOKUP(C100,'PILETAS LOTES'!$A$2:$A1000,'PILETAS LOTES'!$F$2:$F1000,"",0)} | E100: {=XLOOKUP(C100,'PILETAS LOTES'!$A$2:$A1000,'PILETAS LOTES'!$H$2:$H1000,"",0)}
...

Sheet ANALISIS_EXPO
A1: ID_Analaisis | B1: Fecha | C1: Pileta | D1: Lote | E1: Capac | F1: Tipo | G1: Alcohol | H1: Azucar | I1: Volatil | J1: Ac. Total | K1: Ph | L1: Anhi. Libre | M1: Anhi. Total | N1: extracto seco | O1: 420 | P1: 520 | Q1: 620 | R1: Intensidad | S1: Indice | T1: Suma 420_520_620 | U1: Brix | V1: oxigeno | W1: Observaciones
A2: =IFERROR(__xludf.DUMMYFUNCTION("IMPORTRANGE(""https://docs.google.com/spreadsheets/d/1TzUfNWs0yocwDUIiqYtAe6nRr0RJptqO5h0qGqW4PVk/edit?gid=1088908225#gid=1088908225"",""BD_ANALISIS_EXPO!a2:W"")"),2.0) -> 2 | B2: =IFERROR(__xludf.DUMMYFUNCTION("""COMPUTED_VALUE"""),45308.0) -> 45308 | C2: =IFERROR(__xludf.DUMMYFUNCTION("""COMPUTED_VALUE"""),54.0) -> 54 | D2: =IFERROR(__xludf.DUMMYFUNCTION("""COMPUTED_VALUE"""),"#REF!") -> #REF! | E2: =IFERROR(__xludf.DUMMYFUNCTION("""COMPUTED_VALUE"""),22900.0) -> 22900 | F2: =IFERROR(__xludf.DUMMYFUNCTION("""COMPUTED_VALUE"""),"Malbec rectificado") -> Malbec rectificado | G2: =IFERROR(__xludf.DUMMYFUNCTION("""COMPUTED_VALUE"""),13.0) -> 13 | H2: =IFERROR(__xludf.DUMMYFUNCTION("""COMPUTED_VALUE"""),2.0) -> 2 | I2: =IFERROR(__xludf.DUMMYFUNCTION("""COMPUTED_VALUE"""),0.55) -> 0.55 | J2: =IFERROR(__xludf.DUMMYFUNCTION("""COMPUTED_VALUE"""),6.9) -> 6.9 | K2: =IFERROR(__xludf.DUMMYFUNCTION("""COMPUTED_VALUE"""),2.11) -> 2.11 | L2: =IFERROR(__xludf.DUMMYFUNCTION("""COMPUTED_VALUE"""),25.0) -> 25 | M2: =IFERROR(__xludf.DUMMYFUNCTION("""COMPUTED_VALUE"""),90.0) -> 90
A3: =IFERROR(__xludf.DUMMYFUNCTION("""COMPUTED_VALUE"""),3.0) -> 3 | B3: =IFERROR(__xludf.DUMMYFUNCTION("""COMPUTED_VALUE"""),45308.0) -> 45308 | C3: =IFERROR(__xludf.DUMMYFUNCTION("""COMPUTED_VALUE"""),15.0) -> 15 | E3: =IFERROR(__xludf.DUMMYFUNCTION("""COMPUTED_VALUE"""),36500.0) -> 36500 | F3: =IFERROR(__xludf.DUMMYFUNCTION("""COMPUTED_VALUE"""),"Malbec rectificado") -> Malbec rectificado | G3: =IFERROR(__xludf.DUMMYFUNCTION("""COMPUTED_VALUE"""),12.9) -> 12.9 | H3: =IFERROR(__xludf.DUMMYFUNCTION("""COMPUTED_VALUE"""),2.0) -> 2 | I3: =IFERROR(__xludf.DUMMYFUNCTION("""COMPUTED_VALUE"""),0.57) -> 0.57 | J3: =IFERROR(__xludf.DUMMYFUNCTION("""COMPUTED_VALUE"""),8.26) -> 8.26 | K3: =IFERROR(__xludf.DUMMYFUNCTION("""COMPUTED_VALUE"""),2.16) -> 2.16 | L3: =IFERROR(__xludf.DUMMYFUNCTION("""COMPUTED_VALUE"""),26.0) -> 26 | M3: =IFERROR(__xludf.DUMMYFUNCTION("""COMPUTED_VALUE"""),75.0) -> 75
A4: =IFERROR(__xludf.DUMMYFUNCTION("""COMPUTED_VALUE"""),4.0) -> 4 | B4: =IFERROR(__xludf.DUMMYFUNCTION("""COMPUTED_VALUE"""),45308.0) -> 45308 | C4: =IFERROR(__xludf.DUMMYFUNCTION("""COMPUTED_VALUE"""),11.0) -> 11 | D4: =IFERROR(__xludf.DUMMYFUNCTION("""COMPUTED_VALUE"""),"#REF!") -> #REF! | E4: =IFERROR(__xludf.DUMMYFUNCTION("""COMPUTED_VALUE"""),36000.0) -> 36000 | F4: =IFERROR(__xludf.DUMMYFUNCTION("""COMPUTED_VALUE"""),"blanco rectificado") -> blanco rectificado | G4: =IFERROR(__xludf.DUMMYFUNCTION("""COMPUTED_VALUE"""),10.0) -> 10 | H4: =IFERROR(__xludf.DUMMYFUNCTION("""COMPUTED_VALUE"""),2.0) -> 2 | I4: =IFERROR(__xludf.DUMMYFUNCTION("""COMPUTED_VALUE"""),0.55) -> 0.55 | J4: =IFERROR(__xludf.DUMMYFUNCTION("""COMPUTED_VALUE"""),6.12) -> 6.12 | K4: =IFERROR(__xludf.DUMMYFUNCTION("""COMPUTED_VALUE"""),2.2) -> 2.2 | L4: =IFERROR(__xludf.DUMMYFUNCTION("""COMPUTED_VALUE"""),25.0) -> 25 | M4: =IFERROR(__xludf.DUMMYFUNCTION("""COMPUTED_VALUE"""),90.0) -> 90
A5: =IFERROR(__xludf.DUMMYFUNCTION("""COMPUTED_VALUE"""),5.0) -> 5 | B5: =IFERROR(__xludf.DUMMYFUNCTION("""COMPUTED_VALUE"""),45308.0) -> 45308 | C5: =IFERROR(__xludf.DUMMYFUNCTION("""COMPUTED_VALUE"""),36.0) -> 36 | D5: =IFERROR(__xludf.DUMMYFUNCTION("""COMPUTED_VALUE"""),"1.020") -> 1.020 | E5: =IFERROR(__xludf.DUMMYFUNCTION("""COMPUTED_VALUE"""),19700.0) -> 19700 | F5: =IFERROR(__xludf.DUMMYFUNCTION("""COMPUTED_VALUE"""),"Criolla Rectificada") -> Criolla Rectificada | G5: =IFERROR(__xludf.DUMMYFUNCTION("""COMPUTED_VALUE"""),13.0) -> 13 | H5: =IFERROR(__xludf.DUMMYFUNCTION("""COMPUTED_VALUE"""),2.0) -> 2 | I5: =IFERROR(__xludf.DUMMYFUNCTION("""COMPUTED_VALUE"""),0.6) -> 0.6 | J5: =IFERROR(__xludf.DUMMYFUNCTION("""COMPUTED_VALUE"""),6.2) -> 6.2 | K5: =IFERROR(__xludf.DUMMYFUNCTION("""COMPUTED_VALUE"""),2.11) -> 2.11 | L5: =IFERROR(__xludf.DUMMYFUNCTION("""COMPUTED_VALUE"""),22.0) -> 22 | M5: =IFERROR(__xludf.DUMMYFUNCTION("""COMPUTED_VALUE"""),110.0) -> 110
A6: =IFERROR(__xludf.DUMMYFUNCTION("""COMPUTED_VALUE"""),6.0) -> 6 | B6: =IFERROR(__xludf.DUMMYFUNCTION("""COMPUTED_VALUE"""),45309.0) -> 45309 | C6: =IFERROR(__xludf.DUMMYFUNCTION("""COMPUTED_VALUE"""),16.0) -> 16 | E6: =IFERROR(__xludf.DUMMYFUNCTION("""COMPUTED_VALUE"""),19500.0) -> 19500 | F6: =IFERROR(__xludf.DUMMYFUNCTION("""COMPUTED_VALUE"""),"rosado rectificado") -> rosado rectificado | G6: =IFERROR(__xludf.DUMMYFUNCTION("""COMPUTED_VALUE"""),12.9) -> 12.9 | H6: =IFERROR(__xludf.DUMMYFUNCTION("""COMPUTED_VALUE"""),2.0) -> 2 | I6: =IFERROR(__xludf.DUMMYFUNCTION("""COMPUTED_VALUE"""),0.5) -> 0.5 | J6: =IFERROR(__xludf.DUMMYFUNCTION("""COMPUTED_VALUE"""),6.9) -> 6.9 | K6: =IFERROR(__xludf.DUMMYFUNCTION("""COMPUTED_VALUE"""),2.09) -> 2.09 | L6: =IFERROR(__xludf.DUMMYFUNCTION("""COMPUTED_VALUE"""),19.0) -> 19 | M6: =IFERROR(__xludf.DUMMYFUNCTION("""COMPUTED_VALUE"""),160.0) -> 160
A7: =IFERROR(__xludf.DUMMYFUNCTION("""COMPUTED_VALUE"""),7.0) -> 7 | B7: =IFERROR(__xludf.DUMMYFUNCTION("""COMPUTED_VALUE"""),45309.0) -> 45309 | C7: =IFERROR(__xludf.DUMMYFUNCTION("""COMPUTED_VALUE"""),42.0) -> 42 | D7: =IFERROR(__xludf.DUMMYFUNCTION("""COMPUTED_VALUE"""),"#REF!") -> #REF! | E7: =IFERROR(__xludf.DUMMYFUNCTION("""COMPUTED_VALUE"""),35900.0) -> 35900 | F7: =IFERROR(__xludf.DUMMYFUNCTION("""COMPUTED_VALUE"""),"Cabernet Sauvignon rectificado") -> Cabernet Sauvignon rectificado | G7: =IFERROR(__xludf.DUMMYFUNCTION("""COMPUTED_VALUE"""),13.0) -> 13 | H7: =IFERROR(__xludf.DUMMYFUNCTION("""COMPUTED_VALUE"""),2.0) -> 2 | I7: =IFERROR(__xludf.DUMMYFUNCTION("""COMPUTED_VALUE"""),0.57) -> 0.57 | J7: =IFERROR(__xludf.DUMMYFUNCTION("""COMPUTED_VALUE"""),8.8) -> 8.8 | K7: =IFERROR(__xludf.DUMMYFUNCTION("""COMPUTED_VALUE"""),2.21) -> 2.21 | L7: =IFERROR(__xludf.DUMMYFUNCTION("""COMPUTED_VALUE"""),25.0) -> 25 | M7: =IFERROR(__xludf.DUMMYFUNCTION("""COMPUTED_VALUE"""),100.0) -> 100
A8: =IFERROR(__xludf.DUMMYFUNCTION("""COMPUTED_VALUE"""),8.0) -> 8 | B8: =IFERROR(__xludf.DUMMYFUNCTION("""COMPUTED_VALUE"""),45313.0) -> 45313 | C8: =IFERROR(__xludf.DUMMYFUNCTION("""COMPUTED_VALUE"""),48.0) -> 48 | D8: =IFERROR(__xludf.DUMMYFUNCTION("""COMPUTED_VALUE"""),"#REF!") -> #REF! | E8: =IFERROR(__xludf.DUMMYFUNCTION("""COMPUTED_VALUE"""),26000.0) -> 26000 | F8: =IFERROR(__xludf.DUMMYFUNCTION("""COMPUTED_VALUE"""),"Cabernet Sauvignon rectificado") -> Cabernet Sauvignon rectificado | G8: =IFERROR(__xludf.DUMMYFUNCTION("""COMPUTED_VALUE"""),12.8) -> 12.8 | H8: =IFERROR(__xludf.DUMMYFUNCTION("""COMPUTED_VALUE"""),2.0) -> 2 | I8: =IFERROR(__xludf.DUMMYFUNCTION("""COMPUTED_VALUE"""),0.53) -> 0.53 | J8: =IFERROR(__xludf.DUMMYFUNCTION("""COMPUTED_VALUE"""),8.4) -> 8.4 | K8: =IFERROR(__xludf.DUMMYFUNCTION("""COMPUTED_VALUE"""),2.16) -> 2.16 | L8: =IFERROR(__xludf.DUMMYFUNCTION("""COMPUTED_VALUE"""),25.0) -> 25 | M8: =IFERROR(__xludf.DUMMYFUNCTION("""COMPUTED_VALUE"""),90.0) -> 90
A9: =IFERROR(__xludf.DUMMYFUNCTION("""COMPUTED_VALUE"""),9.0) -> 9 | B9: =IFERROR(__xludf.DUMMYFUNCTION("""COMPUTED_VALUE"""),45314.0) -> 45314 | C9: =IFERROR(__xludf.DUMMYFUNCTION("""COMPUTED_VALUE"""),49.0) -> 49 | D9: =IFERROR(__xludf.DUMMYFUNCTION("""COMPUTED_VALUE"""),"#REF!") -> #REF! | E9: =IFERROR(__xludf.DUMMYFUNCTION("""COMPUTED_VALUE"""),26000.0) -> 26000 | F9: =IFERROR(__xludf.DUMMYFUNCTION("""COMPUTED_VALUE"""),"Cabernet Sauvignon rectificado") -> Cabernet Sauvignon rectificado | G9: =IFERROR(__xludf.DUMMYFUNCTION("""COMPUTED_VALUE"""),12.7) -> 12.7 | H9: =IFERROR(__xludf.DUMMYFUNCTION("""COMPUTED_VALUE"""),2.0) -> 2 | I9: =IFERROR(__xludf.DUMMYFUNCTION("""COMPUTED_VALUE"""),0.57) -> 0.57 | J9: =IFERROR(__xludf.DUMMYFUNCTION("""COMPUTED_VALUE"""),8.3) -> 8.3 | K9: =IFERROR(__xludf.DUMMYFUNCTION("""COMPUTED_VALUE"""),2.18) -> 2.18 | L9: =IFERROR(__xludf.DUMMYFUNCTION("""COMPUTED_VALUE"""),27.0) -> 27 | M9: =IFERROR(__xludf.DUMMYFUNCTION("""COMPUTED_VALUE"""),110.0) -> 110
A10: =IFERROR(__xludf.DUMMYFUNCTION("""COMPUTED_VALUE"""),10.0) -> 10 | C10: =IFERROR(__xludf.DUMMYFUNCTION("""COMPUTED_VALUE"""),41.0) -> 41 | D10: =IFERROR(__xludf.DUMMYFUNCTION("""COMPUTED_VALUE"""),"#REF!") -> #REF! | E10: =IFERROR(__xludf.DUMMYFUNCTION("""COMPUTED_VALUE"""),35100.0) -> 35100 | F10: =IFERROR(__xludf.DUMMYFUNCTION("""COMPUTED_VALUE"""),"Cabernet sauvignon recticado") -> Cabernet sauvignon recticado
A11: =IFERROR(__xludf.DUMMYFUNCTION("""COMPUTED_VALUE"""),11.0) -> 11 | B11: =IFERROR(__xludf.DUMMYFUNCTION("""COMPUTED_VALUE"""),44950.0) -> 44950 | C11: =IFERROR(__xludf.DUMMYFUNCTION("""COMPUTED_VALUE"""),50.0) -> 50 | F11: =IFERROR(__xludf.DUMMYFUNCTION("""COMPUTED_VALUE"""),"Malbec montecepas") -> Malbec montecepas | G11: =IFERROR(__xludf.DUMMYFUNCTION("""COMPUTED_VALUE"""),13.1) -> 13.1 | H11: =IFERROR(__xludf.DUMMYFUNCTION("""COMPUTED_VALUE"""),2.0) -> 2 | I11: =IFERROR(__xludf.DUMMYFUNCTION("""COMPUTED_VALUE"""),0.55) -> 0.55 | J11: =IFERROR(__xludf.DUMMYFUNCTION("""COMPUTED_VALUE"""),5.2) -> 5.2 | K11: =IFERROR(__xludf.DUMMYFUNCTION("""COMPUTED_VALUE"""),3.7) -> 3.7 | L11: =IFERROR(__xludf.DUMMYFUNCTION("""COMPUTED_VALUE"""),40.0) -> 40 | M11: =IFERROR(__xludf.DUMMYFUNCTION("""COMPUTED_VALUE"""),130.0) -> 130
A12: =IFERROR(__xludf.DUMMYFUNCTION("""COMPUTED_VALUE"""),12.0) -> 12 | B12: =IFERROR(__xludf.DUMMYFUNCTION("""COMPUTED_VALUE"""),45321.0) -> 45321 | C12: =IFERROR(__xludf.DUMMYFUNCTION("""COMPUTED_VALUE"""),9.0) -> 9 | I12: =IFERROR(__xludf.DUMMYFUNCTION("""COMPUTED_VALUE"""),0.57) -> 0.57 | K12: =IFERROR(__xludf.DUMMYFUNCTION("""COMPUTED_VALUE"""),3.6) -> 3.6 | L12: =IFERROR(__xludf.DUMMYFUNCTION("""COMPUTED_VALUE"""),38.0) -> 38 | M12: =IFERROR(__xludf.DUMMYFUNCTION("""COMPUTED_VALUE"""),120.0) -> 120
A13: =IFERROR(__xludf.DUMMYFUNCTION("""COMPUTED_VALUE"""),13.0) -> 13 | B13: =IFERROR(__xludf.DUMMYFUNCTION("""COMPUTED_VALUE"""),44950.0) -> 44950 | C13: =IFERROR(__xludf.DUMMYFUNCTION("""COMPUTED_VALUE"""),51.0) -> 51 | D13: =IFERROR(__xludf.DUMMYFUNCTION("""COMPUTED_VALUE"""),"1.021") -> 1.021 | E13: =IFERROR(__xludf.DUMMYFUNCTION("""COMPUTED_VALUE"""),2500.0) -> 2500 | F13: =IFERROR(__xludf.DUMMYFUNCTION("""COMPUTED_VALUE"""),"Syrah Malbec") -> Syrah Malbec | G13: =IFERROR(__xludf.DUMMYFUNCTION("""COMPUTED_VALUE"""),13.0) -> 13 | H13: =IFERROR(__xludf.DUMMYFUNCTION("""COMPUTED_VALUE"""),2.0) -> 2 | I13: =IFERROR(__xludf.DUMMYFUNCTION("""COMPUTED_VALUE"""),0.5) -> 0.5 | J13: =IFERROR(__xludf.DUMMYFUNCTION("""COMPUTED_VALUE"""),5.2) -> 5.2 | K13: =IFERROR(__xludf.DUMMYFUNCTION("""COMPUTED_VALUE"""),3.65) -> 3.65 | L13: =IFERROR(__xludf.DUMMYFUNCTION("""COMPUTED_VALUE"""),40.0) -> 40 | M13: =IFERROR(__xludf.DUMMYFUNCTION("""COMPUTED_VALUE"""),100.0) -> 100
A14: =IFERROR(__xludf.DUMMYFUNCTION("""COMPUTED_VALUE"""),14.0) -> 14 | B14: =IFERROR(__xludf.DUMMYFUNCTION("""COMPUTED_VALUE"""),45327.0) -> 45327 | C14: =IFERROR(__xludf.DUMMYFUNCTION("""COMPUTED_VALUE"""),32.0) -> 32 | D14: =IFERROR(__xludf.DUMMYFUNCTION("""COMPUTED_VALUE"""),"#REF!") -> #REF! | E14: =IFERROR(__xludf.DUMMYFUNCTION("""COMPUTED_VALUE"""),36300.0) -> 36300 | F14: =IFERROR(__xludf.DUMMYFUNCTION("""COMPUTED_VALUE"""),"Merlot-syrah 2023") -> Merlot-syrah 2023 | G14: =IFERROR(__xludf.DUMMYFUNCTION("""COMPUTED_VALUE"""),13.2) -> 13.2 | H14: =IFERROR(__xludf.DUMMYFUNCTION("""COMPUTED_VALUE"""),2.0) -> 2 | I14: =IFERROR(__xludf.DUMMYFUNCTION("""COMPUTED_VALUE"""),0.5) -> 0.5 | J14: =IFERROR(__xludf.DUMMYFUNCTION("""COMPUTED_VALUE"""),5.25) -> 5.25 | K14: =IFERROR(__xludf.DUMMYFUNCTION("""COMPUTED_VALUE"""),3.8) -> 3.8 | L14: =IFERROR(__xludf.DUMMYFUNCTION("""COMPUTED_VALUE"""),45.0) -> 45 | M14: =IFERROR(__xludf.DUMMYFUNCTION("""COMPUTED_VALUE"""),130.0) -> 130
A15: =IFERROR(__xludf.DUMMYFUNCTION("""COMPUTED_VALUE"""),15.0) -> 15 | B15: =IFERROR(__xludf.DUMMYFUNCTION("""COMPUTED_VALUE"""),45327.0) -> 45327 | C15: =IFERROR(__xludf.DUMMYFUNCTION("""COMPUTED_VALUE"""),65.0) -> 65 | D15: =IFERROR(__xludf.DUMMYFUNCTION("""COMPUTED_VALUE"""),"#REF!") -> #REF! | E15: =IFERROR(__xludf.DUMMYFUNCTION("""COMPUTED_VALUE"""),17000.0) -> 17000 | F15: =IFERROR(__xludf.DUMMYFUNCTION("""COMPUTED_VALUE"""),"chardonnay-Sauvignon blanc -24") -> chardonnay-Sauvignon blanc -24 | H15: =IFERROR(__xludf.DUMMYFUNCTION("""COMPUTED_VALUE"""),214.0) -> 214 | K15: =IFERROR(__xludf.DUMMYFUNCTION("""COMPUTED_VALUE"""),3.6) -> 3.6
A16: =IFERROR(__xludf.DUMMYFUNCTION("""COMPUTED_VALUE"""),16.0) -> 16 | B16: =IFERROR(__xludf.DUMMYFUNCTION("""COMPUTED_VALUE"""),45327.0) -> 45327 | C16: =IFERROR(__xludf.DUMMYFUNCTION("""COMPUTED_VALUE"""),82.0) -> 82 | D16: =IFERROR(__xludf.DUMMYFUNCTION("""COMPUTED_VALUE"""),"#REF!") -> #REF! | E16: =IFERROR(__xludf.DUMMYFUNCTION("""COMPUTED_VALUE"""),40000.0) -> 40000 | F16: =IFERROR(__xludf.DUMMYFUNCTION("""COMPUTED_VALUE"""),"chardonnay-Sauvignon blanc -24") -> chardonnay-Sauvignon blanc -24 | K16: =IFERROR(__xludf.DUMMYFUNCTION("""COMPUTED_VALUE"""),3.32) -> 3.32
A17: =IFERROR(__xludf.DUMMYFUNCTION("""COMPUTED_VALUE"""),17.0) -> 17 | B17: =IFERROR(__xludf.DUMMYFUNCTION("""COMPUTED_VALUE"""),45327.0) -> 45327 | C17: =IFERROR(__xludf.DUMMYFUNCTION("""COMPUTED_VALUE"""),81.0) -> 81 | D17: =IFERROR(__xludf.DUMMYFUNCTION("""COMPUTED_VALUE"""),"#REF!") -> #REF! | E17: =IFERROR(__xludf.DUMMYFUNCTION("""COMPUTED_VALUE"""),25000.0) -> 25000 | F17: =IFERROR(__xludf.DUMMYFUNCTION("""COMPUTED_VALUE"""),"chardonnay-Sauvignon blanc -24") -> chardonnay-Sauvignon blanc -24 | K17: =IFERROR(__xludf.DUMMYFUNCTION("""COMPUTED_VALUE"""),3.33) -> 3.33
A18: =IFERROR(__xludf.DUMMYFUNCTION("""COMPUTED_VALUE"""),18.0) -> 18 | B18: =IFERROR(__xludf.DUMMYFUNCTION("""COMPUTED_VALUE"""),45328.0) -> 45328 | C18: =IFERROR(__xludf.DUMMYFUNCTION("""COMPUTED_VALUE"""),65.0) -> 65 | D18: =IFERROR(__xludf.DUMMYFUNCTION("""COMPUTED_VALUE"""),"#REF!") -> #REF! | F18: =IFERROR(__xludf.DUMMYFUNCTION("""COMPUTED_VALUE"""),"chardonnay") -> chardonnay | H18: =IFERROR(__xludf.DUMMYFUNCTION("""COMPUTED_VALUE"""),208.0) -> 208 | K18: =IFERROR(__xludf.DUMMYFUNCTION("""COMPUTED_VALUE"""),3.6) -> 3.6
A19: =IFERROR(__xludf.DUMMYFUNCTION("""COMPUTED_VALUE"""),19.0) -> 19 | B19: =IFERROR(__xludf.DUMMYFUNCTION("""COMPUTED_VALUE"""),45329.0) -> 45329 | C19: =IFERROR(__xludf.DUMMYFUNCTION("""COMPUTED_VALUE"""),82.0) -> 82 | D19: =IFERROR(__xludf.DUMMYFUNCTION("""COMPUTED_VALUE"""),"#REF!") -> #REF! | F19: =IFERROR(__xludf.DUMMYFUNCTION("""COMPUTED_VALUE"""),"Chardonnay") -> Chardonnay | H19: =IFERROR(__xludf.DUMMYFUNCTION("""COMPUTED_VALUE"""),6.0) -> 6 | J19: =IFERROR(__xludf.DUMMYFUNCTION("""COMPUTED_VALUE"""),7.3) -> 7.3 | K19: =IFERROR(__xludf.DUMMYFUNCTION("""COMPUTED_VALUE"""),3.3) -> 3.3
A20: =IFERROR(__xludf.DUMMYFUNCTION("""COMPUTED_VALUE"""),20.0) -> 20 | B20: =IFERROR(__xludf.DUMMYFUNCTION("""COMPUTED_VALUE"""),45330.0) -> 45330 | C20: =IFERROR(__xludf.DUMMYFUNCTION("""COMPUTED_VALUE"""),82.0) -> 82 | D20: =IFERROR(__xludf.DUMMYFUNCTION("""COMPUTED_VALUE"""),"#REF!") -> #REF! | F20: =IFERROR(__xludf.DUMMYFUNCTION("""COMPUTED_VALUE"""),"Chardonnay") -> Chardonnay | G20: =IFERROR(__xludf.DUMMYFUNCTION("""COMPUTED_VALUE"""),11.9) -> 11.9 | H20: =IFERROR(__xludf.DUMMYFUNCTION("""COMPUTED_VALUE"""),2.0) -> 2 | I20: =IFERROR(__xludf.DUMMYFUNCTION("""COMPUTED_VALUE"""),0.28) -> 0.28 | J20: =IFERROR(__xludf.DUMMYFUNCTION("""COMPUTED_VALUE"""),7.3) -> 7.3 | K20: =IFERROR(__xludf.DUMMYFUNCTION("""COMPUTED_VALUE"""),3.26) -> 3.26 | L20: =IFERROR(__xludf.DUMMYFUNCTION("""COMPUTED_VALUE"""),25.0) -> 25 | M20: =IFERROR(__xludf.DUMMYFUNCTION("""COMPUTED_VALUE"""),80.0) -> 80
A21: =IFERROR(__xludf.DUMMYFUNCTION("""COMPUTED_VALUE"""),21.0) -> 21 | B21: =IFERROR(__xludf.DUMMYFUNCTION("""COMPUTED_VALUE"""),45330.0) -> 45330 | C21: =IFERROR(__xludf.DUMMYFUNCTION("""COMPUTED_VALUE"""),81.0) -> 81 | D21: =IFERROR(__xludf.DUMMYFUNCTION("""COMPUTED_VALUE"""),"#REF!") -> #REF! | F21: =IFERROR(__xludf.DUMMYFUNCTION("""COMPUTED_VALUE"""),"Chardonnay") -> Chardonnay | G21: =IFERROR(__xludf.DUMMYFUNCTION("""COMPUTED_VALUE"""),12.0) -> 12 | H21: =IFERROR(__xludf.DUMMYFUNCTION("""COMPUTED_VALUE"""),8.0) -> 8 | I21: =IFERROR(__xludf.DUMMYFUNCTION("""COMPUTED_VALUE"""),0.3) -> 0.3 | J21: =IFERROR(__xludf.DUMMYFUNCTION("""COMPUTED_VALUE"""),7.5) -> 7.5 | K21: =IFERROR(__xludf.DUMMYFUNCTION("""COMPUTED_VALUE"""),3.25) -> 3.25 | L21: =IFERROR(__xludf.DUMMYFUNCTION("""COMPUTED_VALUE"""),13.0) -> 13 | M21: =IFERROR(__xludf.DUMMYFUNCTION("""COMPUTED_VALUE"""),76.0) -> 76
A22: =IFERROR(__xludf.DUMMYFUNCTION("""COMPUTED_VALUE"""),22.0) -> 22 | B22: =IFERROR(__xludf.DUMMYFUNCTION("""COMPUTED_VALUE"""),45334.0) -> 45334 | C22: =IFERROR(__xludf.DUMMYFUNCTION("""COMPUTED_VALUE"""),82.0) -> 82 | D22: =IFERROR(__xludf.DUMMYFUNCTION("""COMPUTED_VALUE"""),"#REF!") -> #REF! | F22: =IFERROR(__xludf.DUMMYFUNCTION("""COMPUTED_VALUE"""),"chardonay") -> chardonay | J22: =IFERROR(__xludf.DUMMYFUNCTION("""COMPUTED_VALUE"""),6.5) -> 6.5 | K22: =IFERROR(__xludf.DUMMYFUNCTION("""COMPUTED_VALUE"""),3.5) -> 3.5 | M22: =IFERROR(__xludf.DUMMYFUNCTION("""COMPUTED_VALUE"""),25.0) -> 25
A23: =IFERROR(__xludf.DUMMYFUNCTION("""COMPUTED_VALUE"""),23.0) -> 23 | B23: =IFERROR(__xludf.DUMMYFUNCTION("""COMPUTED_VALUE"""),45334.0) -> 45334 | C23: =IFERROR(__xludf.DUMMYFUNCTION("""COMPUTED_VALUE"""),81.0) -> 81 | D23: =IFERROR(__xludf.DUMMYFUNCTION("""COMPUTED_VALUE"""),"#REF!") -> #REF! | F23: =IFERROR(__xludf.DUMMYFUNCTION("""COMPUTED_VALUE"""),"Chardonnay") -> Chardonnay | G23: =IFERROR(__xludf.DUMMYFUNCTION("""COMPUTED_VALUE"""),12.2) -> 12.2 | H23: =IFERROR(__xludf.DUMMYFUNCTION("""COMPUTED_VALUE"""),2.0) -> 2 | J23: =IFERROR(__xludf.DUMMYFUNCTION("""COMPUTED_VALUE"""),6.2) -> 6.2 | K23: =IFERROR(__xludf.DUMMYFUNCTION("""COMPUTED_VALUE"""),3.55) -> 3.55 | M23: =IFERROR(__xludf.DUMMYFUNCTION("""COMPUTED_VALUE"""),20.0) -> 20
A24: =IFERROR(__xludf.DUMMYFUNCTION("""COMPUTED_VALUE"""),24.0) -> 24 | B24: =IFERROR(__xludf.DUMMYFUNCTION("""COMPUTED_VALUE"""),45335.0) -> 45335 | C24: =IFERROR(__xludf.DUMMYFUNCTION("""COMPUTED_VALUE"""),65.0) -> 65 | D24: =IFERROR(__xludf.DUMMYFUNCTION("""COMPUTED_VALUE"""),"#REF!") -> #REF! | F24: =IFERROR(__xludf.DUMMYFUNCTION("""COMPUTED_VALUE"""),"Chardonnay") -> Chardonnay | G24: =IFERROR(__xludf.DUMMYFUNCTION("""COMPUTED_VALUE"""),12.2) -> 12.2 | H24: =IFERROR(__xludf.DUMMYFUNCTION("""COMPUTED_VALUE"""),2.0) -> 2 | J24: =IFERROR(__xludf.DUMMYFUNCTION("""COMPUTED_VALUE"""),6.5) -> 6.5 | K24: =IFERROR(__xludf.DUMMYFUNCTION("""COMPUTED_VALUE"""),3.6) -> 3.6 | L24: =IFERROR(__xludf.DUMMYFUNCTION("""COMPUTED_VALUE"""),15.0) -> 15
A25: =IFERROR(__xludf.DUMMYFUNCTION("""COMPUTED_VALUE"""),25.0) -> 25 | B25: =IFERROR(__xludf.DUMMYFUNCTION("""COMPUTED_VALUE"""),45335.0) -> 45335 | C25: =IFERROR(__xludf.DUMMYFUNCTION("""COMPUTED_VALUE"""),66.0) -> 66 | D25: =IFERROR(__xludf.DUMMYFUNCTION("""COMPUTED_VALUE"""),"#REF!") -> #REF! | F25: =IFERROR(__xludf.DUMMYFUNCTION("""COMPUTED_VALUE"""),"Chardonnay") -> Chardonnay | G25: =IFERROR(__xludf.DUMMYFUNCTION("""COMPUTED_VALUE"""),12.5) -> 12.5 | H25: =IFERROR(__xludf.DUMMYFUNCTION("""COMPUTED_VALUE"""),2.0) -> 2 | J25: =IFERROR(__xludf.DUMMYFUNCTION("""COMPUTED_VALUE"""),6.12) -> 6.12 | K25: =IFERROR(__xludf.DUMMYFUNCTION("""COMPUTED_VALUE"""),3.53) -> 3.53 | L25: =IFERROR(__xludf.DUMMYFUNCTION("""COMPUTED_VALUE"""),25.0) -> 25
A26: =IFERROR(__xludf.DUMMYFUNCTION("""COMPUTED_VALUE"""),26.0) -> 26 | B26: =IFERROR(__xludf.DUMMYFUNCTION("""COMPUTED_VALUE"""),45335.0) -> 45335 | C26: =IFERROR(__xludf.DUMMYFUNCTION("""COMPUTED_VALUE"""),67.0) -> 67 | D26: =IFERROR(__xludf.DUMMYFUNCTION("""COMPUTED_VALUE"""),"#REF!") -> #REF! | F26: =IFERROR(__xludf.DUMMYFUNCTION("""COMPUTED_VALUE"""),"Chardonnnay") -> Chardonnnay | G26: =IFERROR(__xludf.DUMMYFUNCTION("""COMPUTED_VALUE"""),11.8) -> 11.8 | H26: =IFERROR(__xludf.DUMMYFUNCTION("""COMPUTED_VALUE"""),2.0) -> 2 | J26: =IFERROR(__xludf.DUMMYFUNCTION("""COMPUTED_VALUE"""),6.04) -> 6.04 | K26: =IFERROR(__xludf.DUMMYFUNCTION("""COMPUTED_VALUE"""),3.55) -> 3.55 | L26: =IFERROR(__xludf.DUMMYFUNCTION("""COMPUTED_VALUE"""),18.0) -> 18
A27: =IFERROR(__xludf.DUMMYFUNCTION("""COMPUTED_VALUE"""),27.0) -> 27 | B27: =IFERROR(__xludf.DUMMYFUNCTION("""COMPUTED_VALUE"""),45335.0) -> 45335 | C27: =IFERROR(__xludf.DUMMYFUNCTION("""COMPUTED_VALUE"""),80.0) -> 80 | F27: =IFERROR(__xludf.DUMMYFUNCTION("""COMPUTED_VALUE"""),"Chardonnay") -> Chardonnay | G27: =IFERROR(__xludf.DUMMYFUNCTION("""COMPUTED_VALUE"""),13.0) -> 13 | H27: =IFERROR(__xludf.DUMMYFUNCTION("""COMPUTED_VALUE"""),2.0) -> 2 | J27: =IFERROR(__xludf.DUMMYFUNCTION("""COMPUTED_VALUE"""),5.9) -> 5.9 | K27: =IFERROR(__xludf.DUMMYFUNCTION("""COMPUTED_VALUE"""),3.47) -> 3.47 | L27: =IFERROR(__xludf.DUMMYFUNCTION("""COMPUTED_VALUE"""),18.0) -> 18
A28: =IFERROR(__xludf.DUMMYFUNCTION("""COMPUTED_VALUE"""),28.0) -> 28 | B28: =IFERROR(__xludf.DUMMYFUNCTION("""COMPUTED_VALUE"""),45336.0) -> 45336 | C28: =IFERROR(__xludf.DUMMYFUNCTION("""COMPUTED_VALUE"""),79.0) -> 79 | D28: =IFERROR(__xludf.DUMMYFUNCTION("""COMPUTED_VALUE"""),"#REF!") -> #REF! | F28: =IFERROR(__xludf.DUMMYFUNCTION("""COMPUTED_VALUE"""),"Chardonnay") -> Chardonnay | G28: =IFERROR(__xludf.DUMMYFUNCTION("""COMPUTED_VALUE"""),12.0) -> 12 | H28: =IFERROR(__xludf.DUMMYFUNCTION("""COMPUTED_VALUE"""),2.0) -> 2 | J28: =IFERROR(__xludf.DUMMYFUNCTION("""COMPUTED_VALUE"""),6.2) -> 6.2 | K28: =IFERROR(__xludf.DUMMYFUNCTION("""COMPUTED_VALUE"""),3.45) -> 3.45 | L28: =IFERROR(__xludf.DUMMYFUNCTION("""COMPUTED_VALUE"""),12.0) -> 12
A29: =IFERROR(__xludf.DUMMYFUNCTION("""COMPUTED_VALUE"""),29.0) -> 29 | B29: =IFERROR(__xludf.DUMMYFUNCTION("""COMPUTED_VALUE"""),45336.0) -> 45336 | C29: =IFERROR(__xludf.DUMMYFUNCTION("""COMPUTED_VALUE"""),83.0) -> 83 | D29: =IFERROR(__xludf.DUMMYFUNCTION("""COMPUTED_VALUE"""),"#REF!") -> #REF! | F29: =IFERROR(__xludf.DUMMYFUNCTION("""COMPUTED_VALUE"""),"aspirant") -> aspirant
A30: =IFERROR(__xludf.DUMMYFUNCTION("""COMPUTED_VALUE"""),30.0) -> 30 | B30: =IFERROR(__xludf.DUMMYFUNCTION("""COMPUTED_VALUE"""),45339.0) -> 45339 | C30: =IFERROR(__xludf.DUMMYFUNCTION("""COMPUTED_VALUE"""),90.0) -> 90 | L30: =IFERROR(__xludf.DUMMYFUNCTION("""COMPUTED_VALUE"""),33.0) -> 33
A31: =IFERROR(__xludf.DUMMYFUNCTION("""COMPUTED_VALUE"""),31.0) -> 31 | B31: =IFERROR(__xludf.DUMMYFUNCTION("""COMPUTED_VALUE"""),45341.0) -> 45341 | C31: =IFERROR(__xludf.DUMMYFUNCTION("""COMPUTED_VALUE"""),78.0) -> 78 | G31: =IFERROR(__xludf.DUMMYFUNCTION("""COMPUTED_VALUE"""),11.5) -> 11.5 | H31: =IFERROR(__xludf.DUMMYFUNCTION("""COMPUTED_VALUE"""),2.0) -> 2 | I31: =IFERROR(__xludf.DUMMYFUNCTION("""COMPUTED_VALUE"""),0.3) -> 0.3 | J31: =IFERROR(__xludf.DUMMYFUNCTION("""COMPUTED_VALUE"""),7.3) -> 7.3 | K31: =IFERROR(__xludf.DUMMYFUNCTION("""COMPUTED_VALUE"""),3.26) -> 3.26 | L31: =IFERROR(__xludf.DUMMYFUNCTION("""COMPUTED_VALUE"""),12.0) -> 12
A32: =IFERROR(__xludf.DUMMYFUNCTION("""COMPUTED_VALUE"""),32.0) -> 32 | B32: =IFERROR(__xludf.DUMMYFUNCTION("""COMPUTED_VALUE"""),45341.0) -> 45341 | C32: =IFERROR(__xludf.DUMMYFUNCTION("""COMPUTED_VALUE"""),77.0) -> 77 | D32: =IFERROR(__xludf.DUMMYFUNCTION("""COMPUTED_VALUE"""),"1.083") -> 1.083 | E32: =IFERROR(__xludf.DUMMYFUNCTION("""COMPUTED_VALUE"""),18579.600000000002) -> 18579.6 | F32: =IFERROR(__xludf.DUMMYFUNCTION("""COMPUTED_VALUE"""),"Pedro Gimenez") -> Pedro Gimenez | H32: =IFERROR(__xludf.DUMMYFUNCTION("""COMPUTED_VALUE"""),2.25) -> 2.25
A33: =IFERROR(__xludf.DUMMYFUNCTION("""COMPUTED_VALUE"""),33.0) -> 33 | B33: =IFERROR(__xludf.DUMMYFUNCTION("""COMPUTED_VALUE"""),45341.0) -> 45341 | C33: =IFERROR(__xludf.DUMMYFUNCTION("""COMPUTED_VALUE"""),83.0) -> 83 | D33: =IFERROR(__xludf.DUMMYFUNCTION("""COMPUTED_VALUE"""),"1.108") -> 1.108 | E33: =IFERROR(__xludf.DUMMYFUNCTION("""COMPUTED_VALUE"""),47642.4) -> 47642.4 | F33: =IFERROR(__xludf.DUMMYFUNCTION("""COMPUTED_VALUE"""),"Bonarda") -> Bonarda | H33: =IFERROR(__xludf.DUMMYFUNCTION("""COMPUTED_VALUE"""),2.25) -> 2.25
A34: =IFERROR(__xludf.DUMMYFUNCTION("""COMPUTED_VALUE"""),34.0) -> 34 | B34: =IFERROR(__xludf.DUMMYFUNCTION("""COMPUTED_VALUE"""),45341.0) -> 45341 | C34: =IFERROR(__xludf.DUMMYFUNCTION("""COMPUTED_VALUE"""),67.0) -> 67 | K34: =IFERROR(__xludf.DUMMYFUNCTION("""COMPUTED_VALUE"""),3.45) -> 3.45 | L34: =IFERROR(__xludf.DUMMYFUNCTION("""COMPUTED_VALUE"""),25.0) -> 25 | M34: =IFERROR(__xludf.DUMMYFUNCTION("""COMPUTED_VALUE"""),102.0) -> 102
A35: =IFERROR(__xludf.DUMMYFUNCTION("""COMPUTED_VALUE"""),35.0) -> 35 | B35: =IFERROR(__xludf.DUMMYFUNCTION("""COMPUTED_VALUE"""),45341.0) -> 45341 | C35: =IFERROR(__xludf.DUMMYFUNCTION("""COMPUTED_VALUE"""),80.0) -> 80 | D35: =IFERROR(__xludf.DUMMYFUNCTION("""COMPUTED_VALUE"""),"1.100") -> 1.100 | E35: =IFERROR(__xludf.DUMMYFUNCTION("""COMPUTED_VALUE"""),18657.600000000002) -> 18657.6 | F35: =IFERROR(__xludf.DUMMYFUNCTION("""COMPUTED_VALUE"""),"Syrah") -> Syrah | K35: =IFERROR(__xludf.DUMMYFUNCTION("""COMPUTED_VALUE"""),3.43) -> 3.43 | L35: =IFERROR(__xludf.DUMMYFUNCTION("""COMPUTED_VALUE"""),24.0) -> 24 | M35: =IFERROR(__xludf.DUMMYFUNCTION("""COMPUTED_VALUE"""),83.0) -> 83
A36: =IFERROR(__xludf.DUMMYFUNCTION("""COMPUTED_VALUE"""),36.0) -> 36 | B36: =IFERROR(__xludf.DUMMYFUNCTION("""COMPUTED_VALUE"""),45341.0) -> 45341 | C36: =IFERROR(__xludf.DUMMYFUNCTION("""COMPUTED_VALUE"""),74.0) -> 74 | D36: =IFERROR(__xludf.DUMMYFUNCTION("""COMPUTED_VALUE"""),"1.106") -> 1.106 | E36: =IFERROR(__xludf.DUMMYFUNCTION("""COMPUTED_VALUE"""),13000.0) -> 13000 | F36: =IFERROR(__xludf.DUMMYFUNCTION("""COMPUTED_VALUE"""),"Syrah P") -> Syrah P | K36: =IFERROR(__xludf.DUMMYFUNCTION("""COMPUTED_VALUE"""),3.4) -> 3.4 | L36: =IFERROR(__xludf.DUMMYFUNCTION("""COMPUTED_VALUE"""),20.0) -> 20 | M36: =IFERROR(__xludf.DUMMYFUNCTION("""COMPUTED_VALUE"""),85.0) -> 85
A37: =IFERROR(__xludf.DUMMYFUNCTION("""COMPUTED_VALUE"""),37.0) -> 37 | B37: =IFERROR(__xludf.DUMMYFUNCTION("""COMPUTED_VALUE"""),45341.0) -> 45341 | C37: =IFERROR(__xludf.DUMMYFUNCTION("""COMPUTED_VALUE"""),81.0) -> 81 | K37: =IFERROR(__xludf.DUMMYFUNCTION("""COMPUTED_VALUE"""),3.39) -> 3.39 | L37: =IFERROR(__xludf.DUMMYFUNCTION("""COMPUTED_VALUE"""),23.0) -> 23 | M37: =IFERROR(__xludf.DUMMYFUNCTION("""COMPUTED_VALUE"""),92.0) -> 92
A38: =IFERROR(__xludf.DUMMYFUNCTION("""COMPUTED_VALUE"""),38.0) -> 38 | B38: =IFERROR(__xludf.DUMMYFUNCTION("""COMPUTED_VALUE"""),45341.0) -> 45341 | C38: =IFERROR(__xludf.DUMMYFUNCTION("""COMPUTED_VALUE"""),66.0) -> 66 | K38: =IFERROR(__xludf.DUMMYFUNCTION("""COMPUTED_VALUE"""),3.5) -> 3.5 | L38: =IFERROR(__xludf.DUMMYFUNCTION("""COMPUTED_VALUE"""),26.0) -> 26 | M38: =IFERROR(__xludf.DUMMYFUNCTION("""COMPUTED_VALUE"""),102.0) -> 102
A39: =IFERROR(__xludf.DUMMYFUNCTION("""COMPUTED_VALUE"""),39.0) -> 39 | B39: =IFERROR(__xludf.DUMMYFUNCTION("""COMPUTED_VALUE"""),45341.0) -> 45341 | C39: =IFERROR(__xludf.DUMMYFUNCTION("""COMPUTED_VALUE"""),82.0) -> 82 | K39: =IFERROR(__xludf.DUMMYFUNCTION("""COMPUTED_VALUE"""),3.4) -> 3.4 | L39: =IFERROR(__xludf.DUMMYFUNCTION("""COMPUTED_VALUE"""),25.0) -> 25 | M39: =IFERROR(__xludf.DUMMYFUNCTION("""COMPUTED_VALUE"""),110.0) -> 110
A40: =IFERROR(__xludf.DUMMYFUNCTION("""COMPUTED_VALUE"""),40.0) -> 40 | B40: =IFERROR(__xludf.DUMMYFUNCTION("""COMPUTED_VALUE"""),45341.0) -> 45341 | C40: =IFERROR(__xludf.DUMMYFUNCTION("""COMPUTED_VALUE"""),65.0) -> 65 | K40: =IFERROR(__xludf.DUMMYFUNCTION("""COMPUTED_VALUE"""),3.5) -> 3.5 | L40: =IFERROR(__xludf.DUMMYFUNCTION("""COMPUTED_VALUE"""),27.0) -> 27 | M40: =IFERROR(__xludf.DUMMYFUNCTION("""COMPUTED_VALUE"""),90.0) -> 90
A41: =IFERROR(__xludf.DUMMYFUNCTION("""COMPUTED_VALUE"""),41.0) -> 41 | B41: =IFERROR(__xludf.DUMMYFUNCTION("""COMPUTED_VALUE"""),45342.0) -> 45342 | C41: =IFERROR(__xludf.DUMMYFUNCTION("""COMPUTED_VALUE"""),84.0) -> 84 | D41: =IFERROR(__xludf.DUMMYFUNCTION("""COMPUTED_VALUE"""),"1.110") -> 1.110 | E41: =IFERROR(__xludf.DUMMYFUNCTION("""COMPUTED_VALUE"""),31512.0) -> 31512 | F41: =IFERROR(__xludf.DUMMYFUNCTION("""COMPUTED_VALUE"""),"Cabernet Sauvignon") -> Cabernet Sauvignon | H41: =IFERROR(__xludf.DUMMYFUNCTION("""COMPUTED_VALUE"""),2.0) -> 2 | I41: =IFERROR(__xludf.DUMMYFUNCTION("""COMPUTED_VALUE"""),0.34) -> 0.34 | L41: =IFERROR(__xludf.DUMMYFUNCTION("""COMPUTED_VALUE"""),35.0) -> 35
A42: =IFERROR(__xludf.DUMMYFUNCTION("""COMPUTED_VALUE"""),42.0) -> 42 | B42: =IFERROR(__xludf.DUMMYFUNCTION("""COMPUTED_VALUE"""),45342.0) -> 45342 | C42: =IFERROR(__xludf.DUMMYFUNCTION("""COMPUTED_VALUE"""),102.0) -> 102 | D42: =IFERROR(__xludf.DUMMYFUNCTION("""COMPUTED_VALUE"""),"#REF!") -> #REF! | F42: =IFERROR(__xludf.DUMMYFUNCTION("""COMPUTED_VALUE"""),"Aspirant Ancc") -> Aspirant Ancc | G42: =IFERROR(__xludf.DUMMYFUNCTION("""COMPUTED_VALUE"""),11.5) -> 11.5 | H42: =IFERROR(__xludf.DUMMYFUNCTION("""COMPUTED_VALUE"""),2.0) -> 2 | I42: =IFERROR(__xludf.DUMMYFUNCTION("""COMPUTED_VALUE"""),0.34) -> 0.34 | J42: =IFERROR(__xludf.DUMMYFUNCTION("""COMPUTED_VALUE"""),8.41) -> 8.41 | K42: =IFERROR(__xludf.DUMMYFUNCTION("""COMPUTED_VALUE"""),3.38) -> 3.38 | L42: =IFERROR(__xludf.DUMMYFUNCTION("""COMPUTED_VALUE"""),37.0) -> 37 | M42: =IFERROR(__xludf.DUMMYFUNCTION("""COMPUTED_VALUE"""),70.0) -> 70
A43: =IFERROR(__xludf.DUMMYFUNCTION("""COMPUTED_VALUE"""),43.0) -> 43 | B43: =IFERROR(__xludf.DUMMYFUNCTION("""COMPUTED_VALUE"""),45342.0) -> 45342 | C43: =IFERROR(__xludf.DUMMYFUNCTION("""COMPUTED_VALUE"""),85.0) -> 85 | D43: =IFERROR(__xludf.DUMMYFUNCTION("""COMPUTED_VALUE"""),"1.107") -> 1.107 | E43: =IFERROR(__xludf.DUMMYFUNCTION("""COMPUTED_VALUE"""),45162.0) -> 45162 | F43: =IFERROR(__xludf.DUMMYFUNCTION("""COMPUTED_VALUE"""),"Bonarda") -> Bonarda | H43: =IFERROR(__xludf.DUMMYFUNCTION("""COMPUTED_VALUE"""),2.0) -> 2
A44: =IFERROR(__xludf.DUMMYFUNCTION("""COMPUTED_VALUE"""),44.0) -> 44 | B44: =IFERROR(__xludf.DUMMYFUNCTION("""COMPUTED_VALUE"""),45343.0) -> 45343 | C44: =IFERROR(__xludf.DUMMYFUNCTION("""COMPUTED_VALUE"""),30.0) -> 30 | D44: =IFERROR(__xludf.DUMMYFUNCTION("""COMPUTED_VALUE"""),"1.026") -> 1.026 | E44: =IFERROR(__xludf.DUMMYFUNCTION("""COMPUTED_VALUE"""),38800.0) -> 38800 | F44: =IFERROR(__xludf.DUMMYFUNCTION("""COMPUTED_VALUE"""),"Chardonnay") -> Chardonnay | G44: =IFERROR(__xludf.DUMMYFUNCTION("""COMPUTED_VALUE"""),11.9) -> 11.9 | J44: =IFERROR(__xludf.DUMMYFUNCTION("""COMPUTED_VALUE"""),6.3) -> 6.3 | K44: =IFERROR(__xludf.DUMMYFUNCTION("""COMPUTED_VALUE"""),3.45) -> 3.45 | L44: =IFERROR(__xludf.DUMMYFUNCTION("""COMPUTED_VALUE"""),25.0) -> 25
A45: =IFERROR(__xludf.DUMMYFUNCTION("""COMPUTED_VALUE"""),45.0) -> 45 | B45: =IFERROR(__xludf.DUMMYFUNCTION("""COMPUTED_VALUE"""),45343.0) -> 45343 | C45: =IFERROR(__xludf.DUMMYFUNCTION("""COMPUTED_VALUE"""),34.0) -> 34 | D45: =IFERROR(__xludf.DUMMYFUNCTION("""COMPUTED_VALUE"""),"1.054") -> 1.054 | E45: =IFERROR(__xludf.DUMMYFUNCTION("""COMPUTED_VALUE"""),39500.0) -> 39500 | F45: =IFERROR(__xludf.DUMMYFUNCTION("""COMPUTED_VALUE"""),"Chardonnay") -> Chardonnay | G45: =IFERROR(__xludf.DUMMYFUNCTION("""COMPUTED_VALUE"""),12.2) -> 12.2 | J45: =IFERROR(__xludf.DUMMYFUNCTION("""COMPUTED_VALUE"""),6.2) -> 6.2 | K45: =IFERROR(__xludf.DUMMYFUNCTION("""COMPUTED_VALUE"""),3.54) -> 3.54 | L45: =IFERROR(__xludf.DUMMYFUNCTION("""COMPUTED_VALUE"""),27.0) -> 27
A46: =IFERROR(__xludf.DUMMYFUNCTION("""COMPUTED_VALUE"""),46.0) -> 46 | B46: =IFERROR(__xludf.DUMMYFUNCTION("""COMPUTED_VALUE"""),45343.0) -> 45343 | C46: =IFERROR(__xludf.DUMMYFUNCTION("""COMPUTED_VALUE"""),35.0) -> 35 | D46: =IFERROR(__xludf.DUMMYFUNCTION("""COMPUTED_VALUE"""),"1.028") -> 1.028 | E46: =IFERROR(__xludf.DUMMYFUNCTION("""COMPUTED_VALUE"""),39300.0) -> 39300 | F46: =IFERROR(__xludf.DUMMYFUNCTION("""COMPUTED_VALUE"""),"Chardonnay") -> Chardonnay | G46: =IFERROR(__xludf.DUMMYFUNCTION("""COMPUTED_VALUE"""),12.3) -> 12.3 | J46: =IFERROR(__xludf.DUMMYFUNCTION("""COMPUTED_VALUE"""),6.2) -> 6.2 | K46: =IFERROR(__xludf.DUMMYFUNCTION("""COMPUTED_VALUE"""),3.49) -> 3.49 | L46: =IFERROR(__xludf.DUMMYFUNCTION("""COMPUTED_VALUE"""),22.0) -> 22
A47: =IFERROR(__xludf.DUMMYFUNCTION("""COMPUTED_VALUE"""),47.0) -> 47 | B47: =IFERROR(__xludf.DUMMYFUNCTION("""COMPUTED_VALUE"""),45343.0) -> 45343 | C47: =IFERROR(__xludf.DUMMYFUNCTION("""COMPUTED_VALUE"""),46.0) -> 46 | D47: =IFERROR(__xludf.DUMMYFUNCTION("""COMPUTED_VALUE"""),"1.027") -> 1.027 | E47: =IFERROR(__xludf.DUMMYFUNCTION("""COMPUTED_VALUE"""),29000.0) -> 29000 | F47: =IFERROR(__xludf.DUMMYFUNCTION("""COMPUTED_VALUE"""),"Chardonnay") -> Chardonnay | G47: =IFERROR(__xludf.DUMMYFUNCTION("""COMPUTED_VALUE"""),12.0) -> 12 | J47: =IFERROR(__xludf.DUMMYFUNCTION("""COMPUTED_VALUE"""),6.25) -> 6.25 | K47: =IFERROR(__xludf.DUMMYFUNCTION("""COMPUTED_VALUE"""),3.56) -> 3.56 | L47: =IFERROR(__xludf.DUMMYFUNCTION("""COMPUTED_VALUE"""),23.0) -> 23
A48: =IFERROR(__xludf.DUMMYFUNCTION("""COMPUTED_VALUE"""),48.0) -> 48 | B48: =IFERROR(__xludf.DUMMYFUNCTION("""COMPUTED_VALUE"""),45343.0) -> 45343 | C48: =IFERROR(__xludf.DUMMYFUNCTION("""COMPUTED_VALUE"""),47.0) -> 47 | D48: =IFERROR(__xludf.DUMMYFUNCTION("""COMPUTED_VALUE"""),"1.029") -> 1.029 | E48: =IFERROR(__xludf.DUMMYFUNCTION("""COMPUTED_VALUE"""),20000.0) -> 20000 | F48: =IFERROR(__xludf.DUMMYFUNCTION("""COMPUTED_VALUE"""),"Chardonnay") -> Chardonnay | G48: =IFERROR(__xludf.DUMMYFUNCTION("""COMPUTED_VALUE"""),11.9) -> 11.9 | J48: =IFERROR(__xludf.DUMMYFUNCTION("""COMPUTED_VALUE"""),6.3) -> 6.3 | K48: =IFERROR(__xludf.DUMMYFUNCTION("""COMPUTED_VALUE"""),3.45) -> 3.45 | L48: =IFERROR(__xludf.DUMMYFUNCTION("""COMPUTED_VALUE"""),24.0) -> 24
A49: =IFERROR(__xludf.DUMMYFUNCTION("""COMPUTED_VALUE"""),49.0) -> 49 | B49: =IFERROR(__xludf.DUMMYFUNCTION("""COMPUTED_VALUE"""),45343.0) -> 45343 | C49: =IFERROR(__xludf.DUMMYFUNCTION("""COMPUTED_VALUE"""),83.0) -> 83 | D49: =IFERROR(__xludf.DUMMYFUNCTION("""COMPUTED_VALUE"""),"#REF!") -> #REF! | F49: =IFERROR(__xludf.DUMMYFUNCTION("""COMPUTED_VALUE"""),"merlot /aspirant 1") -> merlot /aspirant 1 | H49: =IFERROR(__xludf.DUMMYFUNCTION("""COMPUTED_VALUE"""),7.5) -> 7.5 | I49: =IFERROR(__xludf.DUMMYFUNCTION("""COMPUTED_VALUE"""),0.36) -> 0.36
A50: =IFERROR(__xludf.DUMMYFUNCTION("""COMPUTED_VALUE"""),50.0) -> 50 | B50: =IFERROR(__xludf.DUMMYFUNCTION("""COMPUTED_VALUE"""),45343.0) -> 45343 | C50: =IFERROR(__xludf.DUMMYFUNCTION("""COMPUTED_VALUE"""),75.0) -> 75 | D50: =IFERROR(__xludf.DUMMYFUNCTION("""COMPUTED_VALUE"""),"#REF!") -> #REF! | F50: =IFERROR(__xludf.DUMMYFUNCTION("""COMPUTED_VALUE"""),"Chardonnay") -> Chardonnay | H50: =IFERROR(__xludf.DUMMYFUNCTION("""COMPUTED_VALUE"""),2.0) -> 2 | J50: =IFERROR(__xludf.DUMMYFUNCTION("""COMPUTED_VALUE"""),6.0) -> 6 | K50: =IFERROR(__xludf.DUMMYFUNCTION("""COMPUTED_VALUE"""),3.5) -> 3.5 | L50: =IFERROR(__xludf.DUMMYFUNCTION("""COMPUTED_VALUE"""),20.0) -> 20
A51: =IFERROR(__xludf.DUMMYFUNCTION("""COMPUTED_VALUE"""),51.0) -> 51 | B51: =IFERROR(__xludf.DUMMYFUNCTION("""COMPUTED_VALUE"""),45344.0) -> 45344 | C51: =IFERROR(__xludf.DUMMYFUNCTION("""COMPUTED_VALUE"""),77.0) -> 77 | D51: =IFERROR(__xludf.DUMMYFUNCTION("""COMPUTED_VALUE"""),"1.083") -> 1.083 | E51: =IFERROR(__xludf.DUMMYFUNCTION("""COMPUTED_VALUE"""),18579.600000000002) -> 18579.6 | F51: =IFERROR(__xludf.DUMMYFUNCTION("""COMPUTED_VALUE"""),"Pedro Gimenez") -> Pedro Gimenez | G51: =IFERROR(__xludf.DUMMYFUNCTION("""COMPUTED_VALUE"""),12.5) -> 12.5 | H51: =IFERROR(__xludf.DUMMYFUNCTION("""COMPUTED_VALUE"""),2.0) -> 2 | I51: =IFERROR(__xludf.DUMMYFUNCTION("""COMPUTED_VALUE"""),0.35) -> 0.35
A52: =IFERROR(__xludf.DUMMYFUNCTION("""COMPUTED_VALUE"""),52.0) -> 52 | B52: =IFERROR(__xludf.DUMMYFUNCTION("""COMPUTED_VALUE"""),45344.0) -> 45344 | C52: =IFERROR(__xludf.DUMMYFUNCTION("""COMPUTED_VALUE"""),84.0) -> 84 | D52: =IFERROR(__xludf.DUMMYFUNCTION("""COMPUTED_VALUE"""),"1.110") -> 1.110 | E52: =IFERROR(__xludf.DUMMYFUNCTION("""COMPUTED_VALUE"""),31512.0) -> 31512 | F52: =IFERROR(__xludf.DUMMYFUNCTION("""COMPUTED_VALUE"""),"Cabernet Sauvignon") -> Cabernet Sauvignon | G52: =IFERROR(__xludf.DUMMYFUNCTION("""COMPUTED_VALUE"""),12.2) -> 12.2 | H52: =IFERROR(__xludf.DUMMYFUNCTION("""COMPUTED_VALUE"""),3.75) -> 3.75 | I52: =IFERROR(__xludf.DUMMYFUNCTION("""COMPUTED_VALUE"""),0.34) -> 0.34
A53: =IFERROR(__xludf.DUMMYFUNCTION("""COMPUTED_VALUE"""),53.0) -> 53 | B53: =IFERROR(__xludf.DUMMYFUNCTION("""COMPUTED_VALUE"""),45344.0) -> 45344 | C53: =IFERROR(__xludf.DUMMYFUNCTION("""COMPUTED_VALUE"""),85.0) -> 85 | D53: =IFERROR(__xludf.DUMMYFUNCTION("""COMPUTED_VALUE"""),"1.107") -> 1.107 | E53: =IFERROR(__xludf.DUMMYFUNCTION("""COMPUTED_VALUE"""),45162.0) -> 45162 | F53: =IFERROR(__xludf.DUMMYFUNCTION("""COMPUTED_VALUE"""),"Bonarda") -> Bonarda | G53: =IFERROR(__xludf.DUMMYFUNCTION("""COMPUTED_VALUE"""),11.2) -> 11.2 | H53: =IFERROR(__xludf.DUMMYFUNCTION("""COMPUTED_VALUE"""),9.0) -> 9 | I53: =IFERROR(__xludf.DUMMYFUNCTION("""COMPUTED_VALUE"""),0.38) -> 0.38
A54: =IFERROR(__xludf.DUMMYFUNCTION("""COMPUTED_VALUE"""),54.0) -> 54 | B54: =IFERROR(__xludf.DUMMYFUNCTION("""COMPUTED_VALUE"""),45344.0) -> 45344 | C54: =IFERROR(__xludf.DUMMYFUNCTION("""COMPUTED_VALUE"""),103.0) -> 103 | D54: =IFERROR(__xludf.DUMMYFUNCTION("""COMPUTED_VALUE"""),"1.104") -> 1.104 | E54: =IFERROR(__xludf.DUMMYFUNCTION("""COMPUTED_VALUE"""),28200.0) -> 28200 | F54: =IFERROR(__xludf.DUMMYFUNCTION("""COMPUTED_VALUE"""),"Malbec Gota") -> Malbec Gota | G54: =IFERROR(__xludf.DUMMYFUNCTION("""COMPUTED_VALUE"""),11.5) -> 11.5 | H54: =IFERROR(__xludf.DUMMYFUNCTION("""COMPUTED_VALUE"""),2.0) -> 2 | I54: =IFERROR(__xludf.DUMMYFUNCTION("""COMPUTED_VALUE"""),0.38) -> 0.38 | J54: =IFERROR(__xludf.DUMMYFUNCTION("""COMPUTED_VALUE"""),7.5) -> 7.5 | L54: =IFERROR(__xludf.DUMMYFUNCTION("""COMPUTED_VALUE"""),40.0) -> 40 | M54: =IFERROR(__xludf.DUMMYFUNCTION("""COMPUTED_VALUE"""),110.0) -> 110
A55: =IFERROR(__xludf.DUMMYFUNCTION("""COMPUTED_VALUE"""),55.0) -> 55 | B55: =IFERROR(__xludf.DUMMYFUNCTION("""COMPUTED_VALUE"""),45344.0) -> 45344 | C55: =IFERROR(__xludf.DUMMYFUNCTION("""COMPUTED_VALUE"""),104.0) -> 104 | D55: =IFERROR(__xludf.DUMMYFUNCTION("""COMPUTED_VALUE"""),"1.095") -> 1.095 | E55: =IFERROR(__xludf.DUMMYFUNCTION("""COMPUTED_VALUE"""),31000.0) -> 31000 | F55: =IFERROR(__xludf.DUMMYFUNCTION("""COMPUTED_VALUE"""),"Syrah Tempranillo") -> Syrah Tempranillo | G55: =IFERROR(__xludf.DUMMYFUNCTION("""COMPUTED_VALUE"""),11.5) -> 11.5 | H55: =IFERROR(__xludf.DUMMYFUNCTION("""COMPUTED_VALUE"""),2.0) -> 2 | I55: =IFERROR(__xludf.DUMMYFUNCTION("""COMPUTED_VALUE"""),0.37) -> 0.37 | J55: =IFERROR(__xludf.DUMMYFUNCTION("""COMPUTED_VALUE"""),7.6) -> 7.6 | L55: =IFERROR(__xludf.DUMMYFUNCTION("""COMPUTED_VALUE"""),39.0) -> 39 | M55: =IFERROR(__xludf.DUMMYFUNCTION("""COMPUTED_VALUE"""),120.0) -> 120
A56: =IFERROR(__xludf.DUMMYFUNCTION("""COMPUTED_VALUE"""),56.0) -> 56 | B56: =IFERROR(__xludf.DUMMYFUNCTION("""COMPUTED_VALUE"""),45345.0) -> 45345 | C56: =IFERROR(__xludf.DUMMYFUNCTION("""COMPUTED_VALUE"""),83.0) -> 83 | D56: =IFERROR(__xludf.DUMMYFUNCTION("""COMPUTED_VALUE"""),"1.108") -> 1.108 | E56: =IFERROR(__xludf.DUMMYFUNCTION("""COMPUTED_VALUE"""),47642.4) -> 47642.4 | F56: =IFERROR(__xludf.DUMMYFUNCTION("""COMPUTED_VALUE"""),"Bonarda") -> Bonarda | H56: =IFERROR(__xludf.DUMMYFUNCTION("""COMPUTED_VALUE"""),3.75) -> 3.75
A57: =IFERROR(__xludf.DUMMYFUNCTION("""COMPUTED_VALUE"""),57.0) -> 57 | B57: =IFERROR(__xludf.DUMMYFUNCTION("""COMPUTED_VALUE"""),45345.0) -> 45345 | C57: =IFERROR(__xludf.DUMMYFUNCTION("""COMPUTED_VALUE"""),85.0) -> 85 | D57: =IFERROR(__xludf.DUMMYFUNCTION("""COMPUTED_VALUE"""),"1.107") -> 1.107 | E57: =IFERROR(__xludf.DUMMYFUNCTION("""COMPUTED_VALUE"""),45162.0) -> 45162 | F57: =IFERROR(__xludf.DUMMYFUNCTION("""COMPUTED_VALUE"""),"Bonarda") -> Bonarda | H57: =IFERROR(__xludf.DUMMYFUNCTION("""COMPUTED_VALUE"""),18.0) -> 18
A58: =IFERROR(__xludf.DUMMYFUNCTION("""COMPUTED_VALUE"""),58.0) -> 58 | B58: =IFERROR(__xludf.DUMMYFUNCTION("""COMPUTED_VALUE"""),45345.0) -> 45345 | C58: =IFERROR(__xludf.DUMMYFUNCTION("""COMPUTED_VALUE"""),68.0) -> 68 | D58: =IFERROR(__xludf.DUMMYFUNCTION("""COMPUTED_VALUE"""),"1.088") -> 1.088 | E58: =IFERROR(__xludf.DUMMYFUNCTION("""COMPUTED_VALUE"""),14385.0) -> 14385 | F58: =IFERROR(__xludf.DUMMYFUNCTION("""COMPUTED_VALUE"""),"Syrah Rosado") -> Syrah Rosado | G58: =IFERROR(__xludf.DUMMYFUNCTION("""COMPUTED_VALUE"""),11.8) -> 11.8 | H58: =IFERROR(__xludf.DUMMYFUNCTION("""COMPUTED_VALUE"""),2.0) -> 2 | J58: =IFERROR(__xludf.DUMMYFUNCTION("""COMPUTED_VALUE"""),8.41) -> 8.41 | K58: =IFERROR(__xludf.DUMMYFUNCTION("""COMPUTED_VALUE"""),3.37) -> 3.37 | L58: =IFERROR(__xludf.DUMMYFUNCTION("""COMPUTED_VALUE"""),19.0) -> 19 | M58: =IFERROR(__xludf.DUMMYFUNCTION("""COMPUTED_VALUE"""),140.0) -> 140
A59: =IFERROR(__xludf.DUMMYFUNCTION("""COMPUTED_VALUE"""),59.0) -> 59 | B59: =IFERROR(__xludf.DUMMYFUNCTION("""COMPUTED_VALUE"""),45345.0) -> 45345 | C59: =IFERROR(__xludf.DUMMYFUNCTION("""COMPUTED_VALUE"""),69.0) -> 69 | D59: =IFERROR(__xludf.DUMMYFUNCTION("""COMPUTED_VALUE"""),"1.092") -> 1.092 | E59: =IFERROR(__xludf.DUMMYFUNCTION("""COMPUTED_VALUE"""),10000.0) -> 10000 | F59: =IFERROR(__xludf.DUMMYFUNCTION("""COMPUTED_VALUE"""),"Tempranillo Merlot s/Asp 2") -> Tempranillo Merlot s/Asp 2 | H59: =IFERROR(__xludf.DUMMYFUNCTION("""COMPUTED_VALUE"""),2.0) -> 2 | J59: =IFERROR(__xludf.DUMMYFUNCTION("""COMPUTED_VALUE"""),8.35) -> 8.35 | K59: =IFERROR(__xludf.DUMMYFUNCTION("""COMPUTED_VALUE"""),3.3) -> 3.3 | L59: =IFERROR(__xludf.DUMMYFUNCTION("""COMPUTED_VALUE"""),12.0) -> 12 | M59: =IFERROR(__xludf.DUMMYFUNCTION("""COMPUTED_VALUE"""),89.0) -> 89
A60: =IFERROR(__xludf.DUMMYFUNCTION("""COMPUTED_VALUE"""),60.0) -> 60 | B60: =IFERROR(__xludf.DUMMYFUNCTION("""COMPUTED_VALUE"""),45345.0) -> 45345 | C60: =IFERROR(__xludf.DUMMYFUNCTION("""COMPUTED_VALUE"""),76.0) -> 76 | H60: =IFERROR(__xludf.DUMMYFUNCTION("""COMPUTED_VALUE"""),2.0) -> 2 | J60: =IFERROR(__xludf.DUMMYFUNCTION("""COMPUTED_VALUE"""),7.3) -> 7.3 | K60: =IFERROR(__xludf.DUMMYFUNCTION("""COMPUTED_VALUE"""),3.588) -> 3.588 | L60: =IFERROR(__xludf.DUMMYFUNCTION("""COMPUTED_VALUE"""),12.0) -> 12 | M60: =IFERROR(__xludf.DUMMYFUNCTION("""COMPUTED_VALUE"""),90.0) -> 90
A61: =IFERROR(__xludf.DUMMYFUNCTION("""COMPUTED_VALUE"""),61.0) -> 61 | B61: =IFERROR(__xludf.DUMMYFUNCTION("""COMPUTED_VALUE"""),45348.0) -> 45348 | C61: =IFERROR(__xludf.DUMMYFUNCTION("""COMPUTED_VALUE"""),85.0) -> 85 | D61: =IFERROR(__xludf.DUMMYFUNCTION("""COMPUTED_VALUE"""),"1.107") -> 1.107 | E61: =IFERROR(__xludf.DUMMYFUNCTION("""COMPUTED_VALUE"""),45162.0) -> 45162 | F61: =IFERROR(__xludf.DUMMYFUNCTION("""COMPUTED_VALUE"""),"Bonarda") -> Bonarda | H61: =IFERROR(__xludf.DUMMYFUNCTION("""COMPUTED_VALUE"""),13.0) -> 13 | I61: =IFERROR(__xludf.DUMMYFUNCTION("""COMPUTED_VALUE"""),0.4) -> 0.4 | J61: =IFERROR(__xludf.DUMMYFUNCTION("""COMPUTED_VALUE"""),7.11) -> 7.11 | K61: =IFERROR(__xludf.DUMMYFUNCTION("""COMPUTED_VALUE"""),3.74) -> 3.74 | L61: =IFERROR(__xludf.DUMMYFUNCTION("""COMPUTED_VALUE"""),32.0) -> 32
A62: =IFERROR(__xludf.DUMMYFUNCTION("""COMPUTED_VALUE"""),62.0) -> 62 | B62: =IFERROR(__xludf.DUMMYFUNCTION("""COMPUTED_VALUE"""),45350.0) -> 45350 | C62: =IFERROR(__xludf.DUMMYFUNCTION("""COMPUTED_VALUE"""),105.0) -> 105 | D62: =IFERROR(__xludf.DUMMYFUNCTION("""COMPUTED_VALUE"""),"1.096") -> 1.096 | E62: =IFERROR(__xludf.DUMMYFUNCTION("""COMPUTED_VALUE"""),31000.0) -> 31000 | F62: =IFERROR(__xludf.DUMMYFUNCTION("""COMPUTED_VALUE"""),"Syrah Tempranillo") -> Syrah Tempranillo | G62: =IFERROR(__xludf.DUMMYFUNCTION("""COMPUTED_VALUE"""),12.8) -> 12.8 | H62: =IFERROR(__xludf.DUMMYFUNCTION("""COMPUTED_VALUE"""),2.0) -> 2 | I62: =IFERROR(__xludf.DUMMYFUNCTION("""COMPUTED_VALUE"""),0.34) -> 0.34 | K62: =IFERROR(__xludf.DUMMYFUNCTION("""COMPUTED_VALUE"""),3.59) -> 3.59 | L62: =IFERROR(__xludf.DUMMYFUNCTION("""COMPUTED_VALUE"""),40.0) -> 40
A63: =IFERROR(__xludf.DUMMYFUNCTION("""COMPUTED_VALUE"""),63.0) -> 63 | B63: =IFERROR(__xludf.DUMMYFUNCTION("""COMPUTED_VALUE"""),45350.0) -> 45350 | C63: =IFERROR(__xludf.DUMMYFUNCTION("""COMPUTED_VALUE"""),106.0) -> 106 | D63: =IFERROR(__xludf.DUMMYFUNCTION("""COMPUTED_VALUE"""),"1.097") -> 1.097 | E63: =IFERROR(__xludf.DUMMYFUNCTION("""COMPUTED_VALUE"""),11000.0) -> 11000 | F63: =IFERROR(__xludf.DUMMYFUNCTION("""COMPUTED_VALUE"""),"Syrah") -> Syrah | G63: =IFERROR(__xludf.DUMMYFUNCTION("""COMPUTED_VALUE"""),13.0) -> 13 | H63: =IFERROR(__xludf.DUMMYFUNCTION("""COMPUTED_VALUE"""),2.0) -> 2 | I63: =IFERROR(__xludf.DUMMYFUNCTION("""COMPUTED_VALUE"""),0.4) -> 0.4 | K63: =IFERROR(__xludf.DUMMYFUNCTION("""COMPUTED_VALUE"""),3.64) -> 3.64 | L63: =IFERROR(__xludf.DUMMYFUNCTION("""COMPUTED_VALUE"""),35.0) -> 35
A64: =IFERROR(__xludf.DUMMYFUNCTION("""COMPUTED_VALUE"""),64.0) -> 64 | B64: =IFERROR(__xludf.DUMMYFUNCTION("""COMPUTED_VALUE"""),45350.0) -> 45350 | C64: =IFERROR(__xludf.DUMMYFUNCTION("""COMPUTED_VALUE"""),107.0) -> 107 | D64: =IFERROR(__xludf.DUMMYFUNCTION("""COMPUTED_VALUE"""),"1.098") -> 1.098 | E64: =IFERROR(__xludf.DUMMYFUNCTION("""COMPUTED_VALUE"""),31000.0) -> 31000 | F64: =IFERROR(__xludf.DUMMYFUNCTION("""COMPUTED_VALUE"""),"Syrah") -> Syrah | G64: =IFERROR(__xludf.DUMMYFUNCTION("""COMPUTED_VALUE"""),12.9) -> 12.9 | H64: =IFERROR(__xludf.DUMMYFUNCTION("""COMPUTED_VALUE"""),2.8) -> 2.8 | I64: =IFERROR(__xludf.DUMMYFUNCTION("""COMPUTED_VALUE"""),0.35) -> 0.35 | K64: =IFERROR(__xludf.DUMMYFUNCTION("""COMPUTED_VALUE"""),3.548) -> 3.548 | L64: =IFERROR(__xludf.DUMMYFUNCTION("""COMPUTED_VALUE"""),35.0) -> 35
A65: =IFERROR(__xludf.DUMMYFUNCTION("""COMPUTED_VALUE"""),65.0) -> 65 | B65: =IFERROR(__xludf.DUMMYFUNCTION("""COMPUTED_VALUE"""),45350.0) -> 45350 | C65: =IFERROR(__xludf.DUMMYFUNCTION("""COMPUTED_VALUE"""),108.0) -> 108 | D65: =IFERROR(__xludf.DUMMYFUNCTION("""COMPUTED_VALUE"""),"1.101") -> 1.101 | E65: =IFERROR(__xludf.DUMMYFUNCTION("""COMPUTED_VALUE"""),31000.0) -> 31000 | F65: =IFERROR(__xludf.DUMMYFUNCTION("""COMPUTED_VALUE"""),"Syrah") -> Syrah | G65: =IFERROR(__xludf.DUMMYFUNCTION("""COMPUTED_VALUE"""),13.1) -> 13.1 | H65: =IFERROR(__xludf.DUMMYFUNCTION("""COMPUTED_VALUE"""),2.8) -> 2.8 | I65: =IFERROR(__xludf.DUMMYFUNCTION("""COMPUTED_VALUE"""),0.35) -> 0.35 | K65: =IFERROR(__xludf.DUMMYFUNCTION("""COMPUTED_VALUE"""),3.66) -> 3.66 | L65: =IFERROR(__xludf.DUMMYFUNCTION("""COMPUTED_VALUE"""),40.0) -> 40
A66: =IFERROR(__xludf.DUMMYFUNCTION("""COMPUTED_VALUE"""),66.0) -> 66 | B66: =IFERROR(__xludf.DUMMYFUNCTION("""COMPUTED_VALUE"""),45350.0) -> 45350 | C66: =IFERROR(__xludf.DUMMYFUNCTION("""COMPUTED_VALUE"""),84.0) -> 84 | D66: =IFERROR(__xludf.DUMMYFUNCTION("""COMPUTED_VALUE"""),"1.110") -> 1.110 | E66: =IFERROR(__xludf.DUMMYFUNCTION("""COMPUTED_VALUE"""),31512.0) -> 31512 | F66: =IFERROR(__xludf.DUMMYFUNCTION("""COMPUTED_VALUE"""),"Cabernet Sauvignon") -> Cabernet Sauvignon | G66: =IFERROR(__xludf.DUMMYFUNCTION("""COMPUTED_VALUE"""),12.6) -> 12.6 | H66: =IFERROR(__xludf.DUMMYFUNCTION("""COMPUTED_VALUE"""),5.0) -> 5 | I66: =IFERROR(__xludf.DUMMYFUNCTION("""COMPUTED_VALUE"""),0.37) -> 0.37 | K66: =IFERROR(__xludf.DUMMYFUNCTION("""COMPUTED_VALUE"""),3.65) -> 3.65
A67: =IFERROR(__xludf.DUMMYFUNCTION("""COMPUTED_VALUE"""),67.0) -> 67 | C67: =IFERROR(__xludf.DUMMYFUNCTION("""COMPUTED_VALUE"""),73.0) -> 73 | D67: =IFERROR(__xludf.DUMMYFUNCTION("""COMPUTED_VALUE"""),"#REF!") -> #REF! | F67: =IFERROR(__xludf.DUMMYFUNCTION("""COMPUTED_VALUE"""),"tinto sobre orujo aspirant rectificado") -> tinto sobre orujo aspirant rectificado | G67: =IFERROR(__xludf.DUMMYFUNCTION("""COMPUTED_VALUE"""),11.0) -> 11 | H67: =IFERROR(__xludf.DUMMYFUNCTION("""COMPUTED_VALUE"""),2.0) -> 2 | I67: =IFERROR(__xludf.DUMMYFUNCTION("""COMPUTED_VALUE"""),0.35) -> 0.35 | K67: =IFERROR(__xludf.DUMMYFUNCTION("""COMPUTED_VALUE"""),3.0) -> 3 | L67: =IFERROR(__xludf.DUMMYFUNCTION("""COMPUTED_VALUE"""),25.0) -> 25 | M67: =IFERROR(__xludf.DUMMYFUNCTION("""COMPUTED_VALUE"""),150.0) -> 150
A68: =IFERROR(__xludf.DUMMYFUNCTION("""COMPUTED_VALUE"""),68.0) -> 68 | B68: =IFERROR(__xludf.DUMMYFUNCTION("""COMPUTED_VALUE"""),45351.0) -> 45351 | C68: =IFERROR(__xludf.DUMMYFUNCTION("""COMPUTED_VALUE"""),85.0) -> 85 | D68: =IFERROR(__xludf.DUMMYFUNCTION("""COMPUTED_VALUE"""),"1.107") -> 1.107 | E68: =IFERROR(__xludf.DUMMYFUNCTION("""COMPUTED_VALUE"""),45162.0) -> 45162 | F68: =IFERROR(__xludf.DUMMYFUNCTION("""COMPUTED_VALUE"""),"Bonarda") -> Bonarda
A69: =IFERROR(__xludf.DUMMYFUNCTION("""COMPUTED_VALUE"""),69.0) -> 69 | B69: =IFERROR(__xludf.DUMMYFUNCTION("""COMPUTED_VALUE"""),45351.0) -> 45351 | C69: =IFERROR(__xludf.DUMMYFUNCTION("""COMPUTED_VALUE"""),77.0) -> 77 | D69: =IFERROR(__xludf.DUMMYFUNCTION("""COMPUTED_VALUE"""),"1.083") -> 1.083 | E69: =IFERROR(__xludf.DUMMYFUNCTION("""COMPUTED_VALUE"""),18579.600000000002) -> 18579.6 | F69: =IFERROR(__xludf.DUMMYFUNCTION("""COMPUTED_VALUE"""),"Pedro Gimenez") -> Pedro Gimenez
A70: =IFERROR(__xludf.DUMMYFUNCTION("""COMPUTED_VALUE"""),70.0) -> 70 | B70: =IFERROR(__xludf.DUMMYFUNCTION("""COMPUTED_VALUE"""),45351.0) -> 45351 | C70: =IFERROR(__xludf.DUMMYFUNCTION("""COMPUTED_VALUE"""),52.0) -> 52 | D70: =IFERROR(__xludf.DUMMYFUNCTION("""COMPUTED_VALUE"""),"#REF!") -> #REF! | F70: =IFERROR(__xludf.DUMMYFUNCTION("""COMPUTED_VALUE"""),"Chardonnay") -> Chardonnay | J70: =IFERROR(__xludf.DUMMYFUNCTION("""COMPUTED_VALUE"""),7.3) -> 7.3 | K70: =IFERROR(__xludf.DUMMYFUNCTION("""COMPUTED_VALUE"""),3.52) -> 3.52 | L70: =IFERROR(__xludf.DUMMYFUNCTION("""COMPUTED_VALUE"""),20.0) -> 20 | M70: =IFERROR(__xludf.DUMMYFUNCTION("""COMPUTED_VALUE"""),77.0) -> 77
A71: =IFERROR(__xludf.DUMMYFUNCTION("""COMPUTED_VALUE"""),71.0) -> 71 | B71: =IFERROR(__xludf.DUMMYFUNCTION("""COMPUTED_VALUE"""),45351.0) -> 45351 | C71: =IFERROR(__xludf.DUMMYFUNCTION("""COMPUTED_VALUE"""),10.0) -> 10 | D71: =IFERROR(__xludf.DUMMYFUNCTION("""COMPUTED_VALUE"""),"#REF!") -> #REF! | F71: =IFERROR(__xludf.DUMMYFUNCTION("""COMPUTED_VALUE"""),"Chardonnay") -> Chardonnay | J71: =IFERROR(__xludf.DUMMYFUNCTION("""COMPUTED_VALUE"""),7.6) -> 7.6 | K71: =IFERROR(__xludf.DUMMYFUNCTION("""COMPUTED_VALUE"""),3.45) -> 3.45 | L71: =IFERROR(__xludf.DUMMYFUNCTION("""COMPUTED_VALUE"""),22.0) -> 22 | M71: =IFERROR(__xludf.DUMMYFUNCTION("""COMPUTED_VALUE"""),100.0) -> 100
A72: =IFERROR(__xludf.DUMMYFUNCTION("""COMPUTED_VALUE"""),72.0) -> 72 | B72: =IFERROR(__xludf.DUMMYFUNCTION("""COMPUTED_VALUE"""),45351.0) -> 45351 | C72: =IFERROR(__xludf.DUMMYFUNCTION("""COMPUTED_VALUE"""),44.0) -> 44 | D72: =IFERROR(__xludf.DUMMYFUNCTION("""COMPUTED_VALUE"""),"#REF!") -> #REF! | F72: =IFERROR(__xludf.DUMMYFUNCTION("""COMPUTED_VALUE"""),"chenin") -> chenin | G72: =IFERROR(__xludf.DUMMYFUNCTION("""COMPUTED_VALUE"""),11.0) -> 11 | J72: =IFERROR(__xludf.DUMMYFUNCTION("""COMPUTED_VALUE"""),9.18) -> 9.18 | K72: =IFERROR(__xludf.DUMMYFUNCTION("""COMPUTED_VALUE"""),3.31) -> 3.31 | L72: =IFERROR(__xludf.DUMMYFUNCTION("""COMPUTED_VALUE"""),18.0) -> 18 | M72: =IFERROR(__xludf.DUMMYFUNCTION("""COMPUTED_VALUE"""),110.0) -> 110
A73: =IFERROR(__xludf.DUMMYFUNCTION("""COMPUTED_VALUE"""),73.0) -> 73 | B73: =IFERROR(__xludf.DUMMYFUNCTION("""COMPUTED_VALUE"""),45351.0) -> 45351 | C73: =IFERROR(__xludf.DUMMYFUNCTION("""COMPUTED_VALUE"""),77.0) -> 77 | D73: =IFERROR(__xludf.DUMMYFUNCTION("""COMPUTED_VALUE"""),"1.083") -> 1.083 | E73: =IFERROR(__xludf.DUMMYFUNCTION("""COMPUTED_VALUE"""),18579.600000000002) -> 18579.6 | F73: =IFERROR(__xludf.DUMMYFUNCTION("""COMPUTED_VALUE"""),"Pedro Gimenez") -> Pedro Gimenez | H73: =IFERROR(__xludf.DUMMYFUNCTION("""COMPUTED_VALUE"""),4.12) -> 4.12 | I73: =IFERROR(__xludf.DUMMYFUNCTION("""COMPUTED_VALUE"""),0.43) -> 0.43 | L73: =IFERROR(__xludf.DUMMYFUNCTION("""COMPUTED_VALUE"""),33.0) -> 33
A74: =IFERROR(__xludf.DUMMYFUNCTION("""COMPUTED_VALUE"""),74.0) -> 74 | B74: =IFERROR(__xludf.DUMMYFUNCTION("""COMPUTED_VALUE"""),45351.0) -> 45351 | C74: =IFERROR(__xludf.DUMMYFUNCTION("""COMPUTED_VALUE"""),85.0) -> 85 | D74: =IFERROR(__xludf.DUMMYFUNCTION("""COMPUTED_VALUE"""),"1.107") -> 1.107 | E74: =IFERROR(__xludf.DUMMYFUNCTION("""COMPUTED_VALUE"""),45162.0) -> 45162 | F74: =IFERROR(__xludf.DUMMYFUNCTION("""COMPUTED_VALUE"""),"Bonarda") -> Bonarda | H74: =IFERROR(__xludf.DUMMYFUNCTION("""COMPUTED_VALUE"""),9.7) -> 9.7 | I74: =IFERROR(__xludf.DUMMYFUNCTION("""COMPUTED_VALUE"""),0.4) -> 0.4 | L74: =IFERROR(__xludf.DUMMYFUNCTION("""COMPUTED_VALUE"""),32.0) -> 32
A75: =IFERROR(__xludf.DUMMYFUNCTION("""COMPUTED_VALUE"""),75.0) -> 75 | B75: =IFERROR(__xludf.DUMMYFUNCTION("""COMPUTED_VALUE"""),45352.0) -> 45352 | C75: =IFERROR(__xludf.DUMMYFUNCTION("""COMPUTED_VALUE"""),41.0) -> 41 | D75: =IFERROR(__xludf.DUMMYFUNCTION("""COMPUTED_VALUE"""),"#REF!") -> #REF! | F75: =IFERROR(__xludf.DUMMYFUNCTION("""COMPUTED_VALUE"""),"corte merlot sobre aspirant 2") -> corte merlot sobre aspirant 2 | G75: =IFERROR(__xludf.DUMMYFUNCTION("""COMPUTED_VALUE"""),12.5) -> 12.5 | H75: =IFERROR(__xludf.DUMMYFUNCTION("""COMPUTED_VALUE"""),3.91) -> 3.91 | I75: =IFERROR(__xludf.DUMMYFUNCTION("""COMPUTED_VALUE"""),0.52) -> 0.52 | J75: =IFERROR(__xludf.DUMMYFUNCTION("""COMPUTED_VALUE"""),6.12) -> 6.12 | K75: =IFERROR(__xludf.DUMMYFUNCTION("""COMPUTED_VALUE"""),3.6) -> 3.6 | L75: =IFERROR(__xludf.DUMMYFUNCTION("""COMPUTED_VALUE"""),32.0) -> 32 | M75: =IFERROR(__xludf.DUMMYFUNCTION("""COMPUTED_VALUE"""),128.0) -> 128
A76: =IFERROR(__xludf.DUMMYFUNCTION("""COMPUTED_VALUE"""),76.0) -> 76 | B76: =IFERROR(__xludf.DUMMYFUNCTION("""COMPUTED_VALUE"""),45353.0) -> 45353 | C76: =IFERROR(__xludf.DUMMYFUNCTION("""COMPUTED_VALUE"""),85.0) -> 85 | D76: =IFERROR(__xludf.DUMMYFUNCTION("""COMPUTED_VALUE"""),"1.107") -> 1.107 | E76: =IFERROR(__xludf.DUMMYFUNCTION("""COMPUTED_VALUE"""),45162.0) -> 45162 | F76: =IFERROR(__xludf.DUMMYFUNCTION("""COMPUTED_VALUE"""),"Bonarda") -> Bonarda | H76: =IFERROR(__xludf.DUMMYFUNCTION("""COMPUTED_VALUE"""),10.0) -> 10 | I76: =IFERROR(__xludf.DUMMYFUNCTION("""COMPUTED_VALUE"""),0.4) -> 0.4 | J76: =IFERROR(__xludf.DUMMYFUNCTION("""COMPUTED_VALUE"""),6.0) -> 6 | L76: =IFERROR(__xludf.DUMMYFUNCTION("""COMPUTED_VALUE"""),30.0) -> 30 | M76: =IFERROR(__xludf.DUMMYFUNCTION("""COMPUTED_VALUE"""),115.0) -> 115
A77: =IFERROR(__xludf.DUMMYFUNCTION("""COMPUTED_VALUE"""),77.0) -> 77 | B77: =IFERROR(__xludf.DUMMYFUNCTION("""COMPUTED_VALUE"""),45353.0) -> 45353 | C77: =IFERROR(__xludf.DUMMYFUNCTION("""COMPUTED_VALUE"""),80.0) -> 80 | D77: =IFERROR(__xludf.DUMMYFUNCTION("""COMPUTED_VALUE"""),"1.100") -> 1.100 | E77: =IFERROR(__xludf.DUMMYFUNCTION("""COMPUTED_VALUE"""),18657.600000000002) -> 18657.6 | F77: =IFERROR(__xludf.DUMMYFUNCTION("""COMPUTED_VALUE"""),"Syrah") -> Syrah | G77: =IFERROR(__xludf.DUMMYFUNCTION("""COMPUTED_VALUE"""),12.1) -> 12.1 | H77: =IFERROR(__xludf.DUMMYFUNCTION("""COMPUTED_VALUE"""),2.0) -> 2 | I77: =IFERROR(__xludf.DUMMYFUNCTION("""COMPUTED_VALUE"""),0.3) -> 0.3
A78: =IFERROR(__xludf.DUMMYFUNCTION("""COMPUTED_VALUE"""),78.0) -> 78 | B78: =IFERROR(__xludf.DUMMYFUNCTION("""COMPUTED_VALUE"""),45355.0) -> 45355 | C78: =IFERROR(__xludf.DUMMYFUNCTION("""COMPUTED_VALUE"""),8.0) -> 8 | D78: =IFERROR(__xludf.DUMMYFUNCTION("""COMPUTED_VALUE"""),"#REF!") -> #REF! | F78: =IFERROR(__xludf.DUMMYFUNCTION("""COMPUTED_VALUE"""),"chardonnay") -> chardonnay | L78: =IFERROR(__xludf.DUMMYFUNCTION("""COMPUTED_VALUE"""),19.0) -> 19 | M78: =IFERROR(__xludf.DUMMYFUNCTION("""COMPUTED_VALUE"""),79.0) -> 79
A79: =IFERROR(__xludf.DUMMYFUNCTION("""COMPUTED_VALUE"""),79.0) -> 79 | B79: =IFERROR(__xludf.DUMMYFUNCTION("""COMPUTED_VALUE"""),45355.0) -> 45355 | C79: =IFERROR(__xludf.DUMMYFUNCTION("""COMPUTED_VALUE"""),10.0) -> 10 | D79: =IFERROR(__xludf.DUMMYFUNCTION("""COMPUTED_VALUE"""),"1.034") -> 1.034 | E79: =IFERROR(__xludf.DUMMYFUNCTION("""COMPUTED_VALUE"""),21000.0) -> 21000 | F79: =IFERROR(__xludf.DUMMYFUNCTION("""COMPUTED_VALUE"""),"Chardonnay") -> Chardonnay | L79: =IFERROR(__xludf.DUMMYFUNCTION("""COMPUTED_VALUE"""),20.0) -> 20 | M79: =IFERROR(__xludf.DUMMYFUNCTION("""COMPUTED_VALUE"""),98.0) -> 98
A80: =IFERROR(__xludf.DUMMYFUNCTION("""COMPUTED_VALUE"""),80.0) -> 80 | B80: =IFERROR(__xludf.DUMMYFUNCTION("""COMPUTED_VALUE"""),45355.0) -> 45355 | C80: =IFERROR(__xludf.DUMMYFUNCTION("""COMPUTED_VALUE"""),30.0) -> 30 | D80: =IFERROR(__xludf.DUMMYFUNCTION("""COMPUTED_VALUE"""),"1.026") -> 1.026 | E80: =IFERROR(__xludf.DUMMYFUNCTION("""COMPUTED_VALUE"""),38800.0) -> 38800 | F80: =IFERROR(__xludf.DUMMYFUNCTION("""COMPUTED_VALUE"""),"Chardonnay") -> Chardonnay | L80: =IFERROR(__xludf.DUMMYFUNCTION("""COMPUTED_VALUE"""),28.0) -> 28 | M80: =IFERROR(__xludf.DUMMYFUNCTION("""COMPUTED_VALUE"""),100.0) -> 100
A81: =IFERROR(__xludf.DUMMYFUNCTION("""COMPUTED_VALUE"""),81.0) -> 81 | B81: =IFERROR(__xludf.DUMMYFUNCTION("""COMPUTED_VALUE"""),45355.0) -> 45355 | C81: =IFERROR(__xludf.DUMMYFUNCTION("""COMPUTED_VALUE"""),34.0) -> 34 | D81: =IFERROR(__xludf.DUMMYFUNCTION("""COMPUTED_VALUE"""),"1.054") -> 1.054 | E81: =IFERROR(__xludf.DUMMYFUNCTION("""COMPUTED_VALUE"""),39500.0) -> 39500 | F81: =IFERROR(__xludf.DUMMYFUNCTION("""COMPUTED_VALUE"""),"Chardonnay") -> Chardonnay | L81: =IFERROR(__xludf.DUMMYFUNCTION("""COMPUTED_VALUE"""),23.0) -> 23 | M81: =IFERROR(__xludf.DUMMYFUNCTION("""COMPUTED_VALUE"""),102.0) -> 102
A82: =IFERROR(__xludf.DUMMYFUNCTION("""COMPUTED_VALUE"""),82.0) -> 82 | B82: =IFERROR(__xludf.DUMMYFUNCTION("""COMPUTED_VALUE"""),45355.0) -> 45355 | C82: =IFERROR(__xludf.DUMMYFUNCTION("""COMPUTED_VALUE"""),35.0) -> 35 | D82: =IFERROR(__xludf.DUMMYFUNCTION("""COMPUTED_VALUE"""),"1.028") -> 1.028 | E82: =IFERROR(__xludf.DUMMYFUNCTION("""COMPUTED_VALUE"""),39300.0) -> 39300 | F82: =IFERROR(__xludf.DUMMYFUNCTION("""COMPUTED_VALUE"""),"Chardonnay") -> Chardonnay | L82: =IFERROR(__xludf.DUMMYFUNCTION("""COMPUTED_VALUE"""),36.0) -> 36 | M82: =IFERROR(__xludf.DUMMYFUNCTION("""COMPUTED_VALUE"""),110.0) -> 110
A83: =IFERROR(__xludf.DUMMYFUNCTION("""COMPUTED_VALUE"""),83.0) -> 83 | B83: =IFERROR(__xludf.DUMMYFUNCTION("""COMPUTED_VALUE"""),45355.0) -> 45355 | C83: =IFERROR(__xludf.DUMMYFUNCTION("""COMPUTED_VALUE"""),44.0) -> 44 | D83: =IFERROR(__xludf.DUMMYFUNCTION("""COMPUTED_VALUE"""),"1.066") -> 1.066 | E83: =IFERROR(__xludf.DUMMYFUNCTION("""COMPUTED_VALUE"""),10000.0) -> 10000 | F83: =IFERROR(__xludf.DUMMYFUNCTION("""COMPUTED_VALUE"""),"Chenin") -> Chenin | L83: =IFERROR(__xludf.DUMMYFUNCTION("""COMPUTED_VALUE"""),19.0) -> 19 | M83: =IFERROR(__xludf.DUMMYFUNCTION("""COMPUTED_VALUE"""),92.0) -> 92
A84: =IFERROR(__xludf.DUMMYFUNCTION("""COMPUTED_VALUE"""),84.0) -> 84 | B84: =IFERROR(__xludf.DUMMYFUNCTION("""COMPUTED_VALUE"""),45355.0) -> 45355 | C84: =IFERROR(__xludf.DUMMYFUNCTION("""COMPUTED_VALUE"""),46.0) -> 46 | D84: =IFERROR(__xludf.DUMMYFUNCTION("""COMPUTED_VALUE"""),"1.027") -> 1.027 | E84: =IFERROR(__xludf.DUMMYFUNCTION("""COMPUTED_VALUE"""),29000.0) -> 29000 | F84: =IFERROR(__xludf.DUMMYFUNCTION("""COMPUTED_VALUE"""),"Chardonnay") -> Chardonnay | L84: =IFERROR(__xludf.DUMMYFUNCTION("""COMPUTED_VALUE"""),25.0) -> 25 | M84: =IFERROR(__xludf.DUMMYFUNCTION("""COMPUTED_VALUE"""),96.0) -> 96
A85: =IFERROR(__xludf.DUMMYFUNCTION("""COMPUTED_VALUE"""),85.0) -> 85 | B85: =IFERROR(__xludf.DUMMYFUNCTION("""COMPUTED_VALUE"""),45355.0) -> 45355 | C85: =IFERROR(__xludf.DUMMYFUNCTION("""COMPUTED_VALUE"""),47.0) -> 47 | D85: =IFERROR(__xludf.DUMMYFUNCTION("""COMPUTED_VALUE"""),"1.029") -> 1.029 | E85: =IFERROR(__xludf.DUMMYFUNCTION("""COMPUTED_VALUE"""),20000.0) -> 20000 | F85: =IFERROR(__xludf.DUMMYFUNCTION("""COMPUTED_VALUE"""),"Chardonnay") -> Chardonnay | L85: =IFERROR(__xludf.DUMMYFUNCTION("""COMPUTED_VALUE"""),26.0) -> 26 | M85: =IFERROR(__xludf.DUMMYFUNCTION("""COMPUTED_VALUE"""),89.0) -> 89
A86: =IFERROR(__xludf.DUMMYFUNCTION("""COMPUTED_VALUE"""),86.0) -> 86 | B86: =IFERROR(__xludf.DUMMYFUNCTION("""COMPUTED_VALUE"""),45355.0) -> 45355 | C86: =IFERROR(__xludf.DUMMYFUNCTION("""COMPUTED_VALUE"""),52.0) -> 52 | D86: =IFERROR(__xludf.DUMMYFUNCTION("""COMPUTED_VALUE"""),"1.033") -> 1.033 | E86: =IFERROR(__xludf.DUMMYFUNCTION("""COMPUTED_VALUE"""),27000.0) -> 27000 | F86: =IFERROR(__xludf.DUMMYFUNCTION("""COMPUTED_VALUE"""),"Chardonnay") -> Chardonnay | L86: =IFERROR(__xludf.DUMMYFUNCTION("""COMPUTED_VALUE"""),25.0) -> 25 | M86: =IFERROR(__xludf.DUMMYFUNCTION("""COMPUTED_VALUE"""),130.0) -> 130
A87: =IFERROR(__xludf.DUMMYFUNCTION("""COMPUTED_VALUE"""),87.0) -> 87 | B87: =IFERROR(__xludf.DUMMYFUNCTION("""COMPUTED_VALUE"""),45356.0) -> 45356 | C87: =IFERROR(__xludf.DUMMYFUNCTION("""COMPUTED_VALUE"""),127.0) -> 127 | D87: =IFERROR(__xludf.DUMMYFUNCTION("""COMPUTED_VALUE"""),"1.084") -> 1.084 | E87: =IFERROR(__xludf.DUMMYFUNCTION("""COMPUTED_VALUE"""),31000.0) -> 31000 | F87: =IFERROR(__xludf.DUMMYFUNCTION("""COMPUTED_VALUE"""),"Syrah s/Asp 2") -> Syrah s/Asp 2 | G87: =IFERROR(__xludf.DUMMYFUNCTION("""COMPUTED_VALUE"""),11.7) -> 11.7 | H87: =IFERROR(__xludf.DUMMYFUNCTION("""COMPUTED_VALUE"""),10.0) -> 10 | I87: =IFERROR(__xludf.DUMMYFUNCTION("""COMPUTED_VALUE"""),0.37) -> 0.37 | J87: =IFERROR(__xludf.DUMMYFUNCTION("""COMPUTED_VALUE"""),6.7) -> 6.7 | L87: =IFERROR(__xludf.DUMMYFUNCTION("""COMPUTED_VALUE"""),32.0) -> 32
A88: =IFERROR(__xludf.DUMMYFUNCTION("""COMPUTED_VALUE"""),88.0) -> 88 | B88: =IFERROR(__xludf.DUMMYFUNCTION("""COMPUTED_VALUE"""),45356.0) -> 45356 | C88: =IFERROR(__xludf.DUMMYFUNCTION("""COMPUTED_VALUE"""),126.0) -> 126 | D88: =IFERROR(__xludf.DUMMYFUNCTION("""COMPUTED_VALUE"""),"1.084") -> 1.084 | E88: =IFERROR(__xludf.DUMMYFUNCTION("""COMPUTED_VALUE"""),31000.0) -> 31000 | F88: =IFERROR(__xludf.DUMMYFUNCTION("""COMPUTED_VALUE"""),"Syrah s/Asp 2") -> Syrah s/Asp 2 | G88: =IFERROR(__xludf.DUMMYFUNCTION("""COMPUTED_VALUE"""),11.6) -> 11.6 | H88: =IFERROR(__xludf.DUMMYFUNCTION("""COMPUTED_VALUE"""),10.0) -> 10 | I88: =IFERROR(__xludf.DUMMYFUNCTION("""COMPUTED_VALUE"""),0.38) -> 0.38 | J88: =IFERROR(__xludf.DUMMYFUNCTION("""COMPUTED_VALUE"""),6.7) -> 6.7 | L88: =IFERROR(__xludf.DUMMYFUNCTION("""COMPUTED_VALUE"""),30.0) -> 30
A89: =IFERROR(__xludf.DUMMYFUNCTION("""COMPUTED_VALUE"""),89.0) -> 89 | B89: =IFERROR(__xludf.DUMMYFUNCTION("""COMPUTED_VALUE"""),45356.0) -> 45356 | C89: =IFERROR(__xludf.DUMMYFUNCTION("""COMPUTED_VALUE"""),120.0) -> 120 | D89: =IFERROR(__xludf.DUMMYFUNCTION("""COMPUTED_VALUE"""),"1.086") -> 1.086 | E89: =IFERROR(__xludf.DUMMYFUNCTION("""COMPUTED_VALUE"""),88800.0) -> 88800 | F89: =IFERROR(__xludf.DUMMYFUNCTION("""COMPUTED_VALUE"""),"Syrah Temp s/Asp 3") -> Syrah Temp s/Asp 3 | G89: =IFERROR(__xludf.DUMMYFUNCTION("""COMPUTED_VALUE"""),12.5) -> 12.5 | H89: =IFERROR(__xludf.DUMMYFUNCTION("""COMPUTED_VALUE"""),3.75) -> 3.75 | M89: =IFERROR(__xludf.DUMMYFUNCTION("""COMPUTED_VALUE"""),96.0) -> 96
A90: =IFERROR(__xludf.DUMMYFUNCTION("""COMPUTED_VALUE"""),90.0) -> 90 | B90: =IFERROR(__xludf.DUMMYFUNCTION("""COMPUTED_VALUE"""),45357.0) -> 45357 | C90: =IFERROR(__xludf.DUMMYFUNCTION("""COMPUTED_VALUE"""),86.0) -> 86 | D90: =IFERROR(__xludf.DUMMYFUNCTION("""COMPUTED_VALUE"""),"1.109") -> 1.109 | E90: =IFERROR(__xludf.DUMMYFUNCTION("""COMPUTED_VALUE"""),49951.200000000004) -> 49951.2 | F90: =IFERROR(__xludf.DUMMYFUNCTION("""COMPUTED_VALUE"""),"Bonarda") -> Bonarda | G90: =IFERROR(__xludf.DUMMYFUNCTION("""COMPUTED_VALUE"""),12.5) -> 12.5 | H90: =IFERROR(__xludf.DUMMYFUNCTION("""COMPUTED_VALUE"""),16.0) -> 16 | I90: =IFERROR(__xludf.DUMMYFUNCTION("""COMPUTED_VALUE"""),0.4) -> 0.4
A91: =IFERROR(__xludf.DUMMYFUNCTION("""COMPUTED_VALUE"""),91.0) -> 91 | B91: =IFERROR(__xludf.DUMMYFUNCTION("""COMPUTED_VALUE"""),45357.0) -> 45357 | C91: =IFERROR(__xludf.DUMMYFUNCTION("""COMPUTED_VALUE"""),87.0) -> 87 | G91: =IFERROR(__xludf.DUMMYFUNCTION("""COMPUTED_VALUE"""),12.5) -> 12.5 | H91: =IFERROR(__xludf.DUMMYFUNCTION("""COMPUTED_VALUE"""),5.7) -> 5.7
A92: =IFERROR(__xludf.DUMMYFUNCTION("""COMPUTED_VALUE"""),92.0) -> 92 | B92: =IFERROR(__xludf.DUMMYFUNCTION("""COMPUTED_VALUE"""),45359.0) -> 45359 | C92: =IFERROR(__xludf.DUMMYFUNCTION("""COMPUTED_VALUE"""),121.0) -> 121 | D92: =IFERROR(__xludf.DUMMYFUNCTION("""COMPUTED_VALUE"""),"#REF!") -> #REF! | F92: =IFERROR(__xludf.DUMMYFUNCTION("""COMPUTED_VALUE"""),"syrah") -> syrah | G92: =IFERROR(__xludf.DUMMYFUNCTION("""COMPUTED_VALUE"""),12.5) -> 12.5 | H92: =IFERROR(__xludf.DUMMYFUNCTION("""COMPUTED_VALUE"""),2.0) -> 2 | I92: =IFERROR(__xludf.DUMMYFUNCTION("""COMPUTED_VALUE"""),0.4) -> 0.4 | J92: =IFERROR(__xludf.DUMMYFUNCTION("""COMPUTED_VALUE"""),6.0) -> 6 | L92: =IFERROR(__xludf.DUMMYFUNCTION("""COMPUTED_VALUE"""),38.0) -> 38 | M92: =IFERROR(__xludf.DUMMYFUNCTION("""COMPUTED_VALUE"""),115.0) -> 115
A93: =IFERROR(__xludf.DUMMYFUNCTION("""COMPUTED_VALUE"""),93.0) -> 93 | B93: =IFERROR(__xludf.DUMMYFUNCTION("""COMPUTED_VALUE"""),45362.0) -> 45362 | C93: =IFERROR(__xludf.DUMMYFUNCTION("""COMPUTED_VALUE"""),8.0) -> 8 | D93: =IFERROR(__xludf.DUMMYFUNCTION("""COMPUTED_VALUE"""),"1.079") -> 1.079 | E93: =IFERROR(__xludf.DUMMYFUNCTION("""COMPUTED_VALUE"""),22000.0) -> 22000 | F93: =IFERROR(__xludf.DUMMYFUNCTION("""COMPUTED_VALUE"""),"Chenin") -> Chenin | K93: =IFERROR(__xludf.DUMMYFUNCTION("""COMPUTED_VALUE"""),3.31) -> 3.31 | L93: =IFERROR(__xludf.DUMMYFUNCTION("""COMPUTED_VALUE"""),19.0) -> 19
A94: =IFERROR(__xludf.DUMMYFUNCTION("""COMPUTED_VALUE"""),94.0) -> 94 | B94: =IFERROR(__xludf.DUMMYFUNCTION("""COMPUTED_VALUE"""),45362.0) -> 45362 | C94: =IFERROR(__xludf.DUMMYFUNCTION("""COMPUTED_VALUE"""),10.0) -> 10 | D94: =IFERROR(__xludf.DUMMYFUNCTION("""COMPUTED_VALUE"""),"1.034") -> 1.034 | E94: =IFERROR(__xludf.DUMMYFUNCTION("""COMPUTED_VALUE"""),21000.0) -> 21000 | F94: =IFERROR(__xludf.DUMMYFUNCTION("""COMPUTED_VALUE"""),"Chardonnay") -> Chardonnay | K94: =IFERROR(__xludf.DUMMYFUNCTION("""COMPUTED_VALUE"""),3.37) -> 3.37 | L94: =IFERROR(__xludf.DUMMYFUNCTION("""COMPUTED_VALUE"""),28.0) -> 28
A95: =IFERROR(__xludf.DUMMYFUNCTION("""COMPUTED_VALUE"""),95.0) -> 95 | B95: =IFERROR(__xludf.DUMMYFUNCTION("""COMPUTED_VALUE"""),45362.0) -> 45362 | C95: =IFERROR(__xludf.DUMMYFUNCTION("""COMPUTED_VALUE"""),30.0) -> 30 | D95: =IFERROR(__xludf.DUMMYFUNCTION("""COMPUTED_VALUE"""),"1.026") -> 1.026 | E95: =IFERROR(__xludf.DUMMYFUNCTION("""COMPUTED_VALUE"""),38800.0) -> 38800 | F95: =IFERROR(__xludf.DUMMYFUNCTION("""COMPUTED_VALUE"""),"Chardonnay") -> Chardonnay | K95: =IFERROR(__xludf.DUMMYFUNCTION("""COMPUTED_VALUE"""),3.31) -> 3.31 | L95: =IFERROR(__xludf.DUMMYFUNCTION("""COMPUTED_VALUE"""),31.0) -> 31
A96: =IFERROR(__xludf.DUMMYFUNCTION("""COMPUTED_VALUE"""),96.0) -> 96 | B96: =IFERROR(__xludf.DUMMYFUNCTION("""COMPUTED_VALUE"""),45362.0) -> 45362 | C96: =IFERROR(__xludf.DUMMYFUNCTION("""COMPUTED_VALUE"""),34.0) -> 34 | D96: =IFERROR(__xludf.DUMMYFUNCTION("""COMPUTED_VALUE"""),"1.054") -> 1.054 | E96: =IFERROR(__xludf.DUMMYFUNCTION("""COMPUTED_VALUE"""),39500.0) -> 39500 | F96: =IFERROR(__xludf.DUMMYFUNCTION("""COMPUTED_VALUE"""),"Chardonnay") -> Chardonnay | K96: =IFERROR(__xludf.DUMMYFUNCTION("""COMPUTED_VALUE"""),3.4) -> 3.4 | L96: =IFERROR(__xludf.DUMMYFUNCTION("""COMPUTED_VALUE"""),32.0) -> 32
A97: =IFERROR(__xludf.DUMMYFUNCTION("""COMPUTED_VALUE"""),97.0) -> 97 | B97: =IFERROR(__xludf.DUMMYFUNCTION("""COMPUTED_VALUE"""),45362.0) -> 45362 | C97: =IFERROR(__xludf.DUMMYFUNCTION("""COMPUTED_VALUE"""),35.0) -> 35 | D97: =IFERROR(__xludf.DUMMYFUNCTION("""COMPUTED_VALUE"""),"1.028") -> 1.028 | E97: =IFERROR(__xludf.DUMMYFUNCTION("""COMPUTED_VALUE"""),39300.0) -> 39300 | F97: =IFERROR(__xludf.DUMMYFUNCTION("""COMPUTED_VALUE"""),"Chardonnay") -> Chardonnay | K97: =IFERROR(__xludf.DUMMYFUNCTION("""COMPUTED_VALUE"""),3.48) -> 3.48 | L97: =IFERROR(__xludf.DUMMYFUNCTION("""COMPUTED_VALUE"""),38.0) -> 38
A98: =IFERROR(__xludf.DUMMYFUNCTION("""COMPUTED_VALUE"""),98.0) -> 98 | B98: =IFERROR(__xludf.DUMMYFUNCTION("""COMPUTED_VALUE"""),45362.0) -> 45362 | C98: =IFERROR(__xludf.DUMMYFUNCTION("""COMPUTED_VALUE"""),44.0) -> 44 | D98: =IFERROR(__xludf.DUMMYFUNCTION("""COMPUTED_VALUE"""),"1.066") -> 1.066 | E98: =IFERROR(__xludf.DUMMYFUNCTION("""COMPUTED_VALUE"""),10000.0) -> 10000 | F98: =IFERROR(__xludf.DUMMYFUNCTION("""COMPUTED_VALUE"""),"Chenin") -> Chenin | K98: =IFERROR(__xludf.DUMMYFUNCTION("""COMPUTED_VALUE"""),3.22) -> 3.22 | L98: =IFERROR(__xludf.DUMMYFUNCTION("""COMPUTED_VALUE"""),28.0) -> 28
A99: =IFERROR(__xludf.DUMMYFUNCTION("""COMPUTED_VALUE"""),99.0) -> 99 | B99: =IFERROR(__xludf.DUMMYFUNCTION("""COMPUTED_VALUE"""),45362.0) -> 45362 | C99: =IFERROR(__xludf.DUMMYFUNCTION("""COMPUTED_VALUE"""),46.0) -> 46 | D99: =IFERROR(__xludf.DUMMYFUNCTION("""COMPUTED_VALUE"""),"1.027") -> 1.027 | E99: =IFERROR(__xludf.DUMMYFUNCTION("""COMPUTED_VALUE"""),29000.0) -> 29000 | F99: =IFERROR(__xludf.DUMMYFUNCTION("""COMPUTED_VALUE"""),"Chardonnay") -> Chardonnay | K99: =IFERROR(__xludf.DUMMYFUNCTION("""COMPUTED_VALUE"""),3.35) -> 3.35 | L99: =IFERROR(__xludf.DUMMYFUNCTION("""COMPUTED_VALUE"""),34.0) -> 34
A100: =IFERROR(__xludf.DUMMYFUNCTION("""COMPUTED_VALUE"""),100.0) -> 100 | B100: =IFERROR(__xludf.DUMMYFUNCTION("""COMPUTED_VALUE"""),45362.0) -> 45362 | C100: =IFERROR(__xludf.DUMMYFUNCTION("""COMPUTED_VALUE"""),47.0) -> 47 | D100: =IFERROR(__xludf.DUMMYFUNCTION("""COMPUTED_VALUE"""),"1.029") -> 1.029 | E100: =IFERROR(__xludf.DUMMYFUNCTION("""COMPUTED_VALUE"""),20000.0) -> 20000 | F100: =IFERROR(__xludf.DUMMYFUNCTION("""COMPUTED_VALUE"""),"Chardonnay") -> Chardonnay | K100: =IFERROR(__xludf.DUMMYFUNCTION("""COMPUTED_VALUE"""),3.48) -> 3.48 | L100: =IFERROR(__xludf.DUMMYFUNCTION("""COMPUTED_VALUE"""),33.0) -> 33
...

Sheet ANALISIS IMPRESION
A1: ID Analisis Impresion | B1: Fecha | C1: Observaciones | D1: Fecha Generacion
A2: 5f9ee4d1 | B2: 45757 | C2: Control Bodega
A3: b3c6eef9 | B3: 45761 | C3: Control Arqueo
A4: f9997bec | B4: 45762 | C4: Visita Victoria
A5: db8f646a | B5: 45764 | C5: Visita Victoria
A6: ffa52fc7 | B6: 45770 | C6: Control Arqueo 23/4/25
A7: c7e3a881 | B7: 45771 | C7: Visita Victoria
A8: a143bd0e | B8: 45777 | C8: Visita Victoria
A9: 3326a654 | B9: 45782 | C9: Control Arqueo 05/May
A10: 4aa90bdd | B10: 45778 | C10: PRUEBA ORDENADAS
A11: 3e08ac4a | B11: 45784 | C11: Visita Victoria
A12: b8c7d185 | B12: 45779 | C12: prueba calificacion
A13: d1ac56f6 | B13: 45787 | C13: Arqueo control 10/05/25
... A32: c4ac1700 | B32: 45881 | C32: Visita Victoria 12/08/25

Sheet CORTE TEORICO
A1: ID Corte Teorico | B1: Fecha | C1: Nombre Corte | D1: Observaciones
A2: a70dcd0c | B2: 45763 | C2: Corte prueba
A3: e48892a3 | B3: 45764 | C3: Bonarda Baudron
A4: f47d7c5e | B4: 45768 | C4: Malbec Tecnovitis | D4: Tinto con numero de Malbec
A5: 3e8987e7 | B5: 45775 | C5: Malbec Millan 233
A6: d8d61385 | B6: 45775 | C6: Malbec Millan 200k
A7: 192efacd | B7: 45777 | C7: vino con azucar
A8: 46fdd27a | B8: 45791 | C8: Chardonnay proporcional
A9: 795f8f7d | B9: 45798 | C9: corte malbec
A10: df7dc1bc | B10: 45820 | C10: Blanco Aromatico
A11: 105c2713 | B11: 45841 | C11: Malbec Corte general
A12: 76a5f033 | B12: 45848 | C12: Malbec Lopez
A13: 697c9a77 | B13: 45848 | C13: Tinto Lopez

Sheet CORTE TEORICO DETALLE
A1: ID Detalle Corte Teorico | B1: Corte Teorico | C1: Volumen al Corte | D1: Pileta | E1: Lote Pileta | F1: Varietal | G1: Volumen Actual | H1: ALC | I1: AC VOL | J1: AC T | K1: PH | L1: SO2L | M1: SO2T
A2: 56ce5437 | B2: a70dcd0c | C2: 36501 | D2: 15 | E2: f764d2d1 | F2: Malbec | G2: 36500 | H2: 12.7 | I2: 0.38 | J2: 5.4 | K2: 3.77 | L2: 14 | M2: 70
A3: b2f5b04b | B3: a70dcd0c | C3: 29001 | D3: 46 | E3: 92bbed34 | F3: Malbec Gota | G3: 29000 | H3: 13.1 | I3: 0.38 | J3: 6.97 | K3: 3.57 | L3: 35 | M3: 101
A4: 8dd4d002 | B4: a70dcd0c | C4: 25002 | D4: 121 | E4: 5c542a1f | F4: Malbec Mec | G4: 85800 | H4: 13.2 | I4: 0.4 | J4: 4.72 | K4: 3.74 | L4: 16 | M4: 51
A5: 953e3d1a | B5: a70dcd0c | C5: 34998 | D5: 25 | E5: a6d28e88 | F5: Syrah | G5: 194300 | H5: 14 | I5: 0.54 | J5: 6.1 | K5: 3.75 | L5: 33 | M5: 101
A6: 8f04eec7 | B6: e48892a3 | C6: 35801 | D6: 34 | E6: 7b6b2c2a | F6: Bonarda | G6: 35800 | H6: 13.3 | I6: 0.51 | J6: 6.67 | K6: 3.69 | L6: 26 | M6: 96
A8: c0d5ccb3 | B8: e48892a3 | C8: 30001 | D8: 127 | E8: 91eadabd | F8: Criolla s/Bonarda | G8: 30000 | H8: 14.3 | I8: 0.57 | J8: 5.55 | K8: 3.83 | L8: 11 | M8: 55
A9: 4d1f3ac3 | B9: e48892a3 | C9: 45000 | D9: 24 | E9: 7efc7da2 | F9: Bonarda C2 | G9: 186600 | H9: 12.8 | I9: 0.62 | J9: 5.1 | K9: 3.89 | L9: 30 | M9: 92
A12: e6d0a217 | B12: f47d7c5e | C12: 30000 | D12: 104 | E12: 1d042bcb | F12: Tinto | G12: 30000 | H12: 13.2 | I12: 0.42 | J12: 5.92 | K12: 3.77 | L12: 18 | M12: 77
A13: 9ab7f8cd | B13: f47d7c5e | C13: 30000 | D13: 24 | E13: 7efc7da2 | F13: Bonarda C2 | G13: 186600 | H13: 12.8 | I13: 0.62 | J13: 5.1 | K13: 3.89 | L13: 30 | M13: 92
A14: 4c5b61ec | B14: 3e8987e7 | C14: 149100 | D14: 24 | E14: 7efc7da2 | F14: Bonarda C2 | G14: 185000 | H14: 12.8 | I14: 0.62 | J14: 5.1 | K14: 3.89 | L14: 30 | M14: 92
A15: 13ec972a | B15: 3e8987e7 | C15: 37280 | D15: 118 | E15: 8ec426a5 | F15: Bonarda | G15: 155000 | H15: 13 | I15: 0.31 | J15: 6.37 | L15: 23
A16: 24c7878a | B16: 3e8987e7 | C16: 46600 | D16: 114 | E16: e53d4606 | F16: Syrah | G16: 125300 | H16: 13.5 | I16: 0.48 | J16: 6.52 | K16: 3.59 | L16: 32 | M16: 96
A17: 4b011795 | B17: d8d61385 | C17: 86000 | D17: 114 | E17: e53d4606 | F17: Syrah | G17: 125300 | H17: 13.5 | I17: 0.48 | J17: 6.52 | K17: 3.59 | L17: 32 | M17: 96
A18: c24482f3 | B18: d8d61385 | C18: 36000 | D18: 24 | E18: 7efc7da2 | F18: Bonarda C2 | G18: 185000 | H18: 12.8 | I18: 0.62 | J18: 5.1 | K18: 3.89 | L18: 30 | M18: 92
A19: 1a03a9f2 | B19: d8d61385 | C19: 50000 | D19: 118 | E19: 8ec426a5 | F19: Bonarda | G19: 155000 | H19: 13 | I19: 0.31 | J19: 6.37 | L19: 23
A20: 1806b4d4 | B20: d8d61385 | C20: 28000 | D20: 46 | E20: 92bbed34 | F20: Malbec Gota | G20: 28500 | H20: 13.1 | I20: 0.38 | J20: 6.97 | K20: 3.57 | L20: 35 | M20: 101
A21: 500eb7d5 | B21: 192efacd | C21: 19000 | D21: 66 | E21: b704cbde | F21: Malbec | G21: 19000 | H21: 13.7 | I21: 0.58 | J21: 6.12 | K21: 3.84 | L21: 19 | M21: 132
A22: 90d70ae0 | B22: 192efacd | C22: 19500 | D22: 67 | E22: de2017df | F22: Malbec | G22: 19500 | H22: 13.9 | I22: 0.57 | J22: 5.5 | K22: 3.9 | L22: 13 | M22: 96
A23: c895fca9 | B23: 192efacd | C23: 46000 | D23: 91 | E23: 028fb505 | F23: Malbec | G23: 46000 | H23: 13 | I23: 0.55 | J23: 5.1 | K23: 3.96 | L23: 12 | M23: 77
A24: b8b42c8d | B24: 192efacd | C24: 23000 | D24: 81 | E24: 3559c80c | F24: Cabernet Sauvignon | G24: 23000 | H24: 15.2 | I24: 0.59 | J24: 5 | K24: 3.85 | L24: 15 | M24: 80
A25: 68df4782 | B25: 46fdd27a | C25: 30000 | D25: 5 | E25: 593f826f | F25: Chardonnay | G25: 30000 | H25: 13.1 | I25: 0.41 | J25: 6.07 | K25: 3.21 | L25: 25 | M25: 96
A26: 5fb32084 | B26: 46fdd27a | C26: 22000 | D26: 8 | E26: 376dbee6 | F26: Chardonnay | G26: 22000 | H26: 13.2 | I26: 0.33 | J26: 5.62 | K26: 3.44 | L26: 47 | M26: 121
A27: 5efb86a8 | B27: 46fdd27a | C27: 21000 | D27: 10 | E27: f9bf68a3 | F27: Chardonnay | G27: 21000 | H27: 13.1 | I27: 0.3 | J27: 6.22 | K27: 3.31 | L27: 38 | M27: 120
A28: b1381b13 | B28: 46fdd27a | C28: 19500 | D28: 16 | E28: b5e03e7f | F28: Chardonnay | G28: 19500 | H28: 12.5 | I28: 0.25 | J28: 6.52 | K28: 3.11 | L28: 38 | M28: 122
A29: 8e19546c | B29: 46fdd27a | C29: 25700 | D29: 31 | E29: 8a7074cf | F29: Chardonnay | G29: 25700 | H29: 11.8 | I29: 0.15 | J29: 6.52 | K29: 3.35 | L29: 36 | M29: 83
A31: 7f3df0d5 | B31: 46fdd27a | C31: 24000 | D31: 40 | E31: 7c5390c8 | F31: Chardonnay | G31: 24000 | H31: 11.6 | I31: 0.25 | J31: 6.37 | K31: 3.19 | L31: 32 | M31: 93
A32: 9b0ff7c9 | B32: 46fdd27a | C32: 30000 | D32: 9 | E32: b73d8cd1 | F32: Chardonnay | G32: 30000 | H32: 11.6 | I32: 0.36 | J32: 6.3 | K32: 3.3 | L32: 35 | M32: 129
... A39: 7b3c7de2 | B39: 46fdd27a | C39: 36300 | D39: 32 | E39: a1e13111 | F39: Chardonnay (Filtra) | G39: 36300 | H39: 11.2 | I39: 0.25 | J39: 5.77 | K39: 3.23 | L39: 34 | M39: 93
A40: 368b736a | B40: 46fdd27a | C40: 25300 | D40: 33 | E40: 7def2139 | F40: Chardonnay | G40: 25300 | H40: 11.8 | J40: 7.2 | K40: 3.17 | L40: 29 | M40: 64
A42: 5245ce30 | B42: 795f8f7d | C42: 35500 | D42: 65 | E42: 91b01170 | F42: Malbec Dulc | G42: 35500 | H42: 14.2 | I42: 0.61 | J42: 6.31 | K42: 3.63 | L42: 19 | M42: 134
A43: 397f936d | B43: 795f8f7d | C43: 84000 | D43: 85 | E43: 33b26126 | F43: Malbec Dulc | G43: 84000 | H43: 14.2 | I43: 0.64 | J43: 5.77 | K43: 3.63 | L43: 16 | M43: 143
A44: 8a0d952b | B44: 795f8f7d | C44: 23000 | D44: 66 | E44: 95f6ad50 | F44: Malbec Dulc | G44: 23000 | H44: 13.9 | I44: 0.54 | J44: 6 | K44: 3.66 | L44: 19 | M44: 134
A45: 1f114664 | B45: 795f8f7d | C45: 44100 | D45: 120 | E45: 7b6d5389 | F45: Malbec Mec | G45: 88800 | H45: 13.2 | I45: 0.52 | J45: 4.57 | K45: 3.96 | L45: 37 | M45: 83
A46: 1dbc1fce | B46: df7dc1bc | C46: 26000 | D46: 48 | E46: ef198a97 | F46: Pedro Gimenez | G46: 26000 | H46: 11.8 | I46: 0.24 | J46: 5.1 | K46: 3.36 | L46: 32 | M46: 108
A47: fa5cf782 | B47: df7dc1bc | C47: 19700 | D47: 36 | E47: 0997a77d | F47: Torrontes | G47: 19700 | H47: 12.5 | I47: 0.25 | J47: 5.62 | K47: 3.35 | L47: 38 | M47: 140
A48: 8cb3fb38 | B48: df7dc1bc | C48: 19100 | D48: 44 | E48: 7ae457f1 | F48: Torrontes | G48: 19100 | H48: 13 | I48: 0.4 | J48: 5.47 | K48: 3.36 | L48: 34 | M48: 121
A49: 154a3087 | B49: 105c2713 | C49: 186600 | D49: 24 | E49: b3a40361 | F49: Malbec | G49: 186600 | H49: 14 | I49: 0.51 | J49: 6 | K49: 3.72 | L49: 36 | M49: 172
A50: 39f9aced | B50: 105c2713 | C50: 39500 | D50: 34 | E50: 08cd1438 | F50: Malbec | G50: 39500 | H50: 13.3 | I50: 0.59 | J50: 5.92 | K50: 3.5 | L50: 32 | M50: 156
A51: 3274eeea | B51: 105c2713 | C51: 81500 | D51: 83 | E51: 1031b227 | F51: Malbec | G51: 81500 | H51: 13.5 | I51: 0.62 | J51: 5.7 | K51: 3.58 | L51: 37 | M51: 153
A52: 32e703b2 | B52: 105c2713 | C52: 99600 | D52: 116 | E52: b4fedb16 | F52: Malbec | G52: 99600 | H52: 13.2 | I52: 0.55 | J52: 5.47 | K52: 3.63 | L52: 40 | M52: 180
A53: 91163fc4 | B53: 105c2713 | C53: 85800 | D53: 121 | E53: 589807bc | F53: Malbec | G53: 85800 | H53: 13.4 | I53: 0.52 | J53: 5.25 | K53: 3.65 | L53: 31 | M53: 166
... A60: c1918663 | B60: 697c9a77 | C60: 15000 | D60: 30 | E60: eec28962 | F60: Aspirant 24 | G60: 38800 | H60: 11.8 | I60: 0.35 | J60: 5.7 | K60: 3.43 | L60: 38 | M60: 102

Sheet ORDENES_TRABAJO_EXPO
A1: ID_Tarea | B1: OT Numero | C1: Fecha | D1: Tq | E1: Lot | F1: Vol Lleno | G1: Variedad | H1: Año | I1: Tarea | J1: Pta Destino | K1: Observaciones | L1: Insumo | M1: Cantidad | N1: Col1 | O1: Litros a Trasegar | P1: Pta Origen | Q1: Lleno Disponible | R1: Lts_x_cm | S1: OT Pasada a Trazabilidad | T1: Operario | U1: Completada | V1: Fecha Completada | W1: Observaciones Completada | X1: SO2L Real
A2: =IFERROR(__xludf.DUMMYFUNCTION("IMPORTRANGE(""https://docs.google.com/spreadsheets/d/15VT85t6bhNSCNmDdjRygljYmDaIXLWZpvJnrc6PO4vQ/edit?gid=1586236347#gid=1586236347"",""ORDENES_TRABAJO_EXPO!A2:R"")"),"#REF!") -> #REF!
S117: TRUE
S144: TRUE
S160: TRUE
S161: TRUE
S162: TRUE
S163: TRUE
S164: TRUE
S165: TRUE
S166: TRUE
S167: TRUE
S168: TRUE
S169: TRUE
... S303: TRUE
S310: TRUE | W310: 1000 lts
S312: TRUE | W312: 6500 lts
S314: TRUE | W314: Rectificado 2200
S317: TRUE
T318: avila | U318: TRUE
S319: TRUE | T319: avila | U319: TRUE
S322: TRUE | T322: Gil | U322: TRUE
S323: TRUE | T323: Gil | U323: TRUE
T324: Gil | U324: TRUE
T326: diaz s | U326: TRUE
T327: diaz s | U327: TRUE
S328: TRUE | T328: aracena | U328: TRUE
T329: diaz s | U329: TRUE
S330: TRUE | T330: aracena
T331: diaz s | U331: TRUE
S332: TRUE | T332: aracena | U332: TRUE
T333: diaz s | U333: TRUE
T334: diaz s
S335: TRUE | T335: aracena
T337: Gil
T338: rios | U338: TRUE
T339: aracena
S340: TRUE | T340: Gil
T341: aracena
T342: aracena
T343: Gil
S344: TRUE | T344: Gil | U344: TRUE | W344: Pedro Gimenez Flotado a pileta de fermentacion
T345: Gil
T346: Gil
T347: Gil
S348: TRUE | T348: aracena | W348: Con lo que sobra que no entra en la 46, a donde va?
S349: TRUE | T349: Gil
S350: TRUE | T350: aracena | U350: TRUE | W350: Fueron 2000 litros de prensa a tanque 103
T351: Gil
T352: Gil
T353: Gil
T354: Gil
S355: TRUE | T355: Gil | U355: TRUE
T356: Gil
T357: Gil
S358: TRUE | T358: sosa | U358: TRUE | W358: Fueron 13000 a tanque 103
S359: TRUE | T359: diaz s
T360: Gil | U360: TRUE
T361: orosco | U361: TRUE
S362: TRUE | T362: sosa | U362: TRUE | W362: 2860 lts
T363: Gil | U363: TRUE
T364: Gil | U364: TRUE
T365: Gil | U365: TRUE
T366: Gil | U366: TRUE
T367: Gil
S368: TRUE
T369: Gil | U369: TRUE
T370: Gil
T371: Gil
T372: Gil | U372: TRUE
T373: aracena | U373: TRUE
T374: Gil
S375: TRUE | T375: Gil | U375: TRUE | W375: 10000 a 66
T376: orosco | U376: TRUE
T377: orosco | U377: TRUE
T378: avila | U378: TRUE
T379: avila | U379: TRUE
T380: avila
T381: avila | U381: TRUE
T382: Gil | U382: TRUE
T383: Gil | U383: TRUE
T384: Gil | U384: TRUE
T385: Gil | U385: TRUE
T386: aracena | U386: TRUE
T387: aracena | U387: TRUE
T388: Gil
T389: aracena | U389: TRUE
T390: aracena | U390: TRUE
T391: Gil | U391: TRUE
T392: Gil | U392: TRUE
T393: Gil
T394: aracena | U394: TRUE
T395: orosco | U395: TRUE
T396: Gil | U396: TRUE
T397: Gil | U397: TRUE
T398: Gil | U398: TRUE
T399: Gil | U399: TRUE
T400: Gil | U400: TRUE
T401: Gil | U401: TRUE
T402: aracena
...

Sheet BAUME
A1: ID Baume | B1: Fecha | C1: Pileta | D1: Lote Pileta | E1: Turno | F1: Grado Bame | G1: Temperatura
A2: 1db990ef | B2: 45749 | C2: 83 | D2: becb2c75 | E2: Mañana | F2: 15
A3: baa8dcd9 | B3: 45749 | C3: 83 | D3: becb2c75 | E3: Tarde | F3: 14
A4: fee7e44e | B4: 45749 | C4: 80 | D4: b7223c27 | E4: Mañana | F4: 13
A5: 6e0538da | B5: 45749 | C5: 80 | D5: b7223c27 | E5: Mañana | F5: 13
A6: 497de2d4 | B6: 45743 | C6: 92 | D6: 857f0b04 | E6: Mañana | F6: 13
A7: 152288c3 | B7: 45743 | C7: 92 | D7: 857f0b04 | E7: Tarde | F7: 14
A8: 9be06c1d | B8: 45748 | C8: 85 | D8: 6d3395c8 | E8: Mañana | F8: 4 | G8: 28
A9: 6b754189 | B9: 45748 | C9: 85 | D9: 6d3395c8 | E9: Tarde | F9: 2.5 | G9: 29
A10: 32c6e9a1 | B10: 45749 | C10: 85 | D10: 6d3395c8 | E10: Mañana | F10: 1.5 | G10: 29
A11: 68bf52f7 | B11: 45749 | C11: 85 | D11: 6d3395c8 | E11: Tarde | F11: 0.5 | G11: 29

Sheet OT_BODEGA
A1: ID OT Bodega | B1: Fecha | C1: Pileta | D1: Tarea OT | E1: Observaciones | F1: Operario | G1: Completada | H1: Fecha Hora Completada
A2: be924618 | B2: 45740 | C2: 15 | D2: Lavado Pileta
A3: 596c3ee3 | B3: 45742 | C3: 6 | D3: Lavado Pileta | F3: sosa
A4: 7350f188 | B4: 45742 | C4: 7 | D4: Lavar canaletas

Sheet TAREAS OT
A1: ID Tarea OT
A2: Lavado Pileta
A3: Lavar canaletas
A4: Desinfeccion Mochila y Peracetico Ac.
A5: Lavado de baños, laboratorio y Comedor
A6: Lavar lagares
A7: Descargar Prensa y Decolorar
A8: Descargar Prensa y lavar
A9: Decolorar refrigerante
A10: Lavado y Desf. Bomba y caño
A11: Lavado y Desinfectado Pileta

Sheet USERS
A1: ID_User | B1: Role
A2: arlanzarini@gmail.com | B2: admin
A3: lanzarini.apps@gmail.com | B3: admin
A4: mscala70@gmail.com | B4: enologo
A5: sergiodanieldiazpancher@gmail.com | B5: capataz
A6: vickiprandina@gmail.com | B6: enologo

Sheet OPERARIOS
A1: ID Operario | B1: Nombre
A2: Gil | B2: Gil Alejandro
A3: aracena | B3: Aracena Agustin
A4: sosa | B4: Sosa Lautaro
A5: rios | B5: Rios Agustin
A6: orosco | B6: Orosco Alejandro
A7: diaz s | B7: Diaz Sergio
A8: lepez | B8: Lepez Carlos
A9: avila | B9: Avila Marcelo
A10: scala | B10: Scala Mauricio
